Workbook

Sheet Cockpit
A1: =VLOOKUP(LARGE(K$48:K$77, L1),K$48:L$77,2,FALSE) -> Denges | L1: 1
A2: =VLOOKUP(LARGE(K$48:K$77, L2),K$48:L$77,2,FALSE) -> Forel (Lavaux) | L2: 2
A3: =VLOOKUP(LARGE(K$48:K$77, L3),K$48:L$77,2,FALSE) -> Savigny | L3: 3
A4: =VLOOKUP(LARGE(K$48:K$77, L4),K$48:L$77,2,FALSE) -> Belmont-sur-Lausanne | L4: 4
A5: =VLOOKUP(LARGE(K$48:K$77, L5),K$48:L$77,2,FALSE) -> Etagnières | B5: BCV seule solution | C5: BCV seule solution | D5: öv reporting | E5: OFS | F5: Prompt IA | G5: Prompt IA | H5: Site du canton de Vaud | I5: site du canton de Vaud | L5: 5
B6: A | C6: A1 | D6: B | E6: C | F6: D | G6: E | H6: F | I6: G | L6: 6
B7: Prix maisons | C7: Prix appartements | D7: Desserte transports publiques | E7: Offre commerces | F7: Qualité de l'air | G7: Offre de place de divertissements | H7: Coefficient fiscaux communaux | I7: Disponibilité logements | L7: 7
B8: 5 | C8: 5 | D8: 7 | E8: 3 | F8: 4 | G8: 8 | H8: 5 | I8: 5 | L8: 8 | O8: Donnée | P8: Onglet du fichier | Q8: Lien
D9: 1 | L9: 9 | N9: 1 | O9: Les prix de l'immobilier par commune et par district vaudois | P9: A | Q9: https://www.bcv.ch/pointsforts/dans-le-canton/bcv-immobilier/les-prix-de-l-immobilier-par-commune-et-par-district-vaudois2.html
D10: 2 | L10: 10 | N10: 2 | O10: Liste de tous les arrêts TP Suisses par commune | P10: B | Q10: Liste des arrêts (Aujourd'hui) — Fahrplanauskunft öV Schweiz
B11: Appart. Prix bas | C11: Maison prix bas | E11: Nombre approx. d'établissements commerciaux | F11: Indice (IQA) | G11: Total places | H11: Impôt rentrée argent | I11: Total logements vacants | N11: 3 | O11: Commerces Suisses par cantons/ commune | P11: C | Q11: Recherche de la raison de commerce | Index central des raisons de commerce
B12: Appart. Prix haut | C12: Maison prix haut | N12: 4 | O12: Qualité de l'air | P12: D | Q12: https://www.lausanne.ch/portrait/carte-identite/environnement/qualite-de-l-air.html
A13: Score commune | N13: 5 | O13: Proximité parc / places de jeux / lac | P13: E
A14: Assens | B14: =(INDEX(A!A:E,MATCH(Cockpit!$A14,A!A:A,0),MATCH(B$11,INDIRECT(B$6 & "!1:1"),0))+INDEX(INDIRECT(B$6 & "!A:G"),MATCH(Cockpit!$A14,INDIRECT(B$6 & "!A:A"),0),MATCH(B$12,INDIRECT(B$6 & "!1:1"),0)))/2 -> 900000 | C14: =(INDEX(INDIRECT(C$6 & "!A:G"),MATCH(Cockpit!$A14,INDIRECT(C$6 & "!A:A"),0),MATCH(C$11,INDIRECT(C$6 & "!1:1"),0))+INDEX(INDIRECT(C$6 & "!A:G"),MATCH(Cockpit!$A14,INDIRECT(C$6 & "!A:A"),0),MATCH(C$12,INDIRECT(C$6 & "!1:1"),0)))/2 -> 1450000 | D14: =LOG((D$9*COUNTIF(B!F:F,Cockpit!A14)-COUNTIFS(B!F:F,Cockpit!A14,B!D:D,"TRAIN") + COUNTIFS(B!F:F,Cockpit!A14,B!D:D,"TRAIN")*D$10)/L14+1) -> 0.0010389825 | E14: =LOG(INDEX(INDIRECT(E$6 & "!A:G"),MATCH(Cockpit!$A14,INDIRECT(E$6 & "!A:A"),0),MATCH(E$11,INDIRECT(E$6 & "!1:1"),0))/L14+1) -> 0.017832777 | F14: =INDEX(INDIRECT(F$6 & "!A:G"),MATCH(Cockpit!$A14,INDIRECT(F$6 & "!A:A"),0),MATCH(F$11,INDIRECT(F$6 & "!1:1"),0)) -> 25 | G14: =LOG((INDEX(INDIRECT(G$6 & "!A:G"),MATCH(Cockpit!$A14,INDIRECT(G$6 & "!A:A"),0),MATCH(G$11,INDIRECT(G$6 & "!1:1"),0))/L14)+1) -> 0.00051980196 | H14: =INDEX(INDIRECT(H$6 & "!A:G"),MATCH(Cockpit!$A14,INDIRECT(H$6 & "!A:A"),0),MATCH(H$11,INDIRECT(H$6 & "!1:1"),0)) -> 70 | I14: =LOG(INDEX(INDIRECT(I$6 & "!A:G"),MATCH(Cockpit!$A14,INDIRECT(I$6 & "!A:A"),0),MATCH(I$11,INDIRECT(I$6 & "!1:1"),0))/L14+1) -> 0.025256795 | K14: Assens | L14: 1670 | N14: 6 | O14: Accueil extrafamilial et parascolaire | P14: F | Q14: https://www.bfs.admin.ch/bfs/fr/home/actualites/quoi-de-neuf.gnpdetail.2024-0551.html
A15: Belmont-sur-Lausanne | B15: =(INDEX(INDIRECT(B$6 & "!A:G"),MATCH(Cockpit!$A15,INDIRECT(B$6 & "!A:A"),0),MATCH(B$11,INDIRECT(B$6 & "!1:1"),0))+INDEX(INDIRECT(B$6 & "!A:G"),MATCH(Cockpit!$A15,INDIRECT(B$6 & "!A:A"),0),MATCH(B$12,INDIRECT(B$6 & "!1:1"),0)))/2 -> 1250000 | C15: =(INDEX(INDIRECT(C$6 & "!A:G"),MATCH(Cockpit!$A15,INDIRECT(C$6 & "!A:A"),0),MATCH(C$11,INDIRECT(C$6 & "!1:1"),0))+INDEX(INDIRECT(C$6 & "!A:G"),MATCH(Cockpit!$A15,INDIRECT(C$6 & "!A:A"),0),MATCH(C$12,INDIRECT(C$6 & "!1:1"),0)))/2 -> 1750000 | D15: =LOG((D$9*COUNTIF(B!F:F,Cockpit!A15)-COUNTIFS(B!F:F,Cockpit!A15,B!D:D,"TRAIN") + COUNTIFS(B!F:F,Cockpit!A15,B!D:D,"TRAIN")*D$10)/L15+1) -> 0.0028746685 | E15: =LOG(INDEX(INDIRECT(E$6 & "!A:G"),MATCH(Cockpit!$A15,INDIRECT(E$6 & "!A:A"),0),MATCH(E$11,INDIRECT(E$6 & "!1:1"),0))/L15+1) -> 0.026883239 | F15: =INDEX(INDIRECT(F$6 & "!A:G"),MATCH(Cockpit!$A15,INDIRECT(F$6 & "!A:A"),0),MATCH(F$11,INDIRECT(F$6 & "!1:1"),0)) -> 40 | G15: =LOG((INDEX(INDIRECT(G$6 & "!A:G"),MATCH(Cockpit!$A15,INDIRECT(G$6 & "!A:A"),0),MATCH(G$11,INDIRECT(G$6 & "!1:1"),0))/L15)+1) -> 0.00044349708 | H15: =INDEX(INDIRECT(H$6 & "!A:G"),MATCH(Cockpit!$A15,INDIRECT(H$6 & "!A:A"),0),MATCH(H$11,INDIRECT(H$6 & "!1:1"),0)) -> 72 | I15: =LOG(INDEX(INDIRECT(I$6 & "!A:G"),MATCH(Cockpit!$A15,INDIRECT(I$6 & "!A:A"),0),MATCH(I$11,INDIRECT(I$6 & "!1:1"),0))/L15+1) -> 0.00055430063 | K15: Belmont-sur-Lausanne | L15: 3915 | N15: 8 | O15: Coefficient communaux | P15: G | Q15: https://www.vd.ch/etat-droit-finances/communes/finances-communales/arretes-dimposition-et-tableaux-des-impots-communaux
A16: Bourg-en-Lavaux | B16: =(INDEX(INDIRECT(B$6 & "!A:G"),MATCH(Cockpit!$A16,INDIRECT(B$6 & "!A:A"),0),MATCH(B$11,INDIRECT(B$6 & "!1:1"),0))+INDEX(INDIRECT(B$6 & "!A:G"),MATCH(Cockpit!$A16,INDIRECT(B$6 & "!A:A"),0),MATCH(B$12,INDIRECT(B$6 & "!1:1"),0)))/2 -> 1450000 | C16: =(INDEX(INDIRECT(C$6 & "!A:G"),MATCH(Cockpit!$A16,INDIRECT(C$6 & "!A:A"),0),MATCH(C$11,INDIRECT(C$6 & "!1:1"),0))+INDEX(INDIRECT(C$6 & "!A:G"),MATCH(Cockpit!$A16,INDIRECT(C$6 & "!A:A"),0),MATCH(C$12,INDIRECT(C$6 & "!1:1"),0)))/2 -> 2150000 | D16: =LOG((D$9*COUNTIF(B!F:F,Cockpit!A16)-COUNTIFS(B!F:F,Cockpit!A16,B!D:D,"TRAIN") + COUNTIFS(B!F:F,Cockpit!A16,B!D:D,"TRAIN")*D$10)/L16+1) -> 0.0023217937 | E16: =LOG(INDEX(INDIRECT(E$6 & "!A:G"),MATCH(Cockpit!$A16,INDIRECT(E$6 & "!A:A"),0),MATCH(E$11,INDIRECT(E$6 & "!1:1"),0))/L16+1) -> 0.024198764 | F16: =INDEX(INDIRECT(F$6 & "!A:G"),MATCH(Cockpit!$A16,INDIRECT(F$6 & "!A:A"),0),MATCH(F$11,INDIRECT(F$6 & "!1:1"),0)) -> 35 | G16: =LOG((INDEX(INDIRECT(G$6 & "!A:G"),MATCH(Cockpit!$A16,INDIRECT(G$6 & "!A:A"),0),MATCH(G$11,INDIRECT(G$6 & "!1:1"),0))/L16)+1) -> 0.00048139057 | H16: =INDEX(INDIRECT(H$6 & "!A:G"),MATCH(Cockpit!$A16,INDIRECT(H$6 & "!A:A"),0),MATCH(H$11,INDIRECT(H$6 & "!1:1"),0)) -> 62.5 | I16: =LOG(INDEX(INDIRECT(I$6 & "!A:G"),MATCH(Cockpit!$A16,INDIRECT(I$6 & "!A:A"),0),MATCH(I$11,INDIRECT(I$6 & "!1:1"),0))/L16+1) -> 0.00056157048 | K16: Bourg-en-Lavaux | L16: 5410 | N16: 9 | O16: Logements disponibles par communes | P16: H | Q16: Communes_Logvac.xlsx
A17: Bremblens | B17: =(INDEX(INDIRECT(B$6 & "!A:G"),MATCH(Cockpit!$A17,INDIRECT(B$6 & "!A:A"),0),MATCH(B$11,INDIRECT(B$6 & "!1:1"),0))+INDEX(INDIRECT(B$6 & "!A:G"),MATCH(Cockpit!$A17,INDIRECT(B$6 & "!A:A"),0),MATCH(B$12,INDIRECT(B$6 & "!1:1"),0)))/2 -> 1150000 | C17: =(INDEX(INDIRECT(C$6 & "!A:G"),MATCH(Cockpit!$A17,INDIRECT(C$6 & "!A:A"),0),MATCH(C$11,INDIRECT(C$6 & "!1:1"),0))+INDEX(INDIRECT(C$6 & "!A:G"),MATCH(Cockpit!$A17,INDIRECT(C$6 & "!A:A"),0),MATCH(C$12,INDIRECT(C$6 & "!1:1"),0)))/2 -> 1650000 | D17: =LOG((D$9*COUNTIF(B!F:F,Cockpit!A17)-COUNTIFS(B!F:F,Cockpit!A17,B!D:D,"TRAIN") + COUNTIFS(B!F:F,Cockpit!A17,B!D:D,"TRAIN")*D$10)/L17+1) -> 0.00072322162 | E17: =LOG(INDEX(INDIRECT(E$6 & "!A:G"),MATCH(Cockpit!$A17,INDIRECT(E$6 & "!A:A"),0),MATCH(E$11,INDIRECT(E$6 & "!1:1"),0))/L17+1) -> 0.024622475 | F17: =INDEX(INDIRECT(F$6 & "!A:G"),MATCH(Cockpit!$A17,INDIRECT(F$6 & "!A:A"),0),MATCH(F$11,INDIRECT(F$6 & "!1:1"),0)) -> 25 | G17: =LOG((INDEX(INDIRECT(G$6 & "!A:G"),MATCH(Cockpit!$A17,INDIRECT(G$6 & "!A:A"),0),MATCH(G$11,INDIRECT(G$6 & "!1:1"),0))/L17)+1) -> 0.0014452409 | H17: =INDEX(INDIRECT(H$6 & "!A:G"),MATCH(Cockpit!$A17,INDIRECT(H$6 & "!A:A"),0),MATCH(H$11,INDIRECT(H$6 & "!1:1"),0)) -> 68 | I17: =LOG(INDEX(INDIRECT(I$6 & "!A:G"),MATCH(Cockpit!$A17,INDIRECT(I$6 & "!A:A"),0),MATCH(I$11,INDIRECT(I$6 & "!1:1"),0))/L17+1) -> 0.00072322162 | K17: Bremblens | L17: 600
A18: Bussigny | B18: =(INDEX(INDIRECT(B$6 & "!A:G"),MATCH(Cockpit!$A18,INDIRECT(B$6 & "!A:A"),0),MATCH(B$11,INDIRECT(B$6 & "!1:1"),0))+INDEX(INDIRECT(B$6 & "!A:G"),MATCH(Cockpit!$A18,INDIRECT(B$6 & "!A:A"),0),MATCH(B$12,INDIRECT(B$6 & "!1:1"),0)))/2 -> 1250000 | C18: =(INDEX(INDIRECT(C$6 & "!A:G"),MATCH(Cockpit!$A18,INDIRECT(C$6 & "!A:A"),0),MATCH(C$11,INDIRECT(C$6 & "!1:1"),0))+INDEX(INDIRECT(C$6 & "!A:G"),MATCH(Cockpit!$A18,INDIRECT(C$6 & "!A:A"),0),MATCH(C$12,INDIRECT(C$6 & "!1:1"),0)))/2 -> 1650000 | D18: =LOG((D$9*COUNTIF(B!F:F,Cockpit!A18)-COUNTIFS(B!F:F,Cockpit!A18,B!D:D,"TRAIN") + COUNTIFS(B!F:F,Cockpit!A18,B!D:D,"TRAIN")*D$10)/L18+1) -> 0.0010069088 | E18: =LOG(INDEX(INDIRECT(E$6 & "!A:G"),MATCH(Cockpit!$A18,INDIRECT(E$6 & "!A:A"),0),MATCH(E$11,INDIRECT(E$6 & "!1:1"),0))/L18+1) -> 0.021843079 | F18: =INDEX(INDIRECT(F$6 & "!A:G"),MATCH(Cockpit!$A18,INDIRECT(F$6 & "!A:A"),0),MATCH(F$11,INDIRECT(F$6 & "!1:1"),0)) -> 35 | G18: =LOG((INDEX(INDIRECT(G$6 & "!A:G"),MATCH(Cockpit!$A18,INDIRECT(G$6 & "!A:A"),0),MATCH(G$11,INDIRECT(G$6 & "!1:1"),0))/L18)+1) -> 0.00048509936 | H18: =INDEX(INDIRECT(H$6 & "!A:G"),MATCH(Cockpit!$A18,INDIRECT(H$6 & "!A:A"),0),MATCH(H$11,INDIRECT(H$6 & "!1:1"),0)) -> 62.5 | I18: =LOG(INDEX(INDIRECT(I$6 & "!A:G"),MATCH(Cockpit!$A18,INDIRECT(I$6 & "!A:A"),0),MATCH(I$11,INDIRECT(I$6 & "!1:1"),0))/L18+1) -> 0.00063425175 | K18: Bussigny | L18: 11632
A19: Chavannes-près-Renens | B19: =(INDEX(INDIRECT(B$6 & "!A:G"),MATCH(Cockpit!$A19,INDIRECT(B$6 & "!A:A"),0),MATCH(B$11,INDIRECT(B$6 & "!1:1"),0))+INDEX(INDIRECT(B$6 & "!A:G"),MATCH(Cockpit!$A19,INDIRECT(B$6 & "!A:A"),0),MATCH(B$12,INDIRECT(B$6 & "!1:1"),0)))/2 -> 1350000 | C19: =(INDEX(INDIRECT(C$6 & "!A:G"),MATCH(Cockpit!$A19,INDIRECT(C$6 & "!A:A"),0),MATCH(C$11,INDIRECT(C$6 & "!1:1"),0))+INDEX(INDIRECT(C$6 & "!A:G"),MATCH(Cockpit!$A19,INDIRECT(C$6 & "!A:A"),0),MATCH(C$12,INDIRECT(C$6 & "!1:1"),0)))/2 -> 1550000 | D19: =LOG((D$9*COUNTIF(B!F:F,Cockpit!A19)-COUNTIFS(B!F:F,Cockpit!A19,B!D:D,"TRAIN") + COUNTIFS(B!F:F,Cockpit!A19,B!D:D,"TRAIN")*D$10)/L19+1) -> 0.00079907011 | E19: =LOG(INDEX(INDIRECT(E$6 & "!A:G"),MATCH(Cockpit!$A19,INDIRECT(E$6 & "!A:A"),0),MATCH(E$11,INDIRECT(E$6 & "!1:1"),0))/L19+1) -> 0.020820978 | F19: =INDEX(INDIRECT(F$6 & "!A:G"),MATCH(Cockpit!$A19,INDIRECT(F$6 & "!A:A"),0),MATCH(F$11,INDIRECT(F$6 & "!1:1"),0)) -> 35 | G19: =LOG((INDEX(INDIRECT(G$6 & "!A:G"),MATCH(Cockpit!$A19,INDIRECT(G$6 & "!A:A"),0),MATCH(G$11,INDIRECT(G$6 & "!1:1"),0))/L19)+1) -> 0.00039971883 | H19: =INDEX(INDIRECT(H$6 & "!A:G"),MATCH(Cockpit!$A19,INDIRECT(H$6 & "!A:A"),0),MATCH(H$11,INDIRECT(H$6 & "!1:1"),0)) -> 77.5 | I19: =LOG(INDEX(INDIRECT(I$6 & "!A:G"),MATCH(Cockpit!$A19,INDIRECT(I$6 & "!A:A"),0),MATCH(I$11,INDIRECT(I$6 & "!1:1"),0))/L19+1) -> 0.00031092421 | K19: Chavannes-près-Renens | L19: 9774
A20: Cheseaux-sur-Lausanne | B20: =(INDEX(INDIRECT(B$6 & "!A:G"),MATCH(Cockpit!$A20,INDIRECT(B$6 & "!A:A"),0),MATCH(B$11,INDIRECT(B$6 & "!1:1"),0))+INDEX(INDIRECT(B$6 & "!A:G"),MATCH(Cockpit!$A20,INDIRECT(B$6 & "!A:A"),0),MATCH(B$12,INDIRECT(B$6 & "!1:1"),0)))/2 -> 1150000 | C20: =(INDEX(INDIRECT(C$6 & "!A:G"),MATCH(Cockpit!$A20,INDIRECT(C$6 & "!A:A"),0),MATCH(C$11,INDIRECT(C$6 & "!1:1"),0))+INDEX(INDIRECT(C$6 & "!A:G"),MATCH(Cockpit!$A20,INDIRECT(C$6 & "!A:A"),0),MATCH(C$12,INDIRECT(C$6 & "!1:1"),0)))/2 -> 1550000 | D20: =LOG((D$9*COUNTIF(B!F:F,Cockpit!A20)-COUNTIFS(B!F:F,Cockpit!A20,B!D:D,"TRAIN") + COUNTIFS(B!F:F,Cockpit!A20,B!D:D,"TRAIN")*D$10)/L20+1) -> 0.00062675227 | E20: =LOG(INDEX(INDIRECT(E$6 & "!A:G"),MATCH(Cockpit!$A20,INDIRECT(E$6 & "!A:A"),0),MATCH(E$11,INDIRECT(E$6 & "!1:1"),0))/L20+1) -> 0.024390298 | F20: =INDEX(INDIRECT(F$6 & "!A:G"),MATCH(Cockpit!$A20,INDIRECT(F$6 & "!A:A"),0),MATCH(F$11,INDIRECT(F$6 & "!1:1"),0)) -> 20 | G20: =LOG((INDEX(INDIRECT(G$6 & "!A:G"),MATCH(Cockpit!$A20,INDIRECT(G$6 & "!A:A"),0),MATCH(G$11,INDIRECT(G$6 & "!1:1"),0))/L20)+1) -> 0.00062675227 | H20: =INDEX(INDIRECT(H$6 & "!A:G"),MATCH(Cockpit!$A20,INDIRECT(H$6 & "!A:A"),0),MATCH(H$11,INDIRECT(H$6 & "!1:1"),0)) -> 73 | I20: =LOG(INDEX(INDIRECT(I$6 & "!A:G"),MATCH(Cockpit!$A20,INDIRECT(I$6 & "!A:A"),0),MATCH(I$11,INDIRECT(I$6 & "!1:1"),0))/L20+1) -> 0.00071621452 | K20: Cheseaux-sur-Lausanne | L20: 4847
A21: Crissier | B21: =(INDEX(INDIRECT(B$6 & "!A:G"),MATCH(Cockpit!$A21,INDIRECT(B$6 & "!A:A"),0),MATCH(B$11,INDIRECT(B$6 & "!1:1"),0))+INDEX(INDIRECT(B$6 & "!A:G"),MATCH(Cockpit!$A21,INDIRECT(B$6 & "!A:A"),0),MATCH(B$12,INDIRECT(B$6 & "!1:1"),0)))/2 -> 1250000 | C21: =(INDEX(INDIRECT(C$6 & "!A:G"),MATCH(Cockpit!$A21,INDIRECT(C$6 & "!A:A"),0),MATCH(C$11,INDIRECT(C$6 & "!1:1"),0))+INDEX(INDIRECT(C$6 & "!A:G"),MATCH(Cockpit!$A21,INDIRECT(C$6 & "!A:A"),0),MATCH(C$12,INDIRECT(C$6 & "!1:1"),0)))/2 -> 1650000 | D21: =LOG((D$9*COUNTIF(B!F:F,Cockpit!A21)-COUNTIFS(B!F:F,Cockpit!A21,B!D:D,"TRAIN") + COUNTIFS(B!F:F,Cockpit!A21,B!D:D,"TRAIN")*D$10)/L21+1) -> 0.00077222379 | E21: =LOG(INDEX(INDIRECT(E$6 & "!A:G"),MATCH(Cockpit!$A21,INDIRECT(E$6 & "!A:A"),0),MATCH(E$11,INDIRECT(E$6 & "!1:1"),0))/L21+1) -> 0.021816473 | F21: =INDEX(INDIRECT(F$6 & "!A:G"),MATCH(Cockpit!$A21,INDIRECT(F$6 & "!A:A"),0),MATCH(F$11,INDIRECT(F$6 & "!1:1"),0)) -> 35 | G21: =LOG((INDEX(INDIRECT(G$6 & "!A:G"),MATCH(Cockpit!$A21,INDIRECT(G$6 & "!A:A"),0),MATCH(G$11,INDIRECT(G$6 & "!1:1"),0))/L21)+1) -> 0.00060976443 | H21: =INDEX(INDIRECT(H$6 & "!A:G"),MATCH(Cockpit!$A21,INDIRECT(H$6 & "!A:A"),0),MATCH(H$11,INDIRECT(H$6 & "!1:1"),0)) -> 63.5 | I21: =LOG(INDEX(INDIRECT(I$6 & "!A:G"),MATCH(Cockpit!$A21,INDIRECT(I$6 & "!A:A"),0),MATCH(I$11,INDIRECT(I$6 & "!1:1"),0))/L21+1) -> 0.0012592376 | K21: Crissier | L21: 10676
A22: Cugy | B22: =(INDEX(INDIRECT(B$6 & "!A:G"),MATCH(Cockpit!$A22,INDIRECT(B$6 & "!A:A"),0),MATCH(B$11,INDIRECT(B$6 & "!1:1"),0))+INDEX(INDIRECT(B$6 & "!A:G"),MATCH(Cockpit!$A22,INDIRECT(B$6 & "!A:A"),0),MATCH(B$12,INDIRECT(B$6 & "!1:1"),0)))/2 -> 950000 | C22: =(INDEX(INDIRECT(C$6 & "!A:G"),MATCH(Cockpit!$A22,INDIRECT(C$6 & "!A:A"),0),MATCH(C$11,INDIRECT(C$6 & "!1:1"),0))+INDEX(INDIRECT(C$6 & "!A:G"),MATCH(Cockpit!$A22,INDIRECT(C$6 & "!A:A"),0),MATCH(C$12,INDIRECT(C$6 & "!1:1"),0)))/2 -> 1550000 | D22: =LOG((D$9*COUNTIF(B!F:F,Cockpit!A22)-COUNTIFS(B!F:F,Cockpit!A22,B!D:D,"TRAIN") + COUNTIFS(B!F:F,Cockpit!A22,B!D:D,"TRAIN")*D$10)/L22+1) -> 0 | E22: =LOG(INDEX(INDIRECT(E$6 & "!A:G"),MATCH(Cockpit!$A22,INDIRECT(E$6 & "!A:A"),0),MATCH(E$11,INDIRECT(E$6 & "!1:1"),0))/L22+1) -> 0.027180578 | F22: =INDEX(INDIRECT(F$6 & "!A:G"),MATCH(Cockpit!$A22,INDIRECT(F$6 & "!A:A"),0),MATCH(F$11,INDIRECT(F$6 & "!1:1"),0)) -> 30 | G22: =LOG((INDEX(INDIRECT(G$6 & "!A:G"),MATCH(Cockpit!$A22,INDIRECT(G$6 & "!A:A"),0),MATCH(G$11,INDIRECT(G$6 & "!1:1"),0))/L22)+1) -> 0.00062286778 | H22: =INDEX(INDIRECT(H$6 & "!A:G"),MATCH(Cockpit!$A22,INDIRECT(H$6 & "!A:A"),0),MATCH(H$11,INDIRECT(H$6 & "!1:1"),0)) -> 76 | I22: =LOG(INDEX(INDIRECT(I$6 & "!A:G"),MATCH(Cockpit!$A22,INDIRECT(I$6 & "!A:A"),0),MATCH(I$11,INDIRECT(I$6 & "!1:1"),0))/L22+1) -> 0.00031154555 | K22: Cugy | L22: 2787
A23: Denges | B23: =(INDEX(INDIRECT(B$6 & "!A:G"),MATCH(Cockpit!$A23,INDIRECT(B$6 & "!A:A"),0),MATCH(B$11,INDIRECT(B$6 & "!1:1"),0))+INDEX(INDIRECT(B$6 & "!A:G"),MATCH(Cockpit!$A23,INDIRECT(B$6 & "!A:A"),0),MATCH(B$12,INDIRECT(B$6 & "!1:1"),0)))/2 -> 1350000 | C23: =(INDEX(INDIRECT(C$6 & "!A:G"),MATCH(Cockpit!$A23,INDIRECT(C$6 & "!A:A"),0),MATCH(C$11,INDIRECT(C$6 & "!1:1"),0))+INDEX(INDIRECT(C$6 & "!A:G"),MATCH(Cockpit!$A23,INDIRECT(C$6 & "!A:A"),0),MATCH(C$12,INDIRECT(C$6 & "!1:1"),0)))/2 -> 1950000 | D23: =LOG((D$9*COUNTIF(B!F:F,Cockpit!A23)-COUNTIFS(B!F:F,Cockpit!A23,B!D:D,"TRAIN") + COUNTIFS(B!F:F,Cockpit!A23,B!D:D,"TRAIN")*D$10)/L23+1) -> 0.0031780768 | E23: =LOG(INDEX(INDIRECT(E$6 & "!A:G"),MATCH(Cockpit!$A23,INDIRECT(E$6 & "!A:A"),0),MATCH(E$11,INDIRECT(E$6 & "!1:1"),0))/L23+1) -> 0.033060101 | F23: =INDEX(INDIRECT(F$6 & "!A:G"),MATCH(Cockpit!$A23,INDIRECT(F$6 & "!A:A"),0),MATCH(F$11,INDIRECT(F$6 & "!1:1"),0)) -> 29 | G23: =LOG((INDEX(INDIRECT(G$6 & "!A:G"),MATCH(Cockpit!$A23,INDIRECT(G$6 & "!A:A"),0),MATCH(G$11,INDIRECT(G$6 & "!1:1"),0))/L23)+1) -> 0.00098034913 | H23: =INDEX(INDIRECT(H$6 & "!A:G"),MATCH(Cockpit!$A23,INDIRECT(H$6 & "!A:A"),0),MATCH(H$11,INDIRECT(H$6 & "!1:1"),0)) -> 62 | I23: =LOG(INDEX(INDIRECT(I$6 & "!A:G"),MATCH(Cockpit!$A23,INDIRECT(I$6 & "!A:A"),0),MATCH(I$11,INDIRECT(I$6 & "!1:1"),0))/L23+1) -> 0.0022026817 | K23: Denges | L23: 1770
A24: Echandens | B24: =(INDEX(INDIRECT(B$6 & "!A:G"),MATCH(Cockpit!$A24,INDIRECT(B$6 & "!A:A"),0),MATCH(B$11,INDIRECT(B$6 & "!1:1"),0))+INDEX(INDIRECT(B$6 & "!A:G"),MATCH(Cockpit!$A24,INDIRECT(B$6 & "!A:A"),0),MATCH(B$12,INDIRECT(B$6 & "!1:1"),0)))/2 -> 1450000 | C24: =(INDEX(INDIRECT(C$6 & "!A:G"),MATCH(Cockpit!$A24,INDIRECT(C$6 & "!A:A"),0),MATCH(C$11,INDIRECT(C$6 & "!1:1"),0))+INDEX(INDIRECT(C$6 & "!A:G"),MATCH(Cockpit!$A24,INDIRECT(C$6 & "!A:A"),0),MATCH(C$12,INDIRECT(C$6 & "!1:1"),0)))/2 -> 1950000 | D24: =LOG((D$9*COUNTIF(B!F:F,Cockpit!A24)-COUNTIFS(B!F:F,Cockpit!A24,B!D:D,"TRAIN") + COUNTIFS(B!F:F,Cockpit!A24,B!D:D,"TRAIN")*D$10)/L24+1) -> 0.0011984678 | E24: =LOG(INDEX(INDIRECT(E$6 & "!A:G"),MATCH(Cockpit!$A24,INDIRECT(E$6 & "!A:A"),0),MATCH(E$11,INDIRECT(E$6 & "!1:1"),0))/L24+1) -> 0.031809483 | F24: =INDEX(INDIRECT(F$6 & "!A:G"),MATCH(Cockpit!$A24,INDIRECT(F$6 & "!A:A"),0),MATCH(F$11,INDIRECT(F$6 & "!1:1"),0)) -> 30 | G24: =LOG((INDEX(INDIRECT(G$6 & "!A:G"),MATCH(Cockpit!$A24,INDIRECT(G$6 & "!A:A"),0),MATCH(G$11,INDIRECT(G$6 & "!1:1"),0))/L24)+1) -> 0.00074942984 | H24: =INDEX(INDIRECT(H$6 & "!A:G"),MATCH(Cockpit!$A24,INDIRECT(H$6 & "!A:A"),0),MATCH(H$11,INDIRECT(H$6 & "!1:1"),0)) -> 60.5 | I24: =LOG(INDEX(INDIRECT(I$6 & "!A:G"),MATCH(Cockpit!$A24,INDIRECT(I$6 & "!A:A"),0),MATCH(I$11,INDIRECT(I$6 & "!1:1"),0))/L24+1) -> 0.00089916074 | K24: Echandens | L24: 2895
A25: Ecublens | B25: =(INDEX(INDIRECT(B$6 & "!A:G"),MATCH(Cockpit!$A25,INDIRECT(B$6 & "!A:A"),0),MATCH(B$11,INDIRECT(B$6 & "!1:1"),0))+INDEX(INDIRECT(B$6 & "!A:G"),MATCH(Cockpit!$A25,INDIRECT(B$6 & "!A:A"),0),MATCH(B$12,INDIRECT(B$6 & "!1:1"),0)))/2 -> 1250000 | C25: =(INDEX(INDIRECT(C$6 & "!A:G"),MATCH(Cockpit!$A25,INDIRECT(C$6 & "!A:A"),0),MATCH(C$11,INDIRECT(C$6 & "!1:1"),0))+INDEX(INDIRECT(C$6 & "!A:G"),MATCH(Cockpit!$A25,INDIRECT(C$6 & "!A:A"),0),MATCH(C$12,INDIRECT(C$6 & "!1:1"),0)))/2 -> 2150000 | D25: =LOG((D$9*COUNTIF(B!F:F,Cockpit!A25)-COUNTIFS(B!F:F,Cockpit!A25,B!D:D,"TRAIN") + COUNTIFS(B!F:F,Cockpit!A25,B!D:D,"TRAIN")*D$10)/L25+1) -> 0 | E25: =LOG(INDEX(INDIRECT(E$6 & "!A:G"),MATCH(Cockpit!$A25,INDIRECT(E$6 & "!A:A"),0),MATCH(E$11,INDIRECT(E$6 & "!1:1"),0))/L25+1) -> 0.014697258 | F25: =INDEX(INDIRECT(F$6 & "!A:G"),MATCH(Cockpit!$A25,INDIRECT(F$6 & "!A:A"),0),MATCH(F$11,INDIRECT(F$6 & "!1:1"),0)) -> 35 | G25: =LOG((INDEX(INDIRECT(G$6 & "!A:G"),MATCH(Cockpit!$A25,INDIRECT(G$6 & "!A:A"),0),MATCH(G$11,INDIRECT(G$6 & "!1:1"),0))/L25)+1) -> 0.00058455858 | H25: =INDEX(INDIRECT(H$6 & "!A:G"),MATCH(Cockpit!$A25,INDIRECT(H$6 & "!A:A"),0),MATCH(H$11,INDIRECT(H$6 & "!1:1"),0)) -> 62.5 | I25: =LOG(INDEX(INDIRECT(I$6 & "!A:G"),MATCH(Cockpit!$A25,INDIRECT(I$6 & "!A:A"),0),MATCH(I$11,INDIRECT(I$6 & "!1:1"),0))/L25+1) -> 0.00165421 | K25: Ecublens | L25: 13364
A26: Epalinges | B26: =(INDEX(INDIRECT(B$6 & "!A:G"),MATCH(Cockpit!$A26,INDIRECT(B$6 & "!A:A"),0),MATCH(B$11,INDIRECT(B$6 & "!1:1"),0))+INDEX(INDIRECT(B$6 & "!A:G"),MATCH(Cockpit!$A26,INDIRECT(B$6 & "!A:A"),0),MATCH(B$12,INDIRECT(B$6 & "!1:1"),0)))/2 -> 1350000 | C26: =(INDEX(INDIRECT(C$6 & "!A:G"),MATCH(Cockpit!$A26,INDIRECT(C$6 & "!A:A"),0),MATCH(C$11,INDIRECT(C$6 & "!1:1"),0))+INDEX(INDIRECT(C$6 & "!A:G"),MATCH(Cockpit!$A26,INDIRECT(C$6 & "!A:A"),0),MATCH(C$12,INDIRECT(C$6 & "!1:1"),0)))/2 -> 1850000 | D26: =LOG((D$9*COUNTIF(B!F:F,Cockpit!A26)-COUNTIFS(B!F:F,Cockpit!A26,B!D:D,"TRAIN") + COUNTIFS(B!F:F,Cockpit!A26,B!D:D,"TRAIN")*D$10)/L26+1) -> 0.0010510308 | E26: =LOG(INDEX(INDIRECT(E$6 & "!A:G"),MATCH(Cockpit!$A26,INDIRECT(E$6 & "!A:A"),0),MATCH(E$11,INDIRECT(E$6 & "!1:1"),0))/L26+1) -> 0.031698974 | F26: =INDEX(INDIRECT(F$6 & "!A:G"),MATCH(Cockpit!$A26,INDIRECT(F$6 & "!A:A"),0),MATCH(F$11,INDIRECT(F$6 & "!1:1"),0)) -> 30 | G26: =LOG((INDEX(INDIRECT(G$6 & "!A:G"),MATCH(Cockpit!$A26,INDIRECT(G$6 & "!A:A"),0),MATCH(G$11,INDIRECT(G$6 & "!1:1"),0))/L26)+1) -> 0.00052583336 | H26: =INDEX(INDIRECT(H$6 & "!A:G"),MATCH(Cockpit!$A26,INDIRECT(H$6 & "!A:A"),0),MATCH(H$11,INDIRECT(H$6 & "!1:1"),0)) -> 64.5 | I26: =LOG(INDEX(INDIRECT(I$6 & "!A:G"),MATCH(Cockpit!$A26,INDIRECT(I$6 & "!A:A"),0),MATCH(I$11,INDIRECT(I$6 & "!1:1"),0))/L26+1) -> 0.0032325428 | K26: Epalinges | L26: 9905
A27: Etagnières | B27: =(INDEX(INDIRECT(B$6 & "!A:G"),MATCH(Cockpit!$A27,INDIRECT(B$6 & "!A:A"),0),MATCH(B$11,INDIRECT(B$6 & "!1:1"),0))+INDEX(INDIRECT(B$6 & "!A:G"),MATCH(Cockpit!$A27,INDIRECT(B$6 & "!A:A"),0),MATCH(B$12,INDIRECT(B$6 & "!1:1"),0)))/2 -> 950000 | C27: =(INDEX(INDIRECT(C$6 & "!A:G"),MATCH(Cockpit!$A27,INDIRECT(C$6 & "!A:A"),0),MATCH(C$11,INDIRECT(C$6 & "!1:1"),0))+INDEX(INDIRECT(C$6 & "!A:G"),MATCH(Cockpit!$A27,INDIRECT(C$6 & "!A:A"),0),MATCH(C$12,INDIRECT(C$6 & "!1:1"),0)))/2 -> 1550000 | D27: =LOG((D$9*COUNTIF(B!F:F,Cockpit!A27)-COUNTIFS(B!F:F,Cockpit!A27,B!D:D,"TRAIN") + COUNTIFS(B!F:F,Cockpit!A27,B!D:D,"TRAIN")*D$10)/L27+1) -> 0.0018599364 | E27: =LOG(INDEX(INDIRECT(E$6 & "!A:G"),MATCH(Cockpit!$A27,INDIRECT(E$6 & "!A:A"),0),MATCH(E$11,INDIRECT(E$6 & "!1:1"),0))/L27+1) -> 0.039184259 | F27: =INDEX(INDIRECT(F$6 & "!A:G"),MATCH(Cockpit!$A27,INDIRECT(F$6 & "!A:A"),0),MATCH(F$11,INDIRECT(F$6 & "!1:1"),0)) -> 22 | G27: =LOG((INDEX(INDIRECT(G$6 & "!A:G"),MATCH(Cockpit!$A27,INDIRECT(G$6 & "!A:A"),0),MATCH(G$11,INDIRECT(G$6 & "!1:1"),0))/L27)+1) -> 0.0011169174 | H27: =INDEX(INDIRECT(H$6 & "!A:G"),MATCH(Cockpit!$A27,INDIRECT(H$6 & "!A:A"),0),MATCH(H$11,INDIRECT(H$6 & "!1:1"),0)) -> 73 | I27: =LOG(INDEX(INDIRECT(I$6 & "!A:G"),MATCH(Cockpit!$A27,INDIRECT(I$6 & "!A:A"),0),MATCH(I$11,INDIRECT(I$6 & "!1:1"),0))/L27+1) -> 0.0022309697 | K27: Etagnières | L27: 1165
A28: Forel (Lavaux) | B28: =(INDEX(INDIRECT(B$6 & "!A:G"),MATCH(Cockpit!$A28,INDIRECT(B$6 & "!A:A"),0),MATCH(B$11,INDIRECT(B$6 & "!1:1"),0))+INDEX(INDIRECT(B$6 & "!A:G"),MATCH(Cockpit!$A28,INDIRECT(B$6 & "!A:A"),0),MATCH(B$12,INDIRECT(B$6 & "!1:1"),0)))/2 -> 850000 | C28: =(INDEX(INDIRECT(C$6 & "!A:G"),MATCH(Cockpit!$A28,INDIRECT(C$6 & "!A:A"),0),MATCH(C$11,INDIRECT(C$6 & "!1:1"),0))+INDEX(INDIRECT(C$6 & "!A:G"),MATCH(Cockpit!$A28,INDIRECT(C$6 & "!A:A"),0),MATCH(C$12,INDIRECT(C$6 & "!1:1"),0)))/2 -> 1350000 | D28: =LOG((D$9*COUNTIF(B!F:F,Cockpit!A28)-COUNTIFS(B!F:F,Cockpit!A28,B!D:D,"TRAIN") + COUNTIFS(B!F:F,Cockpit!A28,B!D:D,"TRAIN")*D$10)/L28+1) -> 0.0022060723 | E28: =LOG(INDEX(INDIRECT(E$6 & "!A:G"),MATCH(Cockpit!$A28,INDIRECT(E$6 & "!A:A"),0),MATCH(E$11,INDIRECT(E$6 & "!1:1"),0))/L28+1) -> 0.025381731 | F28: =INDEX(INDIRECT(F$6 & "!A:G"),MATCH(Cockpit!$A28,INDIRECT(F$6 & "!A:A"),0),MATCH(F$11,INDIRECT(F$6 & "!1:1"),0)) -> 30 | G28: =LOG((INDEX(INDIRECT(G$6 & "!A:G"),MATCH(Cockpit!$A28,INDIRECT(G$6 & "!A:A"),0),MATCH(G$11,INDIRECT(G$6 & "!1:1"),0))/L28)+1) -> 0.00060276829 | H28: =INDEX(INDIRECT(H$6 & "!A:G"),MATCH(Cockpit!$A28,INDIRECT(H$6 & "!A:A"),0),MATCH(H$11,INDIRECT(H$6 & "!1:1"),0)) -> 69 | I28: =LOG(INDEX(INDIRECT(I$6 & "!A:G"),MATCH(Cockpit!$A28,INDIRECT(I$6 & "!A:A"),0),MATCH(I$11,INDIRECT(I$6 & "!1:1"),0))/L28+1) -> 0.00060276829 | K28: Forel (Lavaux) | L28: 2160
A29: Lausanne | B29: =(INDEX(INDIRECT(B$6 & "!A:G"),MATCH(Cockpit!$A29,INDIRECT(B$6 & "!A:A"),0),MATCH(B$11,INDIRECT(B$6 & "!1:1"),0))+INDEX(INDIRECT(B$6 & "!A:G"),MATCH(Cockpit!$A29,INDIRECT(B$6 & "!A:A"),0),MATCH(B$12,INDIRECT(B$6 & "!1:1"),0)))/2 -> 1550000 | C29: =(INDEX(INDIRECT(C$6 & "!A:G"),MATCH(Cockpit!$A29,INDIRECT(C$6 & "!A:A"),0),MATCH(C$11,INDIRECT(C$6 & "!1:1"),0))+INDEX(INDIRECT(C$6 & "!A:G"),MATCH(Cockpit!$A29,INDIRECT(C$6 & "!A:A"),0),MATCH(C$12,INDIRECT(C$6 & "!1:1"),0)))/2 -> 2550000 | D29: =LOG((D$9*COUNTIF(B!F:F,Cockpit!A29)-COUNTIFS(B!F:F,Cockpit!A29,B!D:D,"TRAIN") + COUNTIFS(B!F:F,Cockpit!A29,B!D:D,"TRAIN")*D$10)/L29+1) -> 0.00068594504 | E29: =LOG(INDEX(INDIRECT(E$6 & "!A:G"),MATCH(Cockpit!$A29,INDIRECT(E$6 & "!A:A"),0),MATCH(E$11,INDIRECT(E$6 & "!1:1"),0))/L29+1) -> 0.024761459 | F29: =INDEX(INDIRECT(F$6 & "!A:G"),MATCH(Cockpit!$A29,INDIRECT(F$6 & "!A:A"),0),MATCH(F$11,INDIRECT(F$6 & "!1:1"),0)) -> 36 | G29: =LOG((INDEX(INDIRECT(G$6 & "!A:G"),MATCH(Cockpit!$A29,INDIRECT(G$6 & "!A:A"),0),MATCH(G$11,INDIRECT(G$6 & "!1:1"),0))/L29)+1) -> 0.00038953405 | H29: =INDEX(INDIRECT(H$6 & "!A:G"),MATCH(Cockpit!$A29,INDIRECT(H$6 & "!A:A"),0),MATCH(H$11,INDIRECT(H$6 & "!1:1"),0)) -> 78.5 | I29: =LOG(INDEX(INDIRECT(I$6 & "!A:G"),MATCH(Cockpit!$A29,INDIRECT(I$6 & "!A:A"),0),MATCH(I$11,INDIRECT(I$6 & "!1:1"),0))/L29+1) -> 0.0014245947 | K29: Lausanne | L29: 144873 | P29: 900000 | Q29: 1450000 | R29: 0.0010389825 | S29: 0.017832777 | T29: 25 | U29: 0.00051980196 | W29: 70 | X29: 0.025256795 | Y29: Assens | Z29: 1670
A30: Le Mont-sur-Lausanne | B30: =(INDEX(INDIRECT(B$6 & "!A:G"),MATCH(Cockpit!$A30,INDIRECT(B$6 & "!A:A"),0),MATCH(B$11,INDIRECT(B$6 & "!1:1"),0))+INDEX(INDIRECT(B$6 & "!A:G"),MATCH(Cockpit!$A30,INDIRECT(B$6 & "!A:A"),0),MATCH(B$12,INDIRECT(B$6 & "!1:1"),0)))/2 -> 1350000 | C30: =(INDEX(INDIRECT(C$6 & "!A:G"),MATCH(Cockpit!$A30,INDIRECT(C$6 & "!A:A"),0),MATCH(C$11,INDIRECT(C$6 & "!1:1"),0))+INDEX(INDIRECT(C$6 & "!A:G"),MATCH(Cockpit!$A30,INDIRECT(C$6 & "!A:A"),0),MATCH(C$12,INDIRECT(C$6 & "!1:1"),0)))/2 -> 1750000 | D30: =LOG((D$9*COUNTIF(B!F:F,Cockpit!A30)-COUNTIFS(B!F:F,Cockpit!A30,B!D:D,"TRAIN") + COUNTIFS(B!F:F,Cockpit!A30,B!D:D,"TRAIN")*D$10)/L30+1) -> 0.00059196112 | E30: =LOG(INDEX(INDIRECT(E$6 & "!A:G"),MATCH(Cockpit!$A30,INDIRECT(E$6 & "!A:A"),0),MATCH(E$11,INDIRECT(E$6 & "!1:1"),0))/L30+1) -> 0.037100721 | F30: =INDEX(INDIRECT(F$6 & "!A:G"),MATCH(Cockpit!$A30,INDIRECT(F$6 & "!A:A"),0),MATCH(F$11,INDIRECT(F$6 & "!1:1"),0)) -> 30 | G30: =LOG((INDEX(INDIRECT(G$6 & "!A:G"),MATCH(Cockpit!$A30,INDIRECT(G$6 & "!A:A"),0),MATCH(G$11,INDIRECT(G$6 & "!1:1"),0))/L30)+1) -> 0.00091037552 | H30: =INDEX(INDIRECT(H$6 & "!A:G"),MATCH(Cockpit!$A30,INDIRECT(H$6 & "!A:A"),0),MATCH(H$11,INDIRECT(H$6 & "!1:1"),0)) -> 72 | I30: =LOG(INDEX(INDIRECT(I$6 & "!A:G"),MATCH(Cockpit!$A30,INDIRECT(I$6 & "!A:A"),0),MATCH(I$11,INDIRECT(I$6 & "!1:1"),0))/L30+1) -> 0.00068296048 | K30: Le Mont-sur-Lausanne | L30: 9531 | P30: 1250000 | Q30: 1750000 | R30: 0.0028746685 | S30: 0.026883239 | T30: 40 | U30: 0.00044349708 | W30: 72 | X30: 0.00055430063 | Y30: Belmont-sur-Lausanne | Z30: 3915
A31: Lonay | B31: =(INDEX(INDIRECT(B$6 & "!A:G"),MATCH(Cockpit!$A31,INDIRECT(B$6 & "!A:A"),0),MATCH(B$11,INDIRECT(B$6 & "!1:1"),0))+INDEX(INDIRECT(B$6 & "!A:G"),MATCH(Cockpit!$A31,INDIRECT(B$6 & "!A:A"),0),MATCH(B$12,INDIRECT(B$6 & "!1:1"),0)))/2 -> 1350000 | C31: =(INDEX(INDIRECT(C$6 & "!A:G"),MATCH(Cockpit!$A31,INDIRECT(C$6 & "!A:A"),0),MATCH(C$11,INDIRECT(C$6 & "!1:1"),0))+INDEX(INDIRECT(C$6 & "!A:G"),MATCH(Cockpit!$A31,INDIRECT(C$6 & "!A:A"),0),MATCH(C$12,INDIRECT(C$6 & "!1:1"),0)))/2 -> 1850000 | D31: =LOG((D$9*COUNTIF(B!F:F,Cockpit!A31)-COUNTIFS(B!F:F,Cockpit!A31,B!D:D,"TRAIN") + COUNTIFS(B!F:F,Cockpit!A31,B!D:D,"TRAIN")*D$10)/L31+1) -> 0.0032170109 | E31: =LOG(INDEX(INDIRECT(E$6 & "!A:G"),MATCH(Cockpit!$A31,INDIRECT(E$6 & "!A:A"),0),MATCH(E$11,INDIRECT(E$6 & "!1:1"),0))/L31+1) -> 0.03859505 | F31: =INDEX(INDIRECT(F$6 & "!A:G"),MATCH(Cockpit!$A31,INDIRECT(F$6 & "!A:A"),0),MATCH(F$11,INDIRECT(F$6 & "!1:1"),0)) -> 38 | G31: =LOG((INDEX(INDIRECT(G$6 & "!A:G"),MATCH(Cockpit!$A31,INDIRECT(G$6 & "!A:A"),0),MATCH(G$11,INDIRECT(G$6 & "!1:1"),0))/L31)+1) -> 0.00080648952 | H31: =INDEX(INDIRECT(H$6 & "!A:G"),MATCH(Cockpit!$A31,INDIRECT(H$6 & "!A:A"),0),MATCH(H$11,INDIRECT(H$6 & "!1:1"),0)) -> 55 | I31: =LOG(INDEX(INDIRECT(I$6 & "!A:G"),MATCH(Cockpit!$A31,INDIRECT(I$6 & "!A:A"),0),MATCH(I$11,INDIRECT(I$6 & "!1:1"),0))/L31+1) -> 0.015851923 | K31: Lonay | L31: 2690 | P31: 1450000 | Q31: 2150000 | R31: 0.0023217937 | S31: 0.024198764 | T31: 35 | U31: 0.00048139057 | W31: 62.5 | X31: 0.00056157048 | Y31: Bourg-en-Lavaux | Z31: 5410
A32: Lutry | B32: =(INDEX(INDIRECT(B$6 & "!A:G"),MATCH(Cockpit!$A32,INDIRECT(B$6 & "!A:A"),0),MATCH(B$11,INDIRECT(B$6 & "!1:1"),0))+INDEX(INDIRECT(B$6 & "!A:G"),MATCH(Cockpit!$A32,INDIRECT(B$6 & "!A:A"),0),MATCH(B$12,INDIRECT(B$6 & "!1:1"),0)))/2 -> 1550000 | C32: =(INDEX(INDIRECT(C$6 & "!A:G"),MATCH(Cockpit!$A32,INDIRECT(C$6 & "!A:A"),0),MATCH(C$11,INDIRECT(C$6 & "!1:1"),0))+INDEX(INDIRECT(C$6 & "!A:G"),MATCH(Cockpit!$A32,INDIRECT(C$6 & "!A:A"),0),MATCH(C$12,INDIRECT(C$6 & "!1:1"),0)))/2 -> 2400000 | D32: =LOG((D$9*COUNTIF(B!F:F,Cockpit!A32)-COUNTIFS(B!F:F,Cockpit!A32,B!D:D,"TRAIN") + COUNTIFS(B!F:F,Cockpit!A32,B!D:D,"TRAIN")*D$10)/L32+1) -> 0.0019346793 | E32: =LOG(INDEX(INDIRECT(E$6 & "!A:G"),MATCH(Cockpit!$A32,INDIRECT(E$6 & "!A:A"),0),MATCH(E$11,INDIRECT(E$6 & "!1:1"),0))/L32+1) -> 0.023585262 | F32: =INDEX(INDIRECT(F$6 & "!A:G"),MATCH(Cockpit!$A32,INDIRECT(F$6 & "!A:A"),0),MATCH(F$11,INDIRECT(F$6 & "!1:1"),0)) -> 38 | G32: =LOG((INDEX(INDIRECT(G$6 & "!A:G"),MATCH(Cockpit!$A32,INDIRECT(G$6 & "!A:A"),0),MATCH(G$11,INDIRECT(G$6 & "!1:1"),0))/L32)+1) -> 0.00044412585 | H32: =INDEX(INDIRECT(H$6 & "!A:G"),MATCH(Cockpit!$A32,INDIRECT(H$6 & "!A:A"),0),MATCH(H$11,INDIRECT(H$6 & "!1:1"),0)) -> 54 | I32: =LOG(INDEX(INDIRECT(I$6 & "!A:G"),MATCH(Cockpit!$A32,INDIRECT(I$6 & "!A:A"),0),MATCH(I$11,INDIRECT(I$6 & "!1:1"),0))/L32+1) -> 0.0012101842 | K32: Lutry | L32: 10751 | P32: 1150000 | Q32: 1650000 | R32: 0.00072322162 | S32: 0.024622475 | T32: 25 | U32: 0.0014452409 | W32: 68 | X32: 0.00072322162 | Y32: Bremblens | Z32: 600
A33: Morges | B33: =(INDEX(INDIRECT(B$6 & "!A:G"),MATCH(Cockpit!$A33,INDIRECT(B$6 & "!A:A"),0),MATCH(B$11,INDIRECT(B$6 & "!1:1"),0))+INDEX(INDIRECT(B$6 & "!A:G"),MATCH(Cockpit!$A33,INDIRECT(B$6 & "!A:A"),0),MATCH(B$12,INDIRECT(B$6 & "!1:1"),0)))/2 -> 1450000 | C33: =(INDEX(INDIRECT(C$6 & "!A:G"),MATCH(Cockpit!$A33,INDIRECT(C$6 & "!A:A"),0),MATCH(C$11,INDIRECT(C$6 & "!1:1"),0))+INDEX(INDIRECT(C$6 & "!A:G"),MATCH(Cockpit!$A33,INDIRECT(C$6 & "!A:A"),0),MATCH(C$12,INDIRECT(C$6 & "!1:1"),0)))/2 -> 2050000 | D33: =LOG((D$9*COUNTIF(B!F:F,Cockpit!A33)-COUNTIFS(B!F:F,Cockpit!A33,B!D:D,"TRAIN") + COUNTIFS(B!F:F,Cockpit!A33,B!D:D,"TRAIN")*D$10)/L33+1) -> 0.0010020023 | E33: =LOG(INDEX(INDIRECT(E$6 & "!A:G"),MATCH(Cockpit!$A33,INDIRECT(E$6 & "!A:A"),0),MATCH(E$11,INDIRECT(E$6 & "!1:1"),0))/L33+1) -> 0.037482612 | F33: =INDEX(INDIRECT(F$6 & "!A:G"),MATCH(Cockpit!$A33,INDIRECT(F$6 & "!A:A"),0),MATCH(F$11,INDIRECT(F$6 & "!1:1"),0)) -> 38 | G33: =LOG((INDEX(INDIRECT(G$6 & "!A:G"),MATCH(Cockpit!$A33,INDIRECT(G$6 & "!A:A"),0),MATCH(G$11,INDIRECT(G$6 & "!1:1"),0))/L33)+1) -> 0.00073339924 | H33: =INDEX(INDIRECT(H$6 & "!A:G"),MATCH(Cockpit!$A33,INDIRECT(H$6 & "!A:A"),0),MATCH(H$11,INDIRECT(H$6 & "!1:1"),0)) -> 67 | I33: =LOG(INDEX(INDIRECT(I$6 & "!A:G"),MATCH(Cockpit!$A33,INDIRECT(I$6 & "!A:A"),0),MATCH(I$11,INDIRECT(I$6 & "!1:1"),0))/L33+1) -> 0.00073339924 | K33: Morges | L33: 17750 | P33: 1250000 | Q33: 1650000 | R33: 0.0010069088 | S33: 0.021843079 | T33: 35 | U33: 0.00048509936 | W33: 62.5 | X33: 0.00063425175 | Y33: Bussigny | Z33: 11632
A34: Préverenges | B34: =(INDEX(INDIRECT(B$6 & "!A:G"),MATCH(Cockpit!$A34,INDIRECT(B$6 & "!A:A"),0),MATCH(B$11,INDIRECT(B$6 & "!1:1"),0))+INDEX(INDIRECT(B$6 & "!A:G"),MATCH(Cockpit!$A34,INDIRECT(B$6 & "!A:A"),0),MATCH(B$12,INDIRECT(B$6 & "!1:1"),0)))/2 -> 1350000 | C34: =(INDEX(INDIRECT(C$6 & "!A:G"),MATCH(Cockpit!$A34,INDIRECT(C$6 & "!A:A"),0),MATCH(C$11,INDIRECT(C$6 & "!1:1"),0))+INDEX(INDIRECT(C$6 & "!A:G"),MATCH(Cockpit!$A34,INDIRECT(C$6 & "!A:A"),0),MATCH(C$12,INDIRECT(C$6 & "!1:1"),0)))/2 -> 2350000 | D34: =LOG((D$9*COUNTIF(B!F:F,Cockpit!A34)-COUNTIFS(B!F:F,Cockpit!A34,B!D:D,"TRAIN") + COUNTIFS(B!F:F,Cockpit!A34,B!D:D,"TRAIN")*D$10)/L34+1) -> 0.00025000163 | E34: =LOG(INDEX(INDIRECT(E$6 & "!A:G"),MATCH(Cockpit!$A34,INDIRECT(E$6 & "!A:A"),0),MATCH(E$11,INDIRECT(E$6 & "!1:1"),0))/L34+1) -> 0.018761176 | F34: =INDEX(INDIRECT(F$6 & "!A:G"),MATCH(Cockpit!$A34,INDIRECT(F$6 & "!A:A"),0),MATCH(F$11,INDIRECT(F$6 & "!1:1"),0)) -> 38 | G34: =LOG((INDEX(INDIRECT(G$6 & "!A:G"),MATCH(Cockpit!$A34,INDIRECT(G$6 & "!A:A"),0),MATCH(G$11,INDIRECT(G$6 & "!1:1"),0))/L34)+1) -> 0.00049985942 | H34: =INDEX(INDIRECT(H$6 & "!A:G"),MATCH(Cockpit!$A34,INDIRECT(H$6 & "!A:A"),0),MATCH(H$11,INDIRECT(H$6 & "!1:1"),0)) -> 65 | I34: =LOG(INDEX(INDIRECT(I$6 & "!A:G"),MATCH(Cockpit!$A34,INDIRECT(I$6 & "!A:A"),0),MATCH(I$11,INDIRECT(I$6 & "!1:1"),0))/L34+1) -> 0.00066635146 | K34: Préverenges | L34: 5210 | P34: 1350000 | Q34: 1550000 | R34: 0.00079907011 | S34: 0.020820978 | T34: 35 | U34: 0.00039971883 | W34: 77.5 | X34: 0.00031092421 | Y34: Chavannes-près-Renens | Z34: 9774
A35: Prilly | B35: =(INDEX(INDIRECT(B$6 & "!A:G"),MATCH(Cockpit!$A35,INDIRECT(B$6 & "!A:A"),0),MATCH(B$11,INDIRECT(B$6 & "!1:1"),0))+INDEX(INDIRECT(B$6 & "!A:G"),MATCH(Cockpit!$A35,INDIRECT(B$6 & "!A:A"),0),MATCH(B$12,INDIRECT(B$6 & "!1:1"),0)))/2 -> 1350000 | C35: =(INDEX(INDIRECT(C$6 & "!A:G"),MATCH(Cockpit!$A35,INDIRECT(C$6 & "!A:A"),0),MATCH(C$11,INDIRECT(C$6 & "!1:1"),0))+INDEX(INDIRECT(C$6 & "!A:G"),MATCH(Cockpit!$A35,INDIRECT(C$6 & "!A:A"),0),MATCH(C$12,INDIRECT(C$6 & "!1:1"),0)))/2 -> 1650000 | D35: =LOG((D$9*COUNTIF(B!F:F,Cockpit!A35)-COUNTIFS(B!F:F,Cockpit!A35,B!D:D,"TRAIN") + COUNTIFS(B!F:F,Cockpit!A35,B!D:D,"TRAIN")*D$10)/L35+1) -> 0.00071427232 | E35: =LOG(INDEX(INDIRECT(E$6 & "!A:G"),MATCH(Cockpit!$A35,INDIRECT(E$6 & "!A:A"),0),MATCH(E$11,INDIRECT(E$6 & "!1:1"),0))/L35+1) -> 0.021581403 | F35: =INDEX(INDIRECT(F$6 & "!A:G"),MATCH(Cockpit!$A35,INDIRECT(F$6 & "!A:A"),0),MATCH(F$11,INDIRECT(F$6 & "!1:1"),0)) -> 36 | G35: =LOG((INDEX(INDIRECT(G$6 & "!A:G"),MATCH(Cockpit!$A35,INDIRECT(G$6 & "!A:A"),0),MATCH(G$11,INDIRECT(G$6 & "!1:1"),0))/L35)+1) -> 0.00047631205 | H35: =INDEX(INDIRECT(H$6 & "!A:G"),MATCH(Cockpit!$A35,INDIRECT(H$6 & "!A:A"),0),MATCH(H$11,INDIRECT(H$6 & "!1:1"),0)) -> 72.5 | I35: =LOG(INDEX(INDIRECT(I$6 & "!A:G"),MATCH(Cockpit!$A35,INDIRECT(I$6 & "!A:A"),0),MATCH(I$11,INDIRECT(I$6 & "!1:1"),0))/L35+1) -> 0.0013934413 | K35: Prilly | L35: 12758 | P35: 1150000 | Q35: 1550000 | R35: 0.00062675227 | S35: 0.024390298 | T35: 20 | U35: 0.00062675227 | W35: 73 | X35: 0.00071621452 | Y35: Cheseaux-sur-Lausanne | Z35: 4847
A36: Pully | B36: =(INDEX(INDIRECT(B$6 & "!A:G"),MATCH(Cockpit!$A36,INDIRECT(B$6 & "!A:A"),0),MATCH(B$11,INDIRECT(B$6 & "!1:1"),0))+INDEX(INDIRECT(B$6 & "!A:G"),MATCH(Cockpit!$A36,INDIRECT(B$6 & "!A:A"),0),MATCH(B$12,INDIRECT(B$6 & "!1:1"),0)))/2 -> 1700000 | C36: =(INDEX(INDIRECT(C$6 & "!A:G"),MATCH(Cockpit!$A36,INDIRECT(C$6 & "!A:A"),0),MATCH(C$11,INDIRECT(C$6 & "!1:1"),0))+INDEX(INDIRECT(C$6 & "!A:G"),MATCH(Cockpit!$A36,INDIRECT(C$6 & "!A:A"),0),MATCH(C$12,INDIRECT(C$6 & "!1:1"),0)))/2 -> 2250000 | D36: =LOG((D$9*COUNTIF(B!F:F,Cockpit!A36)-COUNTIFS(B!F:F,Cockpit!A36,B!D:D,"TRAIN") + COUNTIFS(B!F:F,Cockpit!A36,B!D:D,"TRAIN")*D$10)/L36+1) -> 0.00097694096 | E36: =LOG(INDEX(INDIRECT(E$6 & "!A:G"),MATCH(Cockpit!$A36,INDIRECT(E$6 & "!A:A"),0),MATCH(E$11,INDIRECT(E$6 & "!1:1"),0))/L36+1) -> 0.023787503 | F36: =INDEX(INDIRECT(F$6 & "!A:G"),MATCH(Cockpit!$A36,INDIRECT(F$6 & "!A:A"),0),MATCH(F$11,INDIRECT(F$6 & "!1:1"),0)) -> 36 | G36: =LOG((INDEX(INDIRECT(G$6 & "!A:G"),MATCH(Cockpit!$A36,INDIRECT(G$6 & "!A:A"),0),MATCH(G$11,INDIRECT(G$6 & "!1:1"),0))/L36)+1) -> 0.00039992332 | H36: =INDEX(INDIRECT(H$6 & "!A:G"),MATCH(Cockpit!$A36,INDIRECT(H$6 & "!A:A"),0),MATCH(H$11,INDIRECT(H$6 & "!1:1"),0)) -> 61 | I36: =LOG(INDEX(INDIRECT(I$6 & "!A:G"),MATCH(Cockpit!$A36,INDIRECT(I$6 & "!A:A"),0),MATCH(I$11,INDIRECT(I$6 & "!1:1"),0))/L36+1) -> 0.00073291167 | K36: Pully | L36: 19538 | P36: 1250000 | Q36: 1650000 | R36: 0.00077222379 | S36: 0.021816473 | T36: 35 | U36: 0.00060976443 | W36: 63.5 | X36: 0.0012592376 | Y36: Crissier | Z36: 10676
A37: Renens | B37: =(INDEX(INDIRECT(B$6 & "!A:G"),MATCH(Cockpit!$A37,INDIRECT(B$6 & "!A:A"),0),MATCH(B$11,INDIRECT(B$6 & "!1:1"),0))+INDEX(INDIRECT(B$6 & "!A:G"),MATCH(Cockpit!$A37,INDIRECT(B$6 & "!A:A"),0),MATCH(B$12,INDIRECT(B$6 & "!1:1"),0)))/2 -> 1250000 | C37: =(INDEX(INDIRECT(C$6 & "!A:G"),MATCH(Cockpit!$A37,INDIRECT(C$6 & "!A:A"),0),MATCH(C$11,INDIRECT(C$6 & "!1:1"),0))+INDEX(INDIRECT(C$6 & "!A:G"),MATCH(Cockpit!$A37,INDIRECT(C$6 & "!A:A"),0),MATCH(C$12,INDIRECT(C$6 & "!1:1"),0)))/2 -> 1850000 | D37: =LOG((D$9*COUNTIF(B!F:F,Cockpit!A37)-COUNTIFS(B!F:F,Cockpit!A37,B!D:D,"TRAIN") + COUNTIFS(B!F:F,Cockpit!A37,B!D:D,"TRAIN")*D$10)/L37+1) -> 0 | E37: =LOG(INDEX(INDIRECT(E$6 & "!A:G"),MATCH(Cockpit!$A37,INDIRECT(E$6 & "!A:A"),0),MATCH(E$11,INDIRECT(E$6 & "!1:1"),0))/L37+1) -> 0.018742905 | F37: =INDEX(INDIRECT(F$6 & "!A:G"),MATCH(Cockpit!$A37,INDIRECT(F$6 & "!A:A"),0),MATCH(F$11,INDIRECT(F$6 & "!1:1"),0)) -> 36 | G37: =LOG((INDEX(INDIRECT(G$6 & "!A:G"),MATCH(Cockpit!$A37,INDIRECT(G$6 & "!A:A"),0),MATCH(G$11,INDIRECT(G$6 & "!1:1"),0))/L37)+1) -> 0.00044332217 | H37: =INDEX(INDIRECT(H$6 & "!A:G"),MATCH(Cockpit!$A37,INDIRECT(H$6 & "!A:A"),0),MATCH(H$11,INDIRECT(H$6 & "!1:1"),0)) -> 77 | I37: =LOG(INDEX(INDIRECT(I$6 & "!A:G"),MATCH(Cockpit!$A37,INDIRECT(I$6 & "!A:A"),0),MATCH(I$11,INDIRECT(I$6 & "!1:1"),0))/L37+1) -> 0.00074532804 | K37: Renens | L37: 21541 | P37: 950000 | Q37: 1550000 | R37: 0 | S37: 0.027180578 | T37: 30 | U37: 0.00062286778 | W37: 76 | X37: 0.00031154555 | Y37: Cugy | Z37: 2787
A38: Saint-Barthélemy | B38: =(INDEX(INDIRECT(B$6 & "!A:G"),MATCH(Cockpit!$A38,INDIRECT(B$6 & "!A:A"),0),MATCH(B$11,INDIRECT(B$6 & "!1:1"),0))+INDEX(INDIRECT(B$6 & "!A:G"),MATCH(Cockpit!$A38,INDIRECT(B$6 & "!A:A"),0),MATCH(B$12,INDIRECT(B$6 & "!1:1"),0)))/2 -> 700000 | C38: =(INDEX(INDIRECT(C$6 & "!A:G"),MATCH(Cockpit!$A38,INDIRECT(C$6 & "!A:A"),0),MATCH(C$11,INDIRECT(C$6 & "!1:1"),0))+INDEX(INDIRECT(C$6 & "!A:G"),MATCH(Cockpit!$A38,INDIRECT(C$6 & "!A:A"),0),MATCH(C$12,INDIRECT(C$6 & "!1:1"),0)))/2 -> 1250000 | D38: =LOG((D$9*COUNTIF(B!F:F,Cockpit!A38)-COUNTIFS(B!F:F,Cockpit!A38,B!D:D,"TRAIN") + COUNTIFS(B!F:F,Cockpit!A38,B!D:D,"TRAIN")*D$10)/L38+1) -> 0 | E38: =LOG(INDEX(INDIRECT(E$6 & "!A:G"),MATCH(Cockpit!$A38,INDIRECT(E$6 & "!A:A"),0),MATCH(E$11,INDIRECT(E$6 & "!1:1"),0))/L38+1) -> 0.021189299 | F38: =INDEX(INDIRECT(F$6 & "!A:G"),MATCH(Cockpit!$A38,INDIRECT(F$6 & "!A:A"),0),MATCH(F$11,INDIRECT(F$6 & "!1:1"),0)) -> 25 | G38: =LOG((INDEX(INDIRECT(G$6 & "!A:G"),MATCH(Cockpit!$A38,INDIRECT(G$6 & "!A:A"),0),MATCH(G$11,INDIRECT(G$6 & "!1:1"),0))/L38)+1) -> 0.0010843813 | H38: =INDEX(INDIRECT(H$6 & "!A:G"),MATCH(Cockpit!$A38,INDIRECT(H$6 & "!A:A"),0),MATCH(H$11,INDIRECT(H$6 & "!1:1"),0)) -> 77 | I38: =LOG(INDEX(INDIRECT(I$6 & "!A:G"),MATCH(Cockpit!$A38,INDIRECT(I$6 & "!A:A"),0),MATCH(I$11,INDIRECT(I$6 & "!1:1"),0))/L38+1) -> 0.0027058934 | K38: Saint-Barthélemy | L38: 800 | P38: 1350000 | Q38: 1950000 | R38: 0.0031780768 | S38: 0.033060101 | T38: 29 | U38: 0.00098034913 | W38: 62 | X38: 0.0022026817 | Y38: Denges | Z38: 1770
A39: Sainte-Croix | B39: =(INDEX(INDIRECT(B$6 & "!A:G"),MATCH(Cockpit!$A39,INDIRECT(B$6 & "!A:A"),0),MATCH(B$11,INDIRECT(B$6 & "!1:1"),0))+INDEX(INDIRECT(B$6 & "!A:G"),MATCH(Cockpit!$A39,INDIRECT(B$6 & "!A:A"),0),MATCH(B$12,INDIRECT(B$6 & "!1:1"),0)))/2 -> 450000 | C39: =(INDEX(INDIRECT(C$6 & "!A:G"),MATCH(Cockpit!$A39,INDIRECT(C$6 & "!A:A"),0),MATCH(C$11,INDIRECT(C$6 & "!1:1"),0))+INDEX(INDIRECT(C$6 & "!A:G"),MATCH(Cockpit!$A39,INDIRECT(C$6 & "!A:A"),0),MATCH(C$12,INDIRECT(C$6 & "!1:1"),0)))/2 -> 850000 | D39: =LOG((D$9*COUNTIF(B!F:F,Cockpit!A39)-COUNTIFS(B!F:F,Cockpit!A39,B!D:D,"TRAIN") + COUNTIFS(B!F:F,Cockpit!A39,B!D:D,"TRAIN")*D$10)/L39+1) -> 0.0026789716 | E39: =LOG(INDEX(INDIRECT(E$6 & "!A:G"),MATCH(Cockpit!$A39,INDIRECT(E$6 & "!A:A"),0),MATCH(E$11,INDIRECT(E$6 & "!1:1"),0))/L39+1) -> 0.029327064 | F39: =INDEX(INDIRECT(F$6 & "!A:G"),MATCH(Cockpit!$A39,INDIRECT(F$6 & "!A:A"),0),MATCH(F$11,INDIRECT(F$6 & "!1:1"),0)) -> 23 | G39: =LOG((INDEX(INDIRECT(G$6 & "!A:G"),MATCH(Cockpit!$A39,INDIRECT(G$6 & "!A:A"),0),MATCH(G$11,INDIRECT(G$6 & "!1:1"),0))/L39)+1) -> 0.00077946981 | H39: =INDEX(INDIRECT(H$6 & "!A:G"),MATCH(Cockpit!$A39,INDIRECT(H$6 & "!A:A"),0),MATCH(H$11,INDIRECT(H$6 & "!1:1"),0)) -> 70 | I39: =LOG(INDEX(INDIRECT(I$6 & "!A:G"),MATCH(Cockpit!$A39,INDIRECT(I$6 & "!A:A"),0),MATCH(I$11,INDIRECT(I$6 & "!1:1"),0))/L39+1) -> 0.0037115724 | K39: Sainte-Croix | L39: 5010 | P39: 1450000 | Q39: 1950000 | R39: 0.0011984678 | S39: 0.031809483 | T39: 30 | U39: 0.00074942984 | W39: 60.5 | X39: 0.00089916074 | Y39: Echandens | Z39: 2895
A40: Saint-Sulpice | B40: =(INDEX(INDIRECT(B$6 & "!A:G"),MATCH(Cockpit!$A40,INDIRECT(B$6 & "!A:A"),0),MATCH(B$11,INDIRECT(B$6 & "!1:1"),0))+INDEX(INDIRECT(B$6 & "!A:G"),MATCH(Cockpit!$A40,INDIRECT(B$6 & "!A:A"),0),MATCH(B$12,INDIRECT(B$6 & "!1:1"),0)))/2 -> 1450000 | C40: =(INDEX(INDIRECT(C$6 & "!A:G"),MATCH(Cockpit!$A40,INDIRECT(C$6 & "!A:A"),0),MATCH(C$11,INDIRECT(C$6 & "!1:1"),0))+INDEX(INDIRECT(C$6 & "!A:G"),MATCH(Cockpit!$A40,INDIRECT(C$6 & "!A:A"),0),MATCH(C$12,INDIRECT(C$6 & "!1:1"),0)))/2 -> 2750000 | D40: =LOG((D$9*COUNTIF(B!F:F,Cockpit!A40)-COUNTIFS(B!F:F,Cockpit!A40,B!D:D,"TRAIN") + COUNTIFS(B!F:F,Cockpit!A40,B!D:D,"TRAIN")*D$10)/L40+1) -> 0 | E40: =LOG(INDEX(INDIRECT(E$6 & "!A:G"),MATCH(Cockpit!$A40,INDIRECT(E$6 & "!A:A"),0),MATCH(E$11,INDIRECT(E$6 & "!1:1"),0))/L40+1) -> 0.024566085 | F40: =INDEX(INDIRECT(F$6 & "!A:G"),MATCH(Cockpit!$A40,INDIRECT(F$6 & "!A:A"),0),MATCH(F$11,INDIRECT(F$6 & "!1:1"),0)) -> 28 | G40: =LOG((INDEX(INDIRECT(G$6 & "!A:G"),MATCH(Cockpit!$A40,INDIRECT(G$6 & "!A:A"),0),MATCH(G$11,INDIRECT(G$6 & "!1:1"),0))/L40)+1) -> 0.00075756397 | H40: =INDEX(INDIRECT(H$6 & "!A:G"),MATCH(Cockpit!$A40,INDIRECT(H$6 & "!A:A"),0),MATCH(H$11,INDIRECT(H$6 & "!1:1"),0)) -> 55 | I40: =LOG(INDEX(INDIRECT(I$6 & "!A:G"),MATCH(Cockpit!$A40,INDIRECT(I$6 & "!A:A"),0),MATCH(I$11,INDIRECT(I$6 & "!1:1"),0))/L40+1) -> 0.0015138088 | K40: Saint-Sulpice | L40: 5155 | P40: 1250000 | Q40: 2150000 | R40: 0 | S40: 0.014697258 | T40: 35 | U40: 0.00058455858 | W40: 62.5 | X40: 0.00165421 | Y40: Ecublens | Z40: 13364
A41: Savigny | B41: =(INDEX(INDIRECT(B$6 & "!A:G"),MATCH(Cockpit!$A41,INDIRECT(B$6 & "!A:A"),0),MATCH(B$11,INDIRECT(B$6 & "!1:1"),0))+INDEX(INDIRECT(B$6 & "!A:G"),MATCH(Cockpit!$A41,INDIRECT(B$6 & "!A:A"),0),MATCH(B$12,INDIRECT(B$6 & "!1:1"),0)))/2 -> 950000 | C41: =(INDEX(INDIRECT(C$6 & "!A:G"),MATCH(Cockpit!$A41,INDIRECT(C$6 & "!A:A"),0),MATCH(C$11,INDIRECT(C$6 & "!1:1"),0))+INDEX(INDIRECT(C$6 & "!A:G"),MATCH(Cockpit!$A41,INDIRECT(C$6 & "!A:A"),0),MATCH(C$12,INDIRECT(C$6 & "!1:1"),0)))/2 -> 1550000 | D41: =LOG((D$9*COUNTIF(B!F:F,Cockpit!A41)-COUNTIFS(B!F:F,Cockpit!A41,B!D:D,"TRAIN") + COUNTIFS(B!F:F,Cockpit!A41,B!D:D,"TRAIN")*D$10)/L41+1) -> 0.0012330914 | E41: =LOG(INDEX(INDIRECT(E$6 & "!A:G"),MATCH(Cockpit!$A41,INDIRECT(E$6 & "!A:A"),0),MATCH(E$11,INDIRECT(E$6 & "!1:1"),0))/L41+1) -> 0.037819431 | F41: =INDEX(INDIRECT(F$6 & "!A:G"),MATCH(Cockpit!$A41,INDIRECT(F$6 & "!A:A"),0),MATCH(F$11,INDIRECT(F$6 & "!1:1"),0)) -> 32 | G41: =LOG((INDEX(INDIRECT(G$6 & "!A:G"),MATCH(Cockpit!$A41,INDIRECT(G$6 & "!A:A"),0),MATCH(G$11,INDIRECT(G$6 & "!1:1"),0))/L41)+1) -> 0.00098675301 | H41: =INDEX(INDIRECT(H$6 & "!A:G"),MATCH(Cockpit!$A41,INDIRECT(H$6 & "!A:A"),0),MATCH(H$11,INDIRECT(H$6 & "!1:1"),0)) -> 69 | I41: =LOG(INDEX(INDIRECT(I$6 & "!A:G"),MATCH(Cockpit!$A41,INDIRECT(I$6 & "!A:A"),0),MATCH(I$11,INDIRECT(I$6 & "!1:1"),0))/L41+1) -> 0.0012330914 | K41: Savigny | L41: 3517 | P41: 1350000 | Q41: 1850000 | R41: 0.0010510308 | S41: 0.031698974 | T41: 30 | U41: 0.00052583336 | W41: 64.5 | X41: 0.0032325428 | Y41: Epalinges | Z41: 9905
A42: Villars-Sainte-Croix | B42: =(INDEX(INDIRECT(B$6 & "!A:G"),MATCH(Cockpit!$A42,INDIRECT(B$6 & "!A:A"),0),MATCH(B$11,INDIRECT(B$6 & "!1:1"),0))+INDEX(INDIRECT(B$6 & "!A:G"),MATCH(Cockpit!$A42,INDIRECT(B$6 & "!A:A"),0),MATCH(B$12,INDIRECT(B$6 & "!1:1"),0)))/2 -> 1350000 | C42: =(INDEX(INDIRECT(C$6 & "!A:G"),MATCH(Cockpit!$A42,INDIRECT(C$6 & "!A:A"),0),MATCH(C$11,INDIRECT(C$6 & "!1:1"),0))+INDEX(INDIRECT(C$6 & "!A:G"),MATCH(Cockpit!$A42,INDIRECT(C$6 & "!A:A"),0),MATCH(C$12,INDIRECT(C$6 & "!1:1"),0)))/2 -> 1850000 | D42: =LOG((D$9*COUNTIF(B!F:F,Cockpit!A42)-COUNTIFS(B!F:F,Cockpit!A42,B!D:D,"TRAIN") + COUNTIFS(B!F:F,Cockpit!A42,B!D:D,"TRAIN")*D$10)/L42+1) -> 0.00018224695 | E42: =LOG(INDEX(INDIRECT(E$6 & "!A:G"),MATCH(Cockpit!$A42,INDIRECT(E$6 & "!A:A"),0),MATCH(E$11,INDIRECT(E$6 & "!1:1"),0))/L42+1) -> 0.003630487 | F42: =INDEX(INDIRECT(F$6 & "!A:G"),MATCH(Cockpit!$A42,INDIRECT(F$6 & "!A:A"),0),MATCH(F$11,INDIRECT(F$6 & "!1:1"),0)) -> 32 | G42: =LOG((INDEX(INDIRECT(G$6 & "!A:G"),MATCH(Cockpit!$A42,INDIRECT(G$6 & "!A:A"),0),MATCH(G$11,INDIRECT(G$6 & "!1:1"),0))/L42)+1) -> 9.1133036e-05 | H42: =INDEX(INDIRECT(H$6 & "!A:G"),MATCH(Cockpit!$A42,INDIRECT(H$6 & "!A:A"),0),MATCH(H$11,INDIRECT(H$6 & "!1:1"),0)) -> 60.5 | I42: =LOG(INDEX(INDIRECT(I$6 & "!A:G"),MATCH(Cockpit!$A42,INDIRECT(I$6 & "!A:A"),0),MATCH(I$11,INDIRECT(I$6 & "!1:1"),0))/L42+1) -> 0.0045333865 | K42: Villars-Sainte-Croix | L42: 9530 | M42: 953 | P42: 950000 | Q42: 1550000 | R42: 0.0018599364 | S42: 0.039184259 | T42: 22 | U42: 0.0011169174 | W42: 73 | X42: 0.0022309697 | Y42: Etagnières | Z42: 1165
A43: Vaulion | B43: =(INDEX(INDIRECT(B$6 & "!A:G"),MATCH(Cockpit!$A43,INDIRECT(B$6 & "!A:A"),0),MATCH(B$11,INDIRECT(B$6 & "!1:1"),0))+INDEX(INDIRECT(B$6 & "!A:G"),MATCH(Cockpit!$A43,INDIRECT(B$6 & "!A:A"),0),MATCH(B$12,INDIRECT(B$6 & "!1:1"),0)))/2 -> 350000 | C43: =(INDEX(INDIRECT(C$6 & "!A:G"),MATCH(Cockpit!$A43,INDIRECT(C$6 & "!A:A"),0),MATCH(C$11,INDIRECT(C$6 & "!1:1"),0))+INDEX(INDIRECT(C$6 & "!A:G"),MATCH(Cockpit!$A43,INDIRECT(C$6 & "!A:A"),0),MATCH(C$12,INDIRECT(C$6 & "!1:1"),0)))/2 -> 650000 | D43: =LOG((D$9*COUNTIF(B!F:F,Cockpit!A43)-COUNTIFS(B!F:F,Cockpit!A43,B!D:D,"TRAIN") + COUNTIFS(B!F:F,Cockpit!A43,B!D:D,"TRAIN")*D$10)/M43+1) -> 0.0062877238 | E43: =LOG(INDEX(INDIRECT(E$6 & "!A:G"),MATCH(Cockpit!$A43,INDIRECT(E$6 & "!A:A"),0),MATCH(E$11,INDIRECT(E$6 & "!1:1"),0))/M43+1) -> 0.28724171 | F43: =INDEX(INDIRECT(F$6 & "!A:G"),MATCH(Cockpit!$A43,INDIRECT(F$6 & "!A:A"),0),MATCH(F$11,INDIRECT(F$6 & "!1:1"),0)) -> 22 | G43: =LOG((INDEX(INDIRECT(G$6 & "!A:G"),MATCH(Cockpit!$A43,INDIRECT(G$6 & "!A:A"),0),MATCH(G$11,INDIRECT(G$6 & "!1:1"),0))/M43)+1) -> 0.0045005012 | H43: =INDEX(INDIRECT(H$6 & "!A:G"),MATCH(Cockpit!$A43,INDIRECT(H$6 & "!A:A"),0),MATCH(H$11,INDIRECT(H$6 & "!1:1"),0)) -> 81 | I43: =LOG(INDEX(INDIRECT(I$6 & "!A:G"),MATCH(Cockpit!$A43,INDIRECT(I$6 & "!A:A"),0),MATCH(I$11,INDIRECT(I$6 & "!1:1"),0))/M43+1) -> 0.0098402547 | K43: Vaulion | L43: 4800 | M43: 480 | P43: 850000 | Q43: 1350000 | R43: 0.0022060723 | S43: 0.025381731 | T43: 30 | U43: 0.00060276829 | W43: 69 | X43: 0.00060276829 | Y43: Forel (Lavaux) | Z43: 2160
P44: 1550000 | Q44: 2550000 | R44: 0.00068594504 | S44: 0.024761459 | T44: 36 | U44: 0.00038953405 | W44: 78.5 | X44: 0.0014245947 | Y44: Lausanne | Z44: 144873
A45: Z_score | P45: 1350000 | Q45: 1750000 | R45: 0.00059196112 | S45: 0.037100721 | T45: 30 | U45: 0.00091037552 | W45: 72 | X45: 0.00068296048 | Y45: Le Mont-sur-Lausanne | Z45: 9531
A46: Moyenne | B46: =AVERAGE(B14:B43) -> 1201666.7 | C46: =AVERAGE(C14:C43) -> 1778333.3 | D46: =AVERAGE(D14:D43) -> 0.0013137351 | E46: =AVERAGE(E14:E43) -> 0.034453088 | F46: =AVERAGE(F14:F43) -> 31.466667 | G46: =AVERAGE(G14:G43) -> 0.00078323778 | H46: =AVERAGE(H14:H43) -> 67.7 | I46: =AVERAGE(I14:I43) -> 0.0029376499 | P46: 1350000 | Q46: 1850000 | R46: 0.0032170109 | S46: 0.03859505 | T46: 38 | U46: 0.00080648952 | W46: 55 | X46: 0.015851923 | Y46: Lonay | Z46: 2690
A47: Ecart type | B47: =STDEV(B14:B43) -> 314994.07 | C47: =STDEV(C14:C43) -> 452518.5 | D47: =STDEV(D14:D43) -> 0.0013493174 | E47: =STDEV(E14:E43) -> 0.048383084 | F47: =STDEV(F14:F43) -> 5.6491277 | G47: =STDEV(G14:G43) -> 0.00075375143 | H47: =STDEV(H14:H43) -> 7.3573796 | I47: =STDEV(I14:I43) -> 0.0052803838 | P47: 1550000 | Q47: 2400000 | R47: 0.0019346793 | S47: 0.023585262 | T47: 38 | U47: 0.00044412585 | W47: 54 | X47: 0.0012101842 | Y47: Lutry | Z47: 10751
A48: Assens | B48: =(B14-B$46)/B$47*B$8 -> -4.7884499 | C48: =(C14-C$46)/C$47*C$8 -> -3.6278444 | D48: =(D14-D$46)/D$47*D$8 -> -1.4253637 | E48: =(E14-E$46)/E$47*E$8 -> -1.0305447 | F48: =(F14-F$46)/F$47*F$8 -> -4.578878 | G48: =(G14-G$46)/G$47*G$8 -> -2.7959968 | H48: =(H14-H$46)/H$47*H$8 -> 1.5630565 | I48: =(I14-I$46)/I$47*I$8 -> 21.134018 | L48: Assens | P48: 1450000 | Q48: 2050000 | R48: 0.0010020023 | S48: 0.037482612 | T48: 38 | U48: 0.00073339924 | W48: 67 | X48: 0.00073339924 | Y48: Morges | Z48: 17750
A49: Belmont-sur-Lausanne | B49: =(B15-B$46)/B$47*B$8 -> 0.76721021 | C49: =(C15-C$46)/C$47*C$8 -> -0.31306271 | D49: =(D15-D$46)/D$47*D$8 -> 8.097823 | E49: =(E15-E$46)/E$47*E$8 -> -0.46936953 | F49: =(F15-F$46)/F$47*F$8 -> 6.0422308 | G49: =(G15-G$46)/G$47*G$8 -> -3.6058645 | H49: =(H15-H$46)/H$47*H$8 -> 2.9222361 | I49: =(I15-I$46)/I$47*I$8 -> -2.2567955 | K49: =I49-H49+G49+F49+E49+D49-C49-B49 -> 4.4316407 | L49: Belmont-sur-Lausanne | P49: 1350000 | Q49: 2350000 | R49: 0.00025000163 | S49: 0.018761176 | T49: 38 | U49: 0.00049985942 | W49: 65 | X49: 0.00066635146 | Y49: Préverenges | Z49: 5210
A50: Bourg-en-Lavaux | B50: =(B16-B$46)/B$47*B$8 -> 3.9418731 | C50: =(C16-C$46)/C$47*C$8 -> 4.1066461 | D50: =(D16-D$46)/D$47*D$8 -> 5.2296148 | E50: =(E16-E$46)/E$47*E$8 -> -0.63582083 | F50: =(F16-F$46)/F$47*F$8 -> 2.5018612 | G50: =(G16-G$46)/G$47*G$8 -> -3.203679 | H50: =(H16-H$46)/H$47*H$8 -> -3.5338669 | I50: =(I16-I$46)/I$47*I$8 -> -2.2499116 | K50: =I50-H50+G50+F50+E50+D50-C50-B50 -> -2.8725879 | L50: Bourg-en-Lavaux | P50: 1350000 | Q50: 1650000 | R50: 0.00071427232 | S50: 0.021581403 | T50: 36 | U50: 0.00047631205 | W50: 72.5 | X50: 0.0013934413 | Y50: Prilly | Z50: 12758
A51: Bremblens | B51: =(B17-B$46)/B$47*B$8 -> -0.82012126 | C51: =(C17-C$46)/C$47*C$8 -> -1.4179899 | D51: =(D17-D$46)/D$47*D$8 -> -3.0634706 | E51: =(E17-E$46)/E$47*E$8 -> -0.60954855 | F51: =(F17-F$46)/F$47*F$8 -> -4.578878 | G51: =(G17-G$46)/G$47*G$8 -> 7.0262219 | H51: =(H17-H$46)/H$47*H$8 -> 0.20387693 | I51: =(I17-I$46)/I$47*I$8 -> -2.096844 | K51: =I51-H51+G51+F51+E51+D51-C51-B51 -> -1.2882851 | L51: Bremblens | P51: 1700000 | Q51: 2250000 | R51: 0.00097694096 | S51: 0.023787503 | T51: 36 | U51: 0.00039992332 | W51: 61 | X51: 0.00073291167 | Y51: Pully | Z51: 19538
A52: Bussigny | B52: =(B18-B$46)/B$47*B$8 -> 0.76721021 | C52: =(C18-C$46)/C$47*C$8 -> -1.4179899 | D52: =(D18-D$46)/D$47*D$8 -> -1.591756 | E52: =(E18-E$46)/E$47*E$8 -> -0.7818854 | F52: =(F18-F$46)/F$47*F$8 -> 2.5018612 | G52: =(G18-G$46)/G$47*G$8 -> -3.1643155 | H52: =(H18-H$46)/H$47*H$8 -> -3.5338669 | I52: =(I18-I$46)/I$47*I$8 -> -2.1810897 | K52: =I52-H52+G52+F52+E52+D52-C52-B52 -> -1.0325388 | L52: Bussigny | P52: 1250000 | Q52: 1850000 | R52: 0 | S52: 0.018742905 | T52: 36 | U52: 0.00044332217 | W52: 77 | X52: 0.00074532804 | Y52: Renens | Z52: 21541
A53: Chavannes-près-Renens | B53: =(B19-B$46)/B$47*B$8 -> 2.3545417 | C53: =(C19-C$46)/C$47*C$8 -> -2.5229171 | D53: =(D19-D$46)/D$47*D$8 -> -2.6699832 | E53: =(E19-E$46)/E$47*E$8 -> -0.84526088 | F53: =(F19-F$46)/F$47*F$8 -> 2.5018612 | G53: =(G19-G$46)/G$47*G$8 -> -4.0705084 | H53: =(H19-H$46)/H$47*H$8 -> 6.6599799 | I53: =(I19-I$46)/I$47*I$8 -> -2.4872488 | K53: =I53-H53+G53+F53+E53+D53-C53-B53 -> -14.062745 | L53: Chavannes-près-Renens | P53: 700000 | Q53: 1250000 | R53: 0 | S53: 0.021189299 | T53: 25 | U53: 0.0010843813 | W53: 77 | X53: 0.0027058934 | Y53: Saint-Barthélemy | Z53: 800
A54: Cheseaux-sur-Lausanne | B54: =(B20-B$46)/B$47*B$8 -> -0.82012126 | C54: =(C20-C$46)/C$47*C$8 -> -2.5229171 | D54: =(D20-D$46)/D$47*D$8 -> -3.5639351 | E54: =(E20-E$46)/E$47*E$8 -> -0.62394473 | F54: =(F20-F$46)/F$47*F$8 -> -8.1192476 | G54: =(G20-G$46)/G$47*G$8 -> -1.6608712 | H54: =(H20-H$46)/H$47*H$8 -> 3.6018258 | I54: =(I20-I$46)/I$47*I$8 -> -2.103479 | K54: =I54-H54+G54+F54+E54+D54-C54-B54 -> -16.330265 | L54: Cheseaux-sur-Lausanne | P54: 450000 | Q54: 850000 | R54: 0.0026789716 | S54: 0.029327064 | T54: 23 | U54: 0.00077946981 | W54: 70 | X54: 0.0037115724 | Y54: Sainte-Croix | Z54: 5010
A55: Crissier | B55: =(B21-B$46)/B$47*B$8 -> 0.76721021 | C55: =(C21-C$46)/C$47*C$8 -> -1.4179899 | D55: =(D21-D$46)/D$47*D$8 -> -2.8092567 | E55: =(E21-E$46)/E$47*E$8 -> -0.78353511 | F55: =(F21-F$46)/F$47*F$8 -> 2.5018612 | G55: =(G21-G$46)/G$47*G$8 -> -1.841173 | H55: =(H21-H$46)/H$47*H$8 -> -2.8542771 | I55: =(I21-I$46)/I$47*I$8 -> -1.5892901 | K55: =I55-H55+G55+F55+E55+D55-C55-B55 -> -1.0163369 | L55: Crissier | P55: 1450000 | Q55: 2750000 | R55: 0 | S55: 0.024566085 | T55: 28 | U55: 0.00075756397 | W55: 55 | X55: 0.0015138088 | Y55: Saint-Sulpice | Z55: 5155
A56: Cugy | B56: =(B22-B$46)/B$47*B$8 -> -3.9947842 | C56: =(C22-C$46)/C$47*C$8 -> -2.5229171 | D56: =(D22-D$46)/D$47*D$8 -> -6.8154057 | E56: =(E22-E$46)/E$47*E$8 -> -0.45093303 | F56: =(F22-F$46)/F$47*F$8 -> -1.0385084 | G56: =(G22-G$46)/G$47*G$8 -> -1.7020996 | H56: =(H22-H$46)/H$47*H$8 -> 5.6405952 | I56: =(I22-I$46)/I$47*I$8 -> -2.4866604 | K56: =I56-H56+G56+F56+E56+D56-C56-B56 -> -11.616501 | L56: Cugy | P56: 950000 | Q56: 1550000 | R56: 0.0012330914 | S56: 0.037819431 | T56: 32 | U56: 0.00098675301 | W56: 69 | X56: 0.0012330914 | Y56: Savigny | Z56: 3517
A57: Denges | B57: =(B23-B$46)/B$47*B$8 -> 2.3545417 | C57: =(C23-C$46)/C$47*C$8 -> 1.8967917 | D57: =(D23-D$46)/D$47*D$8 -> 9.6718473 | E57: =(E23-E$46)/E$47*E$8 -> -0.086372357 | F57: =(F23-F$46)/F$47*F$8 -> -1.7465823 | G57: =(G23-G$46)/G$47*G$8 -> 2.0920569 | H57: =(H23-H$46)/H$47*H$8 -> -3.8736618 | I57: =(I23-I$46)/I$47*I$8 -> -0.69594198 | K57: =I57-H57+G57+F57+E57+D57-C57-B57 -> 8.8573359 | L57: Denges | P57: 1350000 | Q57: 1850000 | R57: 0.00018224695 | S57: 0.003630487 | T57: 32 | U57: 9.1133036e-05 | W57: 60.5 | X57: 0.0045333865 | Y57: Villars-Sainte-Croix | Z57: 9530
A58: Echandens | B58: =(B24-B$46)/B$47*B$8 -> 3.9418731 | C58: =(C24-C$46)/C$47*C$8 -> 1.8967917 | D58: =(D24-D$46)/D$47*D$8 -> -0.59798474 | E58: =(E24-E$46)/E$47*E$8 -> -0.1639171 | F58: =(F24-F$46)/F$47*F$8 -> -1.0385084 | G58: =(G24-G$46)/G$47*G$8 -> -0.35882323 | H58: =(H24-H$46)/H$47*H$8 -> -4.8930464 | I58: =(I24-I$46)/I$47*I$8 -> -1.9302471 | K58: =I58-H58+G58+F58+E58+D58-C58-B58 -> -5.035099 | L58: Echandens | P58: 350000 | Q58: 650000 | R58: 0.0062877238 | S58: 0.28724171 | T58: 22 | U58: 0.0045005012 | W58: 81 | X58: 0.0098402547 | Y58: Vaulion | Z58: 4800
A59: Ecublens | B59: =(B25-B$46)/B$47*B$8 -> 0.76721021 | C59: =(C25-C$46)/C$47*C$8 -> 4.1066461 | D59: =(D25-D$46)/D$47*D$8 -> -6.8154057 | E59: =(E25-E$46)/E$47*E$8 -> -1.224963 | F59: =(F25-F$46)/F$47*F$8 -> 2.5018612 | G59: =(G25-G$46)/G$47*G$8 -> -2.1086973 | H59: =(H25-H$46)/H$47*H$8 -> -3.5338669 | I59: =(I25-I$46)/I$47*I$8 -> -1.2152903 | K59: =I59-H59+G59+F59+E59+D59-C59-B59 -> -10.202485 | L59: Ecublens
A60: Epalinges | B60: =(B26-B$46)/B$47*B$8 -> 2.3545417 | C60: =(C26-C$46)/C$47*C$8 -> 0.7918645 | D60: =(D26-D$46)/D$47*D$8 -> -1.3628593 | E60: =(E26-E$46)/E$47*E$8 -> -0.17076921 | F60: =(F26-F$46)/F$47*F$8 -> -1.0385084 | G60: =(G26-G$46)/G$47*G$8 -> -2.731982 | H60: =(H26-H$46)/H$47*H$8 -> -2.1746873 | I60: =(I26-I$46)/I$47*I$8 -> 0.27923432 | K60: =I60-H60+G60+F60+E60+D60-C60-B60 -> -5.9966035 | L60: Epalinges
A61: Etagnières | B61: =(B27-B$46)/B$47*B$8 -> -3.9947842 | C61: =(C27-C$46)/C$47*C$8 -> -2.5229171 | D61: =(D27-D$46)/D$47*D$8 -> 2.8335876 | E61: =(E27-E$46)/E$47*E$8 -> 0.29335696 | F61: =(F27-F$46)/F$47*F$8 -> -6.7030998 | G61: =(G27-G$46)/G$47*G$8 -> 3.5415351 | H61: =(H27-H$46)/H$47*H$8 -> 3.6018258 | I61: =(I27-I$46)/I$47*I$8 -> -0.66915606 | K61: =I61-H61+G61+F61+E61+D61-C61-B61 -> 2.2120992 | L61: Etagnières
A62: Forel (Lavaux) | B62: =(B28-B$46)/B$47*B$8 -> -5.5821157 | C62: =(C28-C$46)/C$47*C$8 -> -4.7327716 | D62: =(D28-D$46)/D$47*D$8 -> 4.6292743 | E62: =(E28-E$46)/E$47*E$8 -> -0.56247076 | F62: =(F28-F$46)/F$47*F$8 -> -1.0385084 | G62: =(G28-G$46)/G$47*G$8 -> -1.9154271 | H62: =(H28-H$46)/H$47*H$8 -> 0.88346672 | I62: =(I28-I$46)/I$47*I$8 -> -2.2109014 | K62: =I62-H62+G62+F62+E62+D62-C62-B62 -> 8.3333872 | L62: Forel (Lavaux)
A63: Lausanne | B63: =(B29-B$46)/B$47*B$8 -> 5.5292046 | C63: =(C29-C$46)/C$47*C$8 -> 8.526355 | D63: =(D29-D$46)/D$47*D$8 -> -3.2568543 | E63: =(E29-E$46)/E$47*E$8 -> -0.60093082 | F63: =(F29-F$46)/F$47*F$8 -> 3.2099351 | G63: =(G29-G$46)/G$47*G$8 -> -4.1786054 | H63: =(H29-H$46)/H$47*H$8 -> 7.3395697 | I63: =(I29-I$46)/I$47*I$8 -> -1.4327133 | K63: =I63-H63+G63+F63+E63+D63-C63-B63 -> -27.654298 | L63: Lausanne
A64: Le Mont-sur-Lausanne | B64: =(B30-B$46)/B$47*B$8 -> 2.3545417 | C64: =(C30-C$46)/C$47*C$8 -> -0.31306271 | D64: =(D30-D$46)/D$47*D$8 -> -3.7444249 | E64: =(E30-E$46)/E$47*E$8 -> 0.1641669 | F64: =(F30-F$46)/F$47*F$8 -> -1.0385084 | G64: =(G30-G$46)/G$47*G$8 -> 1.3493864 | H64: =(H30-H$46)/H$47*H$8 -> 2.9222361 | I64: =(I30-I$46)/I$47*I$8 -> -2.1349673 | K64: =I64-H64+G64+F64+E64+D64-C64-B64 -> -10.368062 | L64: Le Mont-sur-Lausanne
A65: Lonay | B65: =(B31-B$46)/B$47*B$8 -> 2.3545417 | C65: =(C31-C$46)/C$47*C$8 -> 0.7918645 | D65: =(D31-D$46)/D$47*D$8 -> 9.8738297 | E65: =(E31-E$46)/E$47*E$8 -> 0.25682297 | F65: =(F31-F$46)/F$47*F$8 -> 4.626083 | G65: =(G31-G$46)/G$47*G$8 -> 0.24678422 | H65: =(H31-H$46)/H$47*H$8 -> -8.6307902 | I65: =(I31-I$46)/I$47*I$8 -> 12.228537 | L65: Lonay
A66: Lutry | B66: =(B32-B$46)/B$47*B$8 -> 5.5292046 | C66: =(C32-C$46)/C$47*C$8 -> 6.8689642 | D66: =(D32-D$46)/D$47*D$8 -> 3.2213395 | E66: =(E32-E$46)/E$47*E$8 -> -0.6738611 | F66: =(F32-F$46)/F$47*F$8 -> 4.626083 | G66: =(G32-G$46)/G$47*G$8 -> -3.5991911 | H66: =(H32-H$46)/H$47*H$8 -> -9.31038 | I66: =(I32-I$46)/I$47*I$8 -> -1.6357388 | K66: =I66-H66+G66+F66+E66+D66-C66-B66 -> -1.1491572 | L66: Lutry
A67: Morges | B67: =(B33-B$46)/B$47*B$8 -> 3.9418731 | C67: =(C33-C$46)/C$47*C$8 -> 3.0017189 | D67: =(D33-D$46)/D$47*D$8 -> -1.61721 | E67: =(E33-E$46)/E$47*E$8 -> 0.18784607 | F67: =(F33-F$46)/F$47*F$8 -> 4.626083 | G67: =(G33-G$46)/G$47*G$8 -> -0.52896518 | H67: =(H33-H$46)/H$47*H$8 -> -0.47571285 | I67: =(I33-I$46)/I$47*I$8 -> -2.0872068 | K67: =I67-H67+G67+F67+E67+D67-C67-B67 -> -5.8873322 | L67: Morges
A68: Préverenges | B68: =(B34-B$46)/B$47*B$8 -> 2.3545417 | C68: =(C34-C$46)/C$47*C$8 -> 6.3165006 | D68: =(D34-D$46)/D$47*D$8 -> -5.5184452 | E68: =(E34-E$46)/E$47*E$8 -> -0.9729792 | F68: =(F34-F$46)/F$47*F$8 -> 4.626083 | G68: =(G34-G$46)/G$47*G$8 -> -3.0076584 | H68: =(H34-H$46)/H$47*H$8 -> -1.8348924 | I68: =(I34-I$46)/I$47*I$8 -> -2.1506944 | K68: =I68-H68+G68+F68+E68+D68-C68-B68 -> -13.859844 | L68: Préverenges
A69: Prilly | B69: =(B35-B$46)/B$47*B$8 -> 2.3545417 | C69: =(C35-C$46)/C$47*C$8 -> -1.4179899 | D69: =(D35-D$46)/D$47*D$8 -> -3.1098978 | E69: =(E35-E$46)/E$47*E$8 -> -0.79811062 | F69: =(F35-F$46)/F$47*F$8 -> 3.2099351 | G69: =(G35-G$46)/G$47*G$8 -> -3.2575803 | H69: =(H35-H$46)/H$47*H$8 -> 3.262031 | I69: =(I35-I$46)/I$47*I$8 -> -1.4622125 | K69: =I69-H69+G69+F69+E69+D69-C69-B69 -> -9.6164488 | L69: Prilly
A70: Pully | B70: =(B36-B$46)/B$47*B$8 -> 7.9102018 | C70: =(C36-C$46)/C$47*C$8 -> 5.2115734 | D70: =(D36-D$46)/D$47*D$8 -> -1.7472233 | E70: =(E36-E$46)/E$47*E$8 -> -0.66132111 | F70: =(F36-F$46)/F$47*F$8 -> 3.2099351 | G70: =(G36-G$46)/G$47*G$8 -> -4.068338 | H70: =(H36-H$46)/H$47*H$8 -> -4.5532515 | I70: =(I36-I$46)/I$47*I$8 -> -2.0876685 | K70: =I70-H70+G70+F70+E70+D70-C70-B70 -> -13.923139 | L70: Pully
A71: Renens | B71: =(B37-B$46)/B$47*B$8 -> 0.76721021 | C71: =(C37-C$46)/C$47*C$8 -> 0.7918645 | D71: =(D37-D$46)/D$47*D$8 -> -6.8154057 | E71: =(E37-E$46)/E$47*E$8 -> -0.97411213 | F71: =(F37-F$46)/F$47*F$8 -> 3.2099351 | G71: =(G37-G$46)/G$47*G$8 -> -3.607721 | H71: =(H37-H$46)/H$47*H$8 -> 6.320185 | I71: =(I37-I$46)/I$47*I$8 -> -2.0759114 | K71: =I71-H71+G71+F71+E71+D71-C71-B71 -> -18.142475 | L71: Renens
A72: Saint-Barthélemy | B72: =(B38-B$46)/B$47*B$8 -> -7.9631129 | C72: =(C38-C$46)/C$47*C$8 -> -5.8376988 | D72: =(D38-D$46)/D$47*D$8 -> -6.8154057 | E72: =(E38-E$46)/E$47*E$8 -> -0.82242311 | F72: =(F38-F$46)/F$47*F$8 -> -4.578878 | G72: =(G38-G$46)/G$47*G$8 -> 3.1962104 | H72: =(H38-H$46)/H$47*H$8 -> 6.320185 | I72: =(I38-I$46)/I$47*I$8 -> -0.21945043 | K72: =I72-H72+G72+F72+E72+D72-C72-B72 -> -1.7593202 | L72: Saint-Barthélemy
A73: Sainte-Croix | B73: =(B39-B$46)/B$47*B$8 -> -11.931442 | C73: =(C39-C$46)/C$47*C$8 -> -10.257408 | D73: =(D39-D$46)/D$47*D$8 -> 7.082585 | E73: =(E39-E$46)/E$47*E$8 -> -0.31783985 | F73: =(F39-F$46)/F$47*F$8 -> -5.9950259 | G73: =(G39-G$46)/G$47*G$8 -> -0.03999155 | H73: =(H39-H$46)/H$47*H$8 -> 1.5630565 | I73: =(I39-I$46)/I$47*I$8 -> 0.73282788 | L73: Sainte-Croix
A74: Saint-Sulpice | B74: =(B40-B$46)/B$47*B$8 -> 3.9418731 | C74: =(C40-C$46)/C$47*C$8 -> 10.736209 | D74: =(D40-D$46)/D$47*D$8 -> -6.8154057 | E74: =(E40-E$46)/E$47*E$8 -> -0.613045 | F74: =(F40-F$46)/F$47*F$8 -> -2.4546563 | G74: =(G40-G$46)/G$47*G$8 -> -0.2724909 | H74: =(H40-H$46)/H$47*H$8 -> -8.6307902 | I74: =(I40-I$46)/I$47*I$8 -> -1.3482363 | K74: =I74-H74+G74+F74+E74+D74-C74-B74 -> -17.551127 | L74: Saint-Sulpice
A75: Savigny | B75: =(B41-B$46)/B$47*B$8 -> -3.9947842 | C75: =(C41-C$46)/C$47*C$8 -> -2.5229171 | D75: =(D41-D$46)/D$47*D$8 -> -0.41836424 | E75: =(E41-E$46)/E$47*E$8 -> 0.20873057 | F75: =(F41-F$46)/F$47*F$8 -> 0.37763943 | G75: =(G41-G$46)/G$47*G$8 -> 2.1600249 | H75: =(H41-H$46)/H$47*H$8 -> 0.88346672 | I75: =(I41-I$46)/I$47*I$8 -> -1.6140479 | K75: =I75-H75+G75+F75+E75+D75-C75-B75 -> 6.3482174 | L75: Savigny
A76: Villars-Sainte-Croix | B76: =(B42-B$46)/B$47*B$8 -> 2.3545417 | C76: =(C42-C$46)/C$47*C$8 -> 0.7918645 | D76: =(D42-D$46)/D$47*D$8 -> -5.8699434 | E76: =(E42-E$46)/E$47*E$8 -> -1.9111597 | F76: =(F42-F$46)/F$47*F$8 -> 0.37763943 | G76: =(G42-G$46)/G$47*G$8 -> -7.345708 | H76: =(H42-H$46)/H$47*H$8 -> -4.8930464 | I76: =(I42-I$46)/I$47*I$8 -> 1.5110044 | K76: =I76-H76+G76+F76+E76+D76-C76-B76 -> -11.491527 | L76: Villars-Sainte-Croix
A77: Vaulion | B77: =(B43-B$46)/B$47*B$8 -> -13.518773 | C77: =(C43-C$46)/C$47*C$8 -> -12.467262 | D77: =(D43-D$46)/D$47*D$8 -> 25.8041 | E77: =(E43-E$46)/E$47*E$8 -> 15.674194 | F77: =(F43-F$46)/F$47*F$8 -> -6.7030998 | G77: =(G43-G$46)/G$47*G$8 -> 39.453468 | H77: =(H43-H$46)/H$47*H$8 -> 9.0385441 | I77: =(I43-I$46)/I$47*I$8 -> 6.5360825 | L77: Vaulion

Sheet A
A1: Commune | B1: Appart. Prix bas | C1: Appart. Prix haut | D1: Maison prix bas | E1: Maison prix haut
A2: Assens | B2: 800000 | C2: 1000000 | D2: 1400000 | E2: 1500000
A3: Belmont-sur-Lausanne | B3: 1200000 | C3: 1300000 | D3: 1700000 | E3: 1800000
A4: Bourg-en-Lavaux | B4: 1400000 | C4: 1500000 | D4: 2100000 | E4: 2200000
A5: Bremblens | B5: 1100000 | C5: 1200000 | D5: 1600000 | E5: 1700000
A6: Bussigny | B6: 1200000 | C6: 1300000 | D6: 1600000 | E6: 1700000
A7: Chavannes-près-Renens | B7: 1300000 | C7: 1400000 | D7: 1500000 | E7: 1600000
A8: Cheseaux-sur-Lausanne | B8: 1100000 | C8: 1200000 | D8: 1500000 | E8: 1600000
A9: Crissier | B9: 1200000 | C9: 1300000 | D9: 1600000 | E9: 1700000
A10: Cugy | B10: 900000 | C10: 1000000 | D10: 1500000 | E10: 1600000
A11: Denges | B11: 1300000 | C11: 1400000 | D11: 1900000 | E11: 2000000
A12: Echandens | B12: 1400000 | C12: 1500000 | D12: 1900000 | E12: 2000000
A13: Ecublens | B13: 1200000 | C13: 1300000 | D13: 2100000 | E13: 2200000
... A31: Vaulion | B31: 300000 | C31: 400000 | D31: 600000 | E31: 700000

Sheet A1
A1: Commune | B1: Appart. Prix bas | C1: Appart. Prix haut | D1: Maison prix bas | E1: Maison prix haut
A2: Assens | B2: 800000 | C2: 1000000 | D2: 1400000 | E2: 1500000
A3: Belmont-sur-Lausanne | B3: 1200000 | C3: 1300000 | D3: 1700000 | E3: 1800000
A4: Bourg-en-Lavaux | B4: 1400000 | C4: 1500000 | D4: 2100000 | E4: 2200000
A5: Bremblens | B5: 1100000 | C5: 1200000 | D5: 1600000 | E5: 1700000
A6: Bussigny | B6: 1200000 | C6: 1300000 | D6: 1600000 | E6: 1700000
A7: Chavannes-près-Renens | B7: 1300000 | C7: 1400000 | D7: 1500000 | E7: 1600000
A8: Cheseaux-sur-Lausanne | B8: 1100000 | C8: 1200000 | D8: 1500000 | E8: 1600000
A9: Crissier | B9: 1200000 | C9: 1300000 | D9: 1600000 | E9: 1700000
A10: Cugy | B10: 900000 | C10: 1000000 | D10: 1500000 | E10: 1600000
A11: Denges | B11: 1300000 | C11: 1400000 | D11: 1900000 | E11: 2000000
A12: Echandens | B12: 1400000 | C12: 1500000 | D12: 1900000 | E12: 2000000
A13: Ecublens | B13: 1200000 | C13: 1300000 | D13: 2100000 | E13: 2200000
... A31: Vaulion | B31: 300000 | C31: 400000 | D31: 600000 | E31: 700000

Sheet B
A1: Code DiDok | B1: Désignation officielle | C1: Désignation organisation commerciale | D1: Moyen de transport | E1: Canton | F1: Commune | G1: Numéro Commune | H1: Localité | I1: Swiss Business Organisation ID | J1: Commentaire OFT | K1: Coordonnées E MN95 | L1: Coordonnées N MN95 | M1: Altitude | N1: Lien sur la carte
A2: 8583891 | B2: Vufflens-Aclens, zone industr. | C2: Automobiles MBC | D2: BUS | E2: VD | F2: Aclens | G2: 5621 | H2: Aclens | I2: ch:1:sboid:100566 | K2: 2529929.7 | L2: 1157464 | M2: 406 | N2: 46.56477268818526, 6.524742392767344
A3: 8570093 | B3: Aclens, collège | C3: Automobiles MBC | D3: BUS | E3: VD | F3: Aclens | G3: 5621 | H3: Aclens | I3: ch:1:sboid:100566 | K3: 2528825 | L3: 1157750 | M3: 450 | N3: 46.567228572318456, 6.510291141153921
A4: 8507650 | B4: Agiez, Vers-le-Pont | C4: PostAuto AG | D4: BUS | E4: VD | F4: Agiez | G4: 5742 | H4: Agiez | I4: ch:1:sboid:100602 | K4: 2529106 | L4: 1174641 | M4: 507 | N4: 46.71919129431517, 6.511347735082323
A5: 8570235 | B5: Agiez, L'Epine | C5: PostAuto AG | D5: BUS | E5: VD | F5: Agiez | G5: 5742 | H5: Agiez | I5: ch:1:sboid:100602 | K5: 2528837 | L5: 1174270 | M5: 523 | N5: 46.71582551025668, 6.507887226046329
A6: 8504425 | B6: Aigle, Les Iles | C6: Transports Publics du Chablais (Bus) | D6: BUS | E6: VD | F6: Aigle | G6: 5401 | H6: Aigle | I6: ch:1:sboid:100617 | K6: 2562250 | L6: 1127697 | M6: 386 | N6: 46.29961661730584, 6.948697073079572
A7: 8505193 | B7: Aigle, Biole | C7: Transports Publics du Chablais (Bus) | D7: BUS | E7: VD | F7: Aigle | G7: 5401 | H7: Aigle | I7: ch:1:sboid:100617 | K7: 2561991 | L7: 1128843 | M7: 384 | N7: 46.309910755987055, 6.945241890286049
A8: 8581845 | B8: Aigle, collège Planchette | C8: Transports Publics du Chablais (Bus) | D8: BUS | E8: VD | F8: Aigle | G8: 5401 | H8: Aigle | I8: ch:1:sboid:100617 | J8: (Bus) ohne Fahrplandaten 2016 [beibehalten] | K8: 2562877 | L8: 1129904 | M8: 396 | N8: 46.31950460015498, 6.956658085456567
A9: 8517484 | B9: Aigle-Parc Aventure | C9: Transports Publics du Chablais | D9: TRAIN | E9: VD | F9: Aigle | G9: 5401 | H9: Aigle | I9: ch:1:sboid:100008 | K9: 2565151.2 | L9: 1129423 | M9: 488.1 | N9: 46.315300001126964, 6.986219994119313
A10: 8581047 | B10: Aigle, Pautex | C10: Transports Publics du Chablais (Bus) | D10: BUS | E10: VD | F10: Aigle | G10: 5401 | H10: Aigle | I10: ch:1:sboid:100617 | K10: 2562697 | L10: 1129618 | M10: 393 | N10: 46.31692190321954, 6.954344102473771
A11: 8593763 | B11: Aigle, av. Margencel | C11: Transports Publics du Chablais (Bus) | D11: BUS | E11: VD | F11: Aigle | G11: 5401 | H11: Aigle | I11: ch:1:sboid:100617 | K11: 2563515 | L11: 1129751 | M11: 406 | N11: 46.318163343780725, 6.964953361332843
A12: 8511106 | B12: Aigle-Dépôt, gare | C12: Transports Publics du Chablais (Bus) | D12: BUS | E12: VD | F12: Aigle | G12: 5401 | H12: Aigle | I12: ch:1:sboid:100617 | K12: 2564331 | L12: 1129735 | M12: 428 | N12: 46.31806335872635, 6.975548588579126
A13: 8512177 | B13: Aigle, Fontanney | C13: Transports Publics du Chablais (Bus) | D13: BUS | E13: VD | F13: Aigle | G13: 5401 | H13: Aigle | I13: ch:1:sboid:100617 | K13: 2565332.6 | L13: 1129785.5 | M13: 532.5 | N13: 46.31857051500889, 6.988548107424288
A14: 8593766 | B14: Aigle, Dents-du-Midi | C14: Transports Publics du Chablais (Bus) | D14: BUS | E14: VD | F14: Aigle | G14: 5401 | H14: Aigle | I14: ch:1:sboid:100617 | K14: 2563046 | L14: 1129261 | M14: 396 | N14: 46.313729866550396, 6.9589034211079
A15: 8593765 | B15: Aigle, Champex | C15: Transports Publics du Chablais (Bus) | D15: BUS | E15: VD | F15: Aigle | G15: 5401 | H15: Aigle | I15: ch:1:sboid:100617 | K15: 2561857 | L15: 1129051 | M15: 383 | N15: 46.31177419397323, 6.943485372920066
A16: 8593764 | B16: Aigle, ch. des Lieugex | C16: Transports Publics du Chablais (Bus) | D16: BUS | E16: VD | F16: Aigle | G16: 5401 | H16: Aigle | I16: ch:1:sboid:100617 | K16: 2563147 | L16: 1129978 | M16: 401 | N16: 46.3201851703714, 6.960157659596822
A17: 8517500 | B17: Aigle-Place-du-Marché (DIAB) | C17: Transports Publics du Chablais | E17: VD | F17: Aigle | G17: 5401 | H17: Aigle | I17: ch:1:sboid:100008 | J17: (Zug) | K17: 2563889.6 | L17: 1129585 | M17: 415.3 | N17: 46.31668999858064, 6.969829998461089
A18: 8501400 | B18: Aigle | C18: Schweizerische Bundesbahnen SBB | D18: TRAIN | E18: VD | F18: Aigle | G18: 5401 | H18: Aigle | I18: ch:1:sboid:100001 | K18: 2563416.3 | L18: 1129606.2 | M18: 403.908 | N18: 46.316855418598124, 6.963683211861402
A19: 8501468 | B19: Aigle-Château | C19: Transports Publics du Chablais | D19: TRAIN | E19: VD | F19: Aigle | G19: 5401 | H19: Aigle | I19: ch:1:sboid:100008 | K19: 2564590 | L19: 1129601 | M19: 433 | N19: 46.31687170607126, 6.97892136108901
A20: 8501554 | B20: Aigle-Place-du-Marché | C20: Transports Publics du Chablais | D20: TRAIN | E20: VD | F20: Aigle | G20: 5401 | H20: Aigle | I20: ch:1:sboid:100008 | K20: 2563929.3 | L20: 1129645.9 | M20: 416.7 | N20: 46.317239994000715, 6.970339995448264
A21: 8509014 | B21: Aigle, Pré Neyroud | C21: Transports Publics du Chablais (Bus) | D21: BUS | E21: VD | F21: Aigle | G21: 5401 | H21: Aigle | I21: ch:1:sboid:100617 | K21: 2561952 | L21: 1127942 | M21: 385 | N21: 46.3018036496258, 6.944809449285151
A22: 8570600 | B22: Aigle, gare | C22: Transports Publics du Chablais (Bus) | D22: BUS | E22: VD | F22: Aigle | G22: 5401 | H22: Aigle | I22: ch:1:sboid:100617 | K22: 2563487 | L22: 1129528 | M22: 406 | N22: 46.31615583128023, 6.964607382328524
A23: 8570601 | B23: Aigle, place du Marché | C23: Transports Publics du Chablais (Bus) | D23: BUS | E23: VD | F23: Aigle | G23: 5401 | H23: Aigle | I23: ch:1:sboid:100617 | K23: 2563920 | L23: 1129661 | M23: 417 | N23: 46.31737568585273, 6.9702184049401295
A24: 8501179 | B24: Pont-de-Drapel | C24: Transports Publics du Chablais | D24: TRAIN | E24: VD | F24: Aigle | G24: 5401 | H24: Aigle | I24: ch:1:sboid:100008 | K24: 2565177.2 | L24: 1129929.8 | M24: 613.7 | N24: 46.31985999970431, 6.986520004273106
A25: 8501485 | B25: Fontanney | C25: Transports Publics du Chablais | D25: TRAIN | E25: VD | F25: Aigle | G25: 5401 | H25: Aigle | I25: ch:1:sboid:100008 | K25: 2564851.2 | L25: 1129760.5 | M25: 548.8 | N25: 46.31831999450118, 6.982299999546069
A26: 8504407 | B26: Aigle, Grand-Pré | C26: Transports Publics du Chablais (Bus) | D26: BUS | E26: VD | F26: Aigle | G26: 5401 | H26: Aigle | I26: ch:1:sboid:100617 | K26: 2561407 | L26: 1129616 | M26: 383 | N26: 46.316830850819, 6.9375968369801955
A27: 8504421 | B27: Aigle, Levant | C27: Transports Publics du Chablais (Bus) | D27: BUS | E27: VD | F27: Aigle | G27: 5401 | H27: Aigle | I27: ch:1:sboid:100617 | K27: 2563107 | L27: 1129587 | M27: 399 | N27: 46.31666574611651, 6.95966940254503
A28: 8511997 | B28: RBC Chablais | C28: Schweizerische Bundesbahnen SBB | E28: VD | F28: Aigle | G28: 5401 | H28: Aigle | I28: ch:1:sboid:100001 | K28: 2563339.5 | L28: 1130262.2 | M28: 405.9 | N28: 46.3227520902552, 6.9626350459755155
A29: 8593770 | B29: Aigle, Pré d'Emoz/écoles | C29: Transports Publics du Chablais (Bus) | D29: BUS | E29: VD | F29: Aigle | G29: 5401 | H29: Aigle | I29: ch:1:sboid:100617 | K29: 2562865 | L29: 1130145 | M29: 397 | N29: 46.32167183919654, 6.956483007024112
A30: 8593769 | B30: Aigle, Novassales | C30: Transports Publics du Chablais (Bus) | D30: BUS | E30: VD | F30: Aigle | G30: 5401 | H30: Aigle | I30: ch:1:sboid:100617 | K30: 2563342 | L30: 1129352 | M30: 403 | N30: 46.31456471306193, 6.962738839240221
A31: 8593768 | B31: Aigle, Vergers | C31: Transports Publics du Chablais (Bus) | D31: BUS | E31: VD | F31: Aigle | G31: 5401 | H31: Aigle | I31: ch:1:sboid:100617 | J31: bis 2018: Aigle, hôpital | K31: 2563407 | L31: 1129066 | M31: 401 | N31: 46.31199556571619, 6.9636052087107245
A32: 8581046 | B32: Aigle, rte d'Evian | C32: Transports Publics du Chablais (Bus) | D32: BUS | E32: VD | F32: Aigle | G32: 5401 | H32: Aigle | I32: ch:1:sboid:100617 | K32: 2563043 | L32: 1129759 | M32: 399 | N32: 46.318209436951534, 6.958824831624484
A33: 8581050 | B33: Aigle, La Mêlée | C33: PostAuto AG | D33: BUS | E33: VD | F33: Aigle | G33: 5401 | H33: Aigle | I33: ch:1:sboid:100602 | K33: 2561446 | L33: 1129765 | M33: 385 | N33: 46.31817341640464, 6.938090780183085
A34: 8511103 | B34: Aigle, Valerette | C34: Transports Publics du Chablais (Bus) | D34: BUS | E34: VD | F34: Aigle | G34: 5401 | H34: Aigle | I34: ch:1:sboid:100617 | K34: 2563701 | L34: 1128915 | M34: 404 | N34: 46.31065324343813, 6.967433533095001
A35: 8519338 | B35: Aigle [voie 11-16] | C35: Transports Publics du Chablais | E35: VD | F35: Aigle | G35: 5401 | H35: Aigle | I35: ch:1:sboid:100008 | J35: (Zug) | K35: 2563448 | L35: 1129549 | M35: 404 | N35: 46.316342609309636, 6.964099417232659
A36: 8581048 | B36: Aigle, Golf | C36: Transports Publics du Chablais (Bus) | D36: BUS | E36: VD | F36: Aigle | G36: 5401 | H36: Aigle | I36: ch:1:sboid:100617 | K36: 2562291 | L36: 1129451 | M36: 388 | N36: 46.315396936375215, 6.949086764936207
A37: 8501484 | B37: Aigle-Dépôt | C37: Transports Publics du Chablais | D37: TRAIN | E37: VD | F37: Aigle | G37: 5401 | H37: Aigle | I37: ch:1:sboid:100008 | K37: 2564317.4 | L37: 1129760.3 | M37: 427.6 | N37: 46.318289994546745, 6.975370001409716
A38: 8596090 | B38: Aigle, Les Glariers | C38: Transports Publics du Chablais (Bus) | D38: BUS | E38: VD | F38: Aigle | G38: 5401 | H38: Aigle | I38: ch:1:sboid:100617 | J38: (neue Hst per 12.2017 aber keine Fahrplandaten) | K38: 2563730 | L38: 1130027 | M38: 412 | N38: 46.32065776499928, 6.967723103787464
A39: 8501471 | B39: Plambuit | C39: Transports Publics du Chablais | D39: TRAIN | E39: VD | F39: Aigle | G39: 5401 | H39: Aigle | I39: ch:1:sboid:100008 | K39: 2568066 | L39: 1130746.4 | M39: 801.4 | N39: 46.32734999369797, 7.023969993526004
A40: 8504408 | B40: Aigle, piscine | C40: Transports Publics du Chablais (Bus) | D40: BUS | E40: VD | F40: Aigle | G40: 5401 | H40: Aigle | I40: ch:1:sboid:100617 | K40: 2563338 | L40: 1130162 | M40: 404 | N40: 46.32185081398912, 6.962622938313034
A41: 8504418 | B41: Aigle, La Chapelle | C41: Transports Publics du Chablais (Bus) | D41: BUS | E41: VD | F41: Aigle | G41: 5401 | H41: Aigle | I41: ch:1:sboid:100617 | K41: 2563697 | L41: 1129155 | M41: 408 | N41: 46.312811936831636, 6.96736284366535
A42: 8517482 | B42: En Châlex | C42: Transports Publics du Chablais | E42: VD | F42: Aigle | G42: 5401 | H42: Aigle | I42: ch:1:sboid:100008 | J42: (Zug) | K42: 2563820.9 | L42: 1128156.1 | M42: 393.4 | N42: 46.30383325051869, 6.969049275811245
A43: 8512152 | B43: Aigle, Marjolin | C43: Transports Publics du Chablais (Bus) | D43: BUS | E43: VD | F43: Aigle | G43: 5401 | H43: Aigle | I43: ch:1:sboid:100617 | K43: 2563721.5 | L43: 1128604.5 | M43: 400.3 | N43: 46.3078612296431, 6.967723842556987
A44: 8504409 | B44: Aigle, médiathèque | C44: Transports Publics du Chablais (Bus) | D44: BUS | E44: VD | F44: Aigle | G44: 5401 | H44: Aigle | I44: ch:1:sboid:100617 | K44: 2563506 | L44: 1129892 | M44: 406 | N44: 46.319431213187656, 6.964825430504725
A45: 8504420 | B45: Aigle, Charmettes | C45: Transports Publics du Chablais (Bus) | D45: BUS | E45: VD | F45: Aigle | G45: 5401 | H45: Aigle | I45: ch:1:sboid:100617 | K45: 2563427 | L45: 1128858 | M45: 399 | N45: 46.31012560278968, 6.963881219363302
A46: 8504422 | B46: Aigle, Orlons | C46: Transports Publics du Chablais (Bus) | D46: BUS | E46: VD | F46: Aigle | G46: 5401 | H46: Aigle | I46: ch:1:sboid:100617 | K46: 2561437 | L46: 1128934 | M46: 383 | N46: 46.31069768911773, 6.9380429534726
A47: 8504424 | B47: Aigle, Marais | C47: Transports Publics du Chablais (Bus) | D47: BUS | E47: VD | F47: Aigle | G47: 5401 | H47: Aigle | I47: ch:1:sboid:100617 | K47: 2561731 | L47: 1128118 | M47: 386 | N47: 46.30337426435545, 6.941926612804922
A48: 8505195 | B48: Aigle, Artisans | C48: Transports Publics du Chablais (Bus) | D48: BUS | E48: VD | F48: Aigle | G48: 5401 | H48: Aigle | I48: ch:1:sboid:100617 | K48: 2561542 | L48: 1129384 | M48: 383 | N48: 46.31475167092162, 6.939368689797344
A49: 8506403 | B49: Allaman, Château | C49: Automobiles MBC | D49: BUS | E49: VD | F49: Allaman | G49: 5851 | H49: Allaman | I49: ch:1:sboid:100566 | K49: 2519979.8 | L49: 1147218.3 | M49: 412.3 | N49: 46.47149624448524, 6.396761418716595
A50: 8579079 | B50: Allaman, gare | C50: PostAuto AG | D50: BUS | E50: VD | F50: Allaman | G50: 5851 | H50: Allaman | I50: ch:1:sboid:100602 | K50: 2520208 | L50: 1147702 | M50: 422 | N50: 46.47587445793586, 6.399648803097864
A51: 8506405 | B51: Allaman, Grand-Rue | C51: Automobiles MBC | D51: BUS | E51: VD | F51: Allaman | G51: 5851 | H51: Allaman | I51: ch:1:sboid:100566 | K51: 2519948 | L51: 1147024 | M51: 400 | N51: 46.46974489677017, 6.39638113595995
A52: 8501035 | B52: Allaman | C52: Schweizerische Bundesbahnen SBB | D52: TRAIN | E52: VD | F52: Allaman | G52: 5851 | H52: Allaman | I52: ch:1:sboid:100001 | K52: 2520211.5 | L52: 1147688.5 | M52: 421.868 | N52: 46.47575352079991, 6.399697079747334
A53: 8593870 | B53: Borex, Le Chanelet | C53: Transports Publics de la Région Nyonnaise | D53: BUS | E53: VD | F53: Arnex-sur-Nyon | G53: 5701 | H53: Arnex-sur-Nyon | I53: ch:1:sboid:100540 | K53: 2503482 | L53: 1137049 | M53: 464 | N53: 46.37785174714398, 6.184110330826253
A54: 8579310 | B54: Arnex-sur-Nyon | C54: Transports Publics de la Région Nyonnaise | D54: BUS | E54: VD | F54: Arnex-sur-Nyon | G54: 5701 | H54: Arnex-sur-Nyon | I54: ch:1:sboid:100540 | K54: 2504188 | L54: 1136690 | M54: 458 | N54: 46.37472404465474, 6.193359473751702
... A57: 8501107 | B57: Arnex | C57: Schweizerische Bundesbahnen SBB | D57: TRAIN | E57: VD | F57: Arnex-sur-Orbe | G57: 5743 | H57: Arnex-sur-Orbe | I57: ch:1:sboid:100001 | K57: 2529656.4 | L57: 1172287.2 | M57: 552.43 | N57: 46.6980776528438, 6.51890716328841
A58: 8582136 | B58: Bassins, gare | C58: PostAuto AG | D58: BUS | E58: VD | F58: Arzier-Le Muids | G58: 5702 | H58: Arzier-Le Muids | I58: ch:1:sboid:100602 | J58: (Bus) ohne Fahrplandaten 12.2016/2018 | K58: 2506599 | L58: 1146212 | M58: 749 | N58: 46.460710536633194, 6.222769946135759
A59: 8510725 | B59: Arzier, gare | C59: Nyon-St-Cergue-Morez Ersatzverkehr | D59: BUS | E59: VD | F59: Arzier-Le Muids | G59: 5702 | H59: Arzier-Le Muids | I59: ch:1:sboid:1100073 | K59: 2505684.7 | L59: 1146020 | M59: 844.5 | N59: 46.45885520350323, 6.210908344524017
A60: 8501065 | B60: Le Muids | C60: Nyon-St-Cergue-Morez | D60: TRAIN | E60: VD | F60: Arzier-Le Muids | G60: 5702 | H60: Arzier-Le Muids | I60: ch:1:sboid:100047 | K60: 2506024.1 | L60: 1145508.2 | M60: 712.2 | N60: 46.45429999374498, 6.215429993950875
A61: 8501057 | B61: La Chèvrerie-Monterêt | C61: Nyon-St-Cergue-Morez | D61: TRAIN | E61: VD | F61: Arzier-Le Muids | G61: 5702 | H61: Arzier-Le Muids | I61: ch:1:sboid:100047 | K61: 2503561.6 | L61: 1144900.1 | M61: 972.3 | N61: 46.44848000803234, 6.1835100034959805
A62: 8510732 | B62: Le Muids, bif. gare | C62: Nyon-St-Cergue-Morez Ersatzverkehr | D62: BUS | E62: VD | F62: Arzier-Le Muids | G62: 5702 | H62: Arzier-Le Muids | I62: ch:1:sboid:1100073 | K62: 2506274.5 | L62: 1145558.7 | M62: 696 | N62: 46.45478881938066, 6.218678202071574
A63: 8501064 | B63: Bassins | C63: Nyon-St-Cergue-Morez | D63: TRAIN | E63: VD | F63: Arzier-Le Muids | G63: 5702 | H63: Arzier-Le Muids | I63: ch:1:sboid:100047 | K63: 2506563.4 | L63: 1146196.9 | M63: 753.2 | N63: 46.460569994939625, 6.222309998990778
A64: 8501063 | B64: Arzier | C64: Nyon-St-Cergue-Morez | D64: TRAIN | E64: VD | F64: Arzier-Le Muids | G64: 5702 | H64: Arzier-Le Muids | I64: ch:1:sboid:100047 | K64: 2505741.3 | L64: 1145995.2 | M64: 839 | N64: 46.45863999465857, 6.211649997069147
A65: 8501172 | B65: Assens | C65: Lausanne-Echallens-Bercher | D65: TRAIN | E65: VD | F65: Assens | G65: 5511 | H65: Assens | I65: ch:1:sboid:100036 | K65: 2537329.8 | L65: 1162760.4 | M65: 622.2 | N65: 46.613149996036185, 6.620530001497214
A66: 8507624 | B66: Assens, gare | C66: Transports Publics de la Région Lausannoise sa | D66: BUS | E66: VD | F66: Assens | G66: 5511 | H66: Assens | I66: ch:1:sboid:100122 | K66: 2537353 | L66: 1162776 | M66: 624.1 | N66: 46.61329265676556, 6.620830172592719
A67: 8507655 | B67: Bioley-Orjulaz, chapelle | C67: PostAuto AG | D67: BUS | E67: VD | F67: Assens | G67: 5511 | H67: Bioley-Orjulaz | I67: ch:1:sboid:100602 | K67: 2535557 | L67: 1163718 | M67: 608 | N67: 46.62159484613944, 6.597254446720099
A68: 8501871 | B68: Montherod, village | C68: PostAuto AG | D68: BUS | E68: VD | F68: Aubonne | G68: 5422 | H68: Montherod | I68: ch:1:sboid:100602 | K68: 2517674 | L68: 1150284 | M68: 591 | N68: 46.49879181833153, 6.366196726582003
A69: 8579082 | B69: Montherod, Battoir | C69: PostAuto AG | D69: BUS | E69: VD | F69: Aubonne | G69: 5422 | H69: Montherod | I69: ch:1:sboid:100602 | K69: 2518059 | L69: 1150264 | M69: 585 | N69: 46.49865922549443, 6.371214970736722
A70: 8583896 | B70: Pizy, village | C70: PostAuto AG | D70: BUS | E70: VD | F70: Aubonne | G70: 5422 | H70: Pizy | I70: ch:1:sboid:100602 | K70: 2516812 | L70: 1149527 | M70: 644 | N70: 46.4918760803042, 6.355105446859123
... A79: 8501870 | B79: Aubonne, gare | C79: PostAuto AG | D79: BUS | E79: VD | F79: Aubonne | G79: 5422 | H79: Aubonne | I79: ch:1:sboid:100602 | K79: 2519720 | L79: 1149706 | M79: 500 | N79: 46.49384165966593, 6.392946852330956
A80: 8583458 | B80: Aubonne, Pré-Baulan | C80: PostAuto AG | D80: BUS | E80: VD | F80: Aubonne | G80: 5422 | H80: Aubonne | I80: ch:1:sboid:100602 | J80: (Bus) ohne Fahrplandaten 12.2018 | K80: 2517891 | L80: 1149939 | M80: 578 | N80: 46.495715310802204, 6.3690845491940635
A81: 8501868 | B81: Aubonne, La Levette | C81: PostAuto AG | D81: BUS | E81: VD | F81: Aubonne | G81: 5422 | H81: Aubonne | I81: ch:1:sboid:100602 | K81: 2520285 | L81: 1148725 | M81: 450 | N81: 46.48508534726661, 6.400474786753574
A82: 8504781 | B82: Avenches, poste | C82: PostAuto AG | D82: BUS | E82: VD | F82: Avenches | G82: 5451 | H82: Avenches | I82: ch:1:sboid:100602 | J82: (Bus) ohne Fahrplandaten 12.2016 [beibehalten] | K82: 2569587 | L82: 1192279 | M82: 469 | N82: 46.88093123399027, 7.039644445060025
A83: 8580759 | B83: Avenches, L'Eau-Noire | C83: PostAuto AG | D83: BUS | E83: VD | F83: Avenches | G83: 5451 | H83: Avenches | I83: ch:1:sboid:100602 | K83: 2569974 | L83: 1194631 | M83: 434 | N83: 46.90210546219474, 7.044565965496157
A84: 8583514 | B84: Avenches, Bibracte | C84: PostAuto AG | D84: BUS | E84: VD | F84: Avenches | G84: 5451 | H84: Avenches | I84: ch:1:sboid:100602 | K84: 2569533 | L84: 1191808 | M84: 455 | N84: 46.87669203340947, 7.038967602272889
A85: 8583516 | B85: Avenches, Milavy | C85: PostAuto AG | D85: BUS | E85: VD | F85: Avenches | G85: 5451 | H85: Avenches | I85: ch:1:sboid:100602 | K85: 2568987 | L85: 1191812 | M85: 443 | N85: 46.87670269402595, 7.031805029088613
A86: 8583894 | B86: Avenches, Hôtel de Ville | C86: PostAuto AG | D86: BUS | E86: VD | F86: Avenches | G86: 5451 | H86: Avenches | I86: ch:1:sboid:100602 | K86: 2569651 | L86: 1192165 | M86: 479 | N86: 46.879908719411, 7.040491661515199
A87: 8583726 | B87: Oleyres, Les Carrières | C87: PostAuto AG | D87: BUS | E87: VD | F87: Avenches | G87: 5451 | H87: Oleyres | I87: ch:1:sboid:100602 | K87: 2569387 | L87: 1189447 | M87: 551 | N87: 46.85544769454535, 7.037211355056684
A88: 8577825 | B88: Avenches, Faubourg | C88: Service d'automobiles TPF | D88: BUS | E88: VD | F88: Avenches | G88: 5451 | H88: Avenches | I88: ch:1:sboid:100633 | K88: 2569788 | L88: 1191968 | M88: 459 | N88: 46.87814293129093, 7.042301999667975
A89: 8504570 | B89: Avenches Plage | C89: Lacs de Neuchâtel et Morat | D89: BOAT | E89: VD | F89: Avenches | G89: 5451 | H89: Avenches | I89: ch:1:sboid:100148 | J89: Bedarfshalt | K89: 2570285.7 | L89: 1195028 | M89: 429 | N89: 46.90569097255497, 7.048630883762216
A90: 8504126 | B90: Avenches | C90: Schweizerische Bundesbahnen SBB | D90: TRAIN | E90: VD | F90: Avenches | G90: 5451 | H90: Avenches | I90: ch:1:sboid:100001 | K90: 2569686.7 | L90: 1192686.5 | M90: 437.75 | N90: 46.88460159766171, 7.0409253236567135
A91: 8583895 | B91: Avenches, EMS Marc-Aurèle | C91: PostAuto AG | D91: BUS | E91: VD | F91: Avenches | G91: 5451 | H91: Avenches | I91: ch:1:sboid:100602 | K91: 2569930 | L91: 1192346 | M91: 459 | N91: 46.88154955977959, 7.044139763990888
A92: 8583723 | B92: Avenches, Le Paon | C92: PostAuto AG | D92: BUS | E92: VD | F92: Avenches | G92: 5451 | H92: Avenches | I92: ch:1:sboid:100602 | K92: 2569119 | L92: 1191803 | M92: 445 | N92: 46.87662790003373, 7.0335371861811655
A93: 8579799 | B93: Avenches, Collège Sous-Ville | C93: PostAuto AG | D93: BUS | E93: VD | F93: Avenches | G93: 5451 | H93: Avenches | I93: ch:1:sboid:100602 | K93: 2569399 | L93: 1192116 | M93: 455 | N93: 46.87945637030937, 7.037189084661411
A94: 8583520 | B94: Avenches, route du Lac | C94: PostAuto AG | D94: BUS | E94: VD | F94: Avenches | G94: 5451 | H94: Avenches | I94: ch:1:sboid:100602 | K94: 2570575 | L94: 1193829 | M94: 435 | N94: 46.89491832506502, 7.052505446485615
A95: 8583515 | B95: Avenches, plage | C95: PostAuto AG | D95: BUS | E95: VD | F95: Avenches | G95: 5451 | H95: Avenches | I95: ch:1:sboid:100602 | K95: 2570225 | L95: 1194523 | M95: 434 | N95: 46.90114531575748, 7.0478671669097395
A96: 8583519 | B96: Avenches, Pré-Vert | C96: PostAuto AG | D96: BUS | E96: VD | F96: Avenches | G96: 5451 | H96: Avenches | I96: ch:1:sboid:100602 | K96: 2570085 | L96: 1192826 | M96: 441 | N96: 46.885874249733945, 7.046141603097115
A97: 8583517 | B97: Avenches, Joli-Val | C97: PostAuto AG | D97: BUS | E97: VD | F97: Avenches | G97: 5451 | H97: Avenches | I97: ch:1:sboid:100602 | K97: 2569782 | L97: 1191743 | M97: 462 | N97: 46.87611874572066, 7.042238249518947
A98: 8510877 | B98: Avenches, Bois de Châtel | C98: PostAuto AG | D98: BUS | E98: VD | F98: Avenches | G98: 5451 | H98: Avenches | I98: ch:1:sboid:100602 | K98: 2569854 | L98: 1190789 | M98: 518 | N98: 46.86754062953069, 7.043245980643021
A99: 8504886 | B99: Donatyre, village | C99: Service d'automobiles TPF | D99: BUS | E99: VD | F99: Avenches | G99: 5451 | H99: Donatyre | I99: ch:1:sboid:100633 | K99: 2570998.7 | L99: 1191663.2 | M99: 505.1 | N99: 46.87545544947485, 7.058203800744052
A100: 8583518 | B100: Avenches, Montmezard | C100: PostAuto AG | D100: BUS | E100: VD | F100: Avenches | G100: 5451 | H100: Avenches | I100: ch:1:sboid:100602 | K100: 2569531 | L100: 1192050 | M100: 469 | N100: 46.87886877066017, 7.038925144185087
A101: 8570514 | B101: Avenches, gare | C101: PostAuto AG | D101: BUS | E101: VD | F101: Avenches | G101: 5451 | H101: Avenches | I101: ch:1:sboid:100602 | K101: 2569711 | L101: 1192691 | M101: 438 | N101: 46.88464291658027, 7.041243716437001
... A103: 8583521 | B103: Oleyres, collège | C103: PostAuto AG | D103: BUS | E103: VD | F103: Avenches | G103: 5451 | H103: Oleyres | I103: ch:1:sboid:100602 | K103: 2569516 | L103: 1189199 | M103: 550 | N103: 46.853222829274074, 7.038919497690416
A104: 8596073 | B104: Donatyre, école | C104: Service d'automobiles TPF | D104: BUS | E104: VD | F104: Avenches | G104: 5451 | H104: Donatyre | I104: ch:1:sboid:100633 | J104: bis 2018: Donatyre, croisée | K104: 2571028.1 | L104: 1191856.9 | M104: 506.1 | N104: 46.877199368902204, 7.058576401856821
A105: 8579907 | B105: Ballaigues, cure | C105: Transports Vallée de Joux-Yverdon-Ste-Croix | D105: BUS | E105: VD | F105: Ballaigues | G105: 5744 | H105: Ballaigues | I105: ch:1:sboid:100694 | K105: 2521428.9 | L105: 1175837.2 | M105: 870 | N105: 46.72908859384227, 6.41073719984595
A106: 8579095 | B106: Ballaigues, poste | C106: Transports Vallée de Joux-Yverdon-Ste-Croix | D106: BUS | E106: VD | F106: Ballaigues | G106: 5744 | H106: Ballaigues | I106: ch:1:sboid:100694 | K106: 2521664 | L106: 1175838 | M106: 865 | N106: 46.72912385842083, 6.413812614743324
A107: 8579096 | B107: Ballaigues, Jura-Rosaly | C107: Transports Vallée de Joux-Yverdon-Ste-Croix | D107: BUS | E107: VD | F107: Ballaigues | G107: 5744 | H107: Ballaigues | I107: ch:1:sboid:100694 | K107: 2522804.8 | L107: 1176243 | M107: 830 | N107: 46.73289994623634, 6.428667573016799
A108: 8579094 | B108: Ballaigues, Vers-chez-Barrat | C108: Transports Vallée de Joux-Yverdon-Ste-Croix | D108: BUS | E108: VD | F108: Ballaigues | G108: 5744 | H108: Ballaigues | I108: ch:1:sboid:100694 | K108: 2521167 | L108: 1175799 | M108: 869 | N108: 46.72871439138754, 6.407318121946539
A109: 8579908 | B109: Ballaigues, collège | C109: Transports Vallée de Joux-Yverdon-Ste-Croix | D109: BUS | E109: VD | F109: Ballaigues | G109: 5744 | H109: Ballaigues | I109: ch:1:sboid:100694 | K109: 2521769 | L109: 1175971 | M109: 880 | N109: 46.73033250043713, 6.415163378827366
A110: 8579906 | B110: Ballaigues, Maillefer | C110: Transports Vallée de Joux-Yverdon-Ste-Croix | D110: BUS | E110: VD | F110: Ballaigues | G110: 5744 | H110: Ballaigues | I110: ch:1:sboid:100694 | K110: 2521979.3 | L110: 1175863.5 | M110: 863 | N110: 46.72939031007999, 6.417932705333199
A111: 8501095 | B111: Ballens | C111: Transports de la région Morges-Bière-Cossonay | D111: TRAIN | E111: VD | F111: Ballens | G111: 5423 | H111: Ballens | I111: ch:1:sboid:100012 | K111: 2518389 | L111: 1156218.6 | M111: 710.3 | N111: 46.552259998028006, 6.374459998099317
...

Sheet C
A1: Commune | B1: Nombre approx. d'établissements commerciaux | G1: Prompt ia google | H1: # donne moi simplement le nombre de commerce par commune pour cette liste
A2: Assens | B2: 70
A3: Belmont-sur-Lausanne | B3: 250
A4: Bourg-en-Lavaux | B4: 310
A5: Bremblens | B5: 35
A6: Bussigny | B6: 600
A7: Chavannes-près-Renens | B7: 480
A8: Cheseaux-sur-Lausanne | B8: 280
A9: Crissier | B9: 550
A10: Cugy | B10: 180
A11: Denges | B11: 140
A12: Echandens | B12: 220
A13: Ecublens | B13: 460
... A31: Vaulion | B31: 450

Sheet D
A1: Commune | B1: Indice (IQA) | C1: Qualité | F1: IQA (Indice de Qualité de l'Air) : Indicateur numérique standardisé mesurant la concentration de polluants atmosphériques (particules fines, ozone, | I1: ). Un score de 0 à 50 est considéré comme Bon (aucun risque). Plus l'indice est élevé, plus la pollution est importante. | S1: Source, prompt IA Google
A2: Assens | B2: 25 | C2: Bonne
A3: Belmont-sur-Lausanne | B3: 40 | C3: Bonne
A4: Bourg-en-Lavaux | B4: 35 | C4: Bonne
A5: Bremblens | B5: 25 | C5: Excellente
A6: Bussigny | B6: 35 | C6: Bonne
A7: Chavannes-près-Renens | B7: 35 | C7: Bonne
A8: Cheseaux-sur-Lausanne | B8: 20 | C8: Bonne
A9: Crissier | B9: 35 | C9: Bonne
A10: Cugy | B10: 30 | C10: Excellente
A11: Denges | B11: 29 | C11: Excellente
A12: Echandens | B12: 30 | C12: Excellente
A13: Ecublens | B13: 35 | C13: Bonne
... A31: Vaulion | B31: 22 | C31: Excellente

Sheet E
A1: Commune | B1: Places de jeux | C1: Terrains de sport / Centres | D1: Total places | G1: Prompt google ia
A2: Assens | B2: 1 | C2: 1 | D2: =B2+C2 -> 2 | G2: Simplement , il me faut : le nombre de place de jeux, place de sport pour chacune de ces communes. Merci d'avance !
A3: Belmont-sur-Lausanne | B3: 2 | C3: 2 | D3: =B3+C3 -> 4
A4: Bourg-en-Lavaux | B4: 3 | C4: 3 | D4: =B4+C4 -> 6
A5: Bremblens | B5: 1 | C5: 1 | D5: =B5+C5 -> 2
A6: Bussigny | B6: 6 | C6: 7 | D6: =B6+C6 -> 13
A7: Chavannes-près-Renens | B7: 5 | C7: 4 | D7: =B7+C7 -> 9
A8: Cheseaux-sur-Lausanne | B8: 4 | C8: 3 | D8: =B8+C8 -> 7
A9: Crissier | B9: 6 | C9: 9 | D9: =B9+C9 -> 15
A10: Cugy | B10: 2 | C10: 2 | D10: =B10+C10 -> 4
A11: Denges | B11: 2 | C11: 2 | D11: =B11+C11 -> 4
A12: Echandens | B12: 2 | C12: 3 | D12: =B12+C12 -> 5
A13: Ecublens | B13: 7 | C13: 11 | D13: =B13+C13 -> 18
A14: Epalinges | B14: 7 | C14: 5 | D14: =B14+C14 -> 12
... A31: Vaulion | B31: 2 | C31: 3 | D31: =B31+C31 -> 5

Sheet F
A1: 2026 | B1: Adopté en | C1: Valable jusqu'en | D1: Impôt rentrée argent | E1: Impôt spécial affecté | F1: Pour-cent total | G1: Immeubles | H1: Constr. non immatric. registre foncier | I1: Impôt personnel fixe | J1: Ventes, cessions, etc. | K1: Ligne directe ascendante | L1: Ligne directe descendante | M1: Ligne collatérale | N1: Entre non-parents | O1: Impôt compl. s/immeubles soc. et fond. | P1: * Chiens | Q1: * Impôt sur les divertissements
D2: 1 | E2: 2 | F2: 1+2 | G2: 0/00 | H2: 0/00 | I2: Fr. | J2: ct. | K2: ct. | L2: ct. | M2: ct. | N2: ct. | O2: ct. | P2: Fr. | Q2: 0/0
A4: DISTRICT D'AIGLE
A5: Aigle | B5: 2021 | C5: 2026 | D5: 66 | E5: - | F5: 66 | G5: 1.2 | H5: 0.5 | I5: - | J5: 50 | K5: 50 | L5: 50 | M5: 100 | N5: 100 | O5: 50 | P5: 100 | Q5: 5
A6: Bex | B6: 2024 | C6: 2026 | D6: 71 | E6: - | F6: 71 | G6: 1.25 | H6: 0.5 | I6: - | J6: 50 | K6: 50 | L6: 50 | M6: 100 | N6: 100 | O6: 50 | P6: 100 | Q6: 0
A7: Chessel | B7: 2025 | C7: 2026 | D7: 65 | E7: - | F7: =+D7 -> 65 | G7: 1 | H7: 0.5 | I7: - | J7: 50 | K7: - | L7: - | M7: 50 | N7: 100 | O7: 50 | P7: 100 | Q7: 0
A8: Corbeyrier | B8: 2025 | C8: 2026 | D8: 74 | E8: - | F8: 74 | G8: 1.5 | H8: 0.5 | I8: - | J8: 50 | K8: 50 | L8: 50 | M8: 100 | N8: 100 | O8: 50 | P8: 100 | Q8: 5
A9: Gryon | B9: 2025 | C9: 2026 | D9: 73.5 | E9: - | F9: 73.5 | G9: 1.5 | H9: 0.5 | I9: - | J9: 50 | K9: - | L9: - | M9: 50 | N9: 100 | O9: 50 | P9: 100 | Q9: 0
A10: Lavey-Morcles | B10: 2025 | C10: 2026 | D10: 71.5 | E10: - | F10: 71.5 | G10: 1.3 | H10: 0.5 | I10: - | J10: 50 | K10: 50 | L10: 50 | M10: 100 | N10: 100 | O10: 50 | P10: 100 | Q10: 75 cts
A11: Leysin | B11: 2025 | C11: 2026 | D11: 78 | E11: - | F11: 78 | G11: 1.5 | H11: 0.5 | I11: - | J11: 50 | K11: 50 | L11: - | M11: 100 | N11: 100 | O11: 50 | P11: 100 | Q11: 15
A12: Noville | B12: 2025 | C12: 2026 | D12: 75 | E12: - | F12: 75 | G12: 1.5 | H12: 0.5 | I12: - | J12: 50 | K12: - | L12: - | M12: 50 | N12: 100 | O12: 50 | P12: 100 | Q12: 0
A13: Ollon | B13: 2025 | C13: 2026 | D13: 68 | E13: - | F13: 68 | G13: 1.3 | H13: 0.5 | I13: - | J13: 50 | K13: - | L13: - | M13: 100 | N13: 100 | O13: 50 | P13: 100 | Q13: 0
A14: Ormont-Dessous | B14: 2024 | C14: 2026 | D14: 74.9 | E14: 2.1 | F14: 77 | G14: 1.5 | H14: 0.5 | I14: - | J14: 50 | K14: 50 | L14: 50 | M14: 100 | N14: 100 | O14: 50 | P14: 100 | Q14: 0
A15: Ormont-Dessus | B15: 2025 | C15: 2026 | D15: 73 | E15: 3 | F15: 76 | G15: 1.5 | H15: 0.5 | I15: - | J15: 50 | K15: 50 | L15: - | M15: 100 | N15: 100 | O15: 50 | P15: 100 | Q15: 0
A16: Rennaz | B16: 2025 | C16: 2027 | D16: 64 | E16: 0 | F16: 64 | G16: 1 | H16: 0.5 | I16: - | J16: 50 | K16: 50 | L16: - | M16: 50 | N16: 100 | O16: 50 | P16: 100 | Q16: 10
A17: Roche | B17: 2025 | C17: 2026 | D17: 66.5 | E17: - | F17: 66.5 | G17: 1.2 | H17: 0.5 | I17: - | J17: 50 | K17: 50 | L17: 50 | M17: 100 | N17: 100 | O17: 50 | P17: 150 | Q17: 0
A18: Villeneuve | B18: 2025 | C18: 2026 | D18: 66.5 | E18: - | F18: 66.5 | G18: 1 | H18: 0.5 | I18: - | J18: 50 | K18: 50 | L18: - | M18: 100 | N18: 100 | O18: 50 | P18: 115 | Q18: 0
A19: Yvorne | B19: 2025 | C19: 2026 | D19: 71.5 | E19: - | F19: 71.5 | G19: 1.5 | H19: 0.5 | I19: - | J19: 50 | K19: 50 | L19: 50 | M19: 100 | N19: 100 | O19: 50 | P19: 100 | Q19: 0
A21: DISTRICT DE LA BROYE-VULLY
A22: Avenches | B22: 2025 | C22: 2026 | D22: 65 | E22: - | F22: 65 | G22: 0.75 | H22: 0.5 | I22: - | J22: 50 | K22: 100 | L22: - | M22: 100 | N22: 100 | O22: 50 | P22: 100 | Q22: 0
A23: Bussy-sur-Moudon | B23: 2025 | C23: 2026 | D23: 78.5 | E23: 0 | F23: 78.5 | G23: 1 | H23: 0.5 | I23: 10 | J23: 50 | K23: 50 | L23: 50 | M23: 100 | N23: 100 | O23: 50 | P23: 60 | Q23: 10
A24: Champtauroz | B24: 2025 | C24: 2026 | D24: 77 | E24: 0 | F24: 77 | G24: 0.8 | H24: 0.5 | I24: - | J24: 50 | K24: - | L24: - | M24: 100 | N24: 100 | O24: 50 | P24: 40 | Q24: 0
A25: Chavannes-sur-Moudon | B25: 2025 | C25: 2026 | D25: 70 | E25: 0 | F25: 70 | G25: 1 | H25: 0 | I25: - | J25: 50 | K25: - | L25: - | M25: - | N25: - | O25: 50 | P25: 60 | Q25: 0
A26: Chevroux | B26: 2025 | C26: 2026 | D26: 68.5 | E26: - | F26: 68.5 | G26: 1.2 | H26: 0.5 | I26: - | J26: 50 | K26: 50 | L26: 50 | M26: 100 | N26: 100 | O26: - | P26: 1.0p/Fr | Q26: 10
A27: Corcelles-le-Jorat | B27: 2025 | C27: 2027 | D27: 75 | E27: - | F27: 75 | G27: 1 | H27: 0.5 | I27: - | J27: 50 | K27: 40 | L27: 20 | M27: 100 | N27: 100 | O27: 50 | P27: 40 | Q27: 10
A28: Corcelles-près-Payerne | B28: 2025 | C28: 2026 | D28: 65 | E28: - | F28: 65 | G28: 0.7 | H28: - | I28: - | J28: 50 | K28: 50 | L28: 50 | M28: 100 | N28: 100 | O28: 50 | P28: 60 | Q28: 10
A29: Cudrefin | B29: 2025 | C29: 2026 | D29: 59 | E29: - | F29: 59 | G29: 1.5 | H29: 0.5 | I29: - | J29: 50 | K29: 100 | L29: 100 | M29: 100 | N29: 100 | O29: 50 | P29: 100 | Q29: 10
A30: Curtilles | B30: 2025 | C30: 2026 | D30: 71 | E30: 0 | F30: 71 | G30: 0.5 | H30: 0.5 | I30: - | J30: 50 | K30: - | L30: - | M30: 60 | N30: 100 | O30: 50 | P30: 1.0p/Fr | Q30: 0
A31: Dompierre | B31: 2024 | C31: 2026 | D31: 78 | E31: - | F31: 78 | G31: 1 | H31: 0.5 | I31: 10 | J31: 50 | K31: 50 | L31: - | M31: - | N31: 100 | O31: 50 | P31: 90 | Q31: 0
A32: Faoug | B32: 2025 | C32: 2026 | D32: 65 | E32: - | F32: 65 | G32: 1.5 | H32: 0.5 | I32: - | J32: 50 | K32: 80 | L32: 80 | M32: 100 | N32: 100 | O32: 50 | P32: 1.0p/Fr | Q32: 0
A33: Grandcour | B33: 2025 | C33: 2026 | D33: 72 | E33: - | F33: 72 | G33: 1 | H33: 0.5 | I33: 10 | J33: 50 | K33: - | L33: - | M33: 100 | N33: 100 | O33: 50 | P33: 60 | Q33: 0
A34: Henniez | B34: 2025 | C34: 2026 | D34: 69 | E34: - | F34: 69 | G34: 1 | H34: 0.5 | I34: - | J34: 50 | K34: - | L34: - | M34: - | N34: - | O34: 30 | P34: 40 | Q34: 0
A35: Hermenches | B35: 2025 | C35: 2026 | D35: 78 | E35: - | F35: 78 | G35: 0.6 | H35: 0.5 | I35: 10 | J35: 50 | K35: - | L35: - | M35: 90 | N35: 100 | O35: 50 | P35: 100 | Q35: 10
A36: Lovatens | B36: 2023 | C36: 2026 | D36: 75 | E36: - | F36: 75 | G36: 0.7 | H36: 0.5 | I36: - | J36: 50 | K36: 50 | L36: - | M36: 100 | N36: 100 | O36: 50 | P36: 60 | Q36: 100 cts
A37: Lucens | B37: 2025 | C37: 2027 | D37: 69.5 | E37: - | F37: 69.5 | G37: 1.1 | H37: 0.5 | I37: - | J37: 50 | K37: 50 | L37: 50 | M37: 100 | N37: 100 | O37: 50 | P37: 100 | Q37: 10
A38: Missy | B38: 2025 | C38: 2026 | D38: 69 | E38: - | F38: 69 | G38: 1 | H38: - | I38: 10 | J38: 50 | K38: 50 | L38: - | M38: 100 | N38: 100 | O38: 50 | P38: 100 | Q38: -
A39: Moudon | B39: 2025 | C39: 2026 | D39: 72.5 | E39: - | F39: 72.5 | G39: 1 | H39: 0.5 | I39: 10 | J39: 50 | K39: 50 | L39: 50 | M39: 100 | N39: 100 | O39: 50 | P39: 120 | Q39: 10
A40: Payerne | B40: 2022 | C40: 2026 | D40: 70 | E40: - | F40: 70 | G40: 1 | H40: 0.5 | I40: - | J40: 50 | K40: 100 | L40: - | M40: 100 | N40: 100 | O40: 50 | P40: 50 | Q40: 10
A41: Prévonloup | B41: 2025 | C41: 2026 | D41: 72.5 | E41: - | F41: 72.5 | G41: 1 | H41: - | I41: - | J41: 50 | K41: - | L41: - | M41: 50 | N41: 100 | O41: 50 | P41: 50 | Q41: -
A42: Ropraz | B42: 2024 | C42: 2026 | D42: 77.5 | E42: - | F42: 77.5 | G42: 1 | H42: 0.5 | I42: - | J42: 50 | K42: 50 | L42: 50 | M42: 100 | N42: 100 | O42: 50 | P42: 60 | Q42: 10
A43: Rossenges | B43: 2025 | C43: 2026 | D43: 65 | E43: 0 | F43: 65 | G43: 0.8 | H43: 0.5 | I43: - | J43: 50 | K43: - | L43: - | M43: 50 | N43: 50 | O43: 50 | P43: - | Q43: 0
A44: Syens | B44: 2024 | C44: 2026 | D44: 65 | E44: 0 | F44: 65 | G44: 1 | H44: 0.5 | I44: - | J44: 50 | K44: - | L44: - | M44: 100 | N44: 100 | O44: 50 | P44: 100 | Q44: 0
A45: Trey | B45: 2025 | C45: 2026 | D45: 78 | E45: - | F45: 78 | G45: 1 | H45: - | I45: 10 | J45: 50 | K45: 50 | L45: - | M45: 100 | N45: 100 | O45: 50 | P45: 50 | Q45: 0
A46: Treytorrens | B46: 2025 | C46: 2026 | D46: 81.5 | E46: 0 | F46: 81.5 | G46: 1.5 | H46: - | I46: - | J46: 50 | K46: 50 | L46: 50 | M46: 100 | N46: 100 | O46: - | P46: 30 | Q46: 10
A47: Valbroye | B47: 2025 | C47: 2026 | D47: 70.5 | E47: - | F47: 70.5 | G47: 0.6 | H47: - | I47: - | J47: 50 | K47: 50 | L47: 50 | M47: 100 | N47: 100 | O47: 50 | P47: 0.5p/Fr | Q47: 0
A48: Villars-le-Comte | B48: 2024 | C48: 2026 | D48: 68 | E48: 0 | F48: 68 | G48: 1 | H48: 0.5 | I48: 10 | J48: 50 | K48: 30 | L48: 30 | M48: 100 | N48: 100 | O48: 50 | P48: 0.5p/Fr | Q48: 0
A49: Villarzel | B49: 2024 | C49: 2026 | D49: 75 | E49: - | F49: 75 | G49: 1 | H49: - | I49: - | J49: 50 | K49: - | L49: - | M49: 100 | N49: 100 | O49: 50 | P49: 60 | Q49: 0
A50: Vucherens | B50: 2025 | C50: 2026 | D50: 75 | E50: - | F50: 75 | G50: 1 | H50: 0.5 | I50: - | J50: 50 | K50: 50 | L50: - | M50: 100 | N50: 100 | O50: 50 | P50: 1.0p/Fr | Q50: 0
A51: Vulliens | B51: 2025 | C51: 2026 | D51: 74 | E51: - | F51: 74 | G51: 1 | H51: 0.5 | I51: - | J51: 50 | K51: 80 | L51: 60 | M51: 100 | N51: 100 | O51: - | P51: 100 | Q51: 10
A52: Vully-les-Lacs | B52: 2025 | C52: 2027 | D52: 67 | E52: - | F52: 67 | G52: 1.5 | H52: 0.5 | I52: - | J52: 50 | K52: 50 | L52: - | M52: 100 | N52: 100 | O52: 50 | P52: 100 | Q52: 0
A54: DISTRICT DU GROS-DE VAUD
A55: Assens | B55: 2025 | C55: 2026 | D55: 70 | E55: 0 | F55: 70 | G55: 1 | H55: - | I55: - | J55: 50 | K55: - | L55: - | M55: 100 | N55: 100 | O55: 50 | P55: 150 | Q55: 0
A56: Bercher | B56: 2025 | C56: 2026 | D56: 79 | E56: - | F56: 79 | G56: 1 | H56: - | I56: - | J56: 50 | K56: 50 | L56: 50 | M56: 100 | N56: 100 | O56: 50 | P56: 100 | Q56: 10
A57: Bettens | B57: 2025 | C57: 2026 | D57: 70 | E57: - | F57: 70 | G57: 0.9 | H57: - | I57: - | J57: 50 | K57: - | L57: - | M57: 100 | N57: 100 | O57: 50 | P57: 100 | Q57: 0
A58: Bottens | B58: 2024 | C58: 2026 | D58: 72.5 | E58: 0 | F58: 72.5 | G58: 1 | H58: - | I58: - | J58: 50 | K58: 50 | L58: 50 | M58: 100 | N58: 100 | O58: 50 | P58: 100 | Q58: 0
A59: Boulens | B59: 2025 | C59: 2026 | D59: 71.5 | E59: 0 | F59: 71.5 | G59: 1 | H59: - | I59: - | J59: 50 | K59: 50 | L59: - | M59: 50 | N59: 100 | O59: 50 | P59: 200 | Q59: 0
A60: Bournens | B60: 2025 | C60: 2026 | D60: 65 | E60: - | F60: 65 | G60: 1 | H60: 0.5 | I60: - | J60: 50 | K60: - | L60: - | M60: - | N60: 100 | O60: 50 | P60: 60 | Q60: 0
A61: Boussens | B61: 2025 | C61: 2027 | D61: 64 | E61: - | F61: 64 | G61: 1 | H61: 0.5 | I61: - | J61: 50 | K61: - | L61: - | M61: 100 | N61: 100 | O61: 50 | P61: 80 | Q61: 0
A62: Bretigny-sur-Morrens | B62: 2025 | C62: 2026 | D62: 76 | E62: - | F62: 76 | G62: 1 | H62: - | I62: - | J62: 50 | K62: - | L62: - | M62: 100 | N62: 100 | O62: 50 | P62: 100 | Q62: 0
A63: Cugy | B63: 2024 | C63: 2026 | D63: 76 | E63: - | F63: 76 | G63: 1.2 | H63: 0.5 | I63: - | J63: 50 | K63: - | L63: - | M63: 100 | N63: 100 | O63: 50 | P63: 100 | Q63: 0
A64: Daillens | B64: 2024 | C64: 2026 | D64: 66 | E64: 0 | F64: 66 | G64: 1.2 | H64: 0.5 | I64: - | J64: 50 | K64: - | L64: - | M64: 100 | N64: 100 | O64: 50 | P64: 1.0p/Fr | Q64: 5
A65: Echallens | B65: 2023 | C65: 2026 | D65: 72.5 | E65: 0 | F65: 72.5 | G65: 1 | H65: 0.5 | I65: - | J65: 50 | K65: 50 | L65: 50 | M65: 100 | N65: 100 | O65: 50 | P65: 70 | Q65: 0
A66: Essertines-sur-Yverdon | B66: 2025 | C66: 2026 | D66: 72 | E66: - | F66: 72 | G66: 1 | H66: - | I66: - | J66: 50 | K66: 50 | L66: 50 | M66: 100 | N66: 100 | O66: 50 | P66: 100 | Q66: 0
A67: Etagnières | B67: 2025 | C67: 2026 | D67: 73 | E67: - | F67: 73 | G67: 1 | H67: 0.5 | I67: - | J67: 50 | K67: - | L67: - | M67: 50 | N67: 100 | O67: 50 | P67: 100 | Q67: 0
A68: Fey | B68: 2025 | C68: 2026 | D68: 75 | E68: 0 | F68: 75 | G68: 1 | H68: - | I68: - | J68: 50 | K68: - | L68: - | M68: 100 | N68: 100 | O68: 50 | P68: 75 | Q68: 0
A69: Froideville | B69: 2025 | C69: 2026 | D69: 72 | E69: - | F69: 72 | G69: 1.25 | H69: 0.5 | I69: - | J69: 50 | K69: - | L69: - | M69: 100 | N69: 100 | O69: 50 | P69: 75 | Q69: 0
A70: Goumoëns | B70: 2025 | C70: 2026 | D70: 75.5 | E70: - | F70: 75.5 | G70: 1 | H70: - | I70: - | J70: 50 | K70: 20 | L70: 20 | M70: 50 | N70: 100 | O70: 50 | P70: 100 | Q70: 0
A71: Jorat-Menthue | B71: 2025 | C71: 2026 | D71: 70.5 | E71: - | F71: 70.5 | G71: 1 | H71: 0.5 | I71: - | J71: 50 | K71: 50 | L71: 50 | M71: 100 | N71: 100 | O71: 50 | P71: 150 | Q71: 0
A72: Lussery-Villars | B72: 2025 | C72: 2026 | D72: 75 | E72: - | F72: 75 | G72: 1 | H72: 0.5 | I72: - | J72: 50 | K72: 30 | L72: 30 | M72: 50 | N72: 100 | O72: 50 | P72: 60 | Q72: 0
A73: Mex | B73: 2025 | C73: 2026 | D73: 59.5 | E73: 0 | F73: 59.5 | G73: 1 | H73: 0.5 | I73: - | J73: 50 | K73: 50 | L73: - | M73: 50 | N73: 100 | O73: 50 | P73: 60 | Q73: 0
A74: Montanaire | B74: 2024 | C74: 2026 | D74: 70 | E74: - | F74: 70 | G74: 1 | H74: - | I74: - | J74: 50 | K74: - | L74: - | M74: 100 | N74: 100 | O74: 50 | P74: 100 | Q74: 0
A75: Montilliez | B75: 2025 | C75: 2026 | D75: 72.5 | E75: - | F75: 72.5 | G75: 0.8 | H75: - | I75: - | J75: 50 | K75: 20 | L75: 20 | M75: 100 | N75: 100 | O75: 50 | P75: 1.0p/Fr | Q75: 0
A76: Morrens | B76: 2025 | C76: 2026 | D76: 74 | E76: - | F76: 74 | G76: 1 | H76: 0.5 | I76: - | J76: 50 | K76: - | L76: - | M76: 100 | N76: 100 | O76: 50 | P76: 100 | Q76: 0
A77: Ogens | B77: 2025 | C77: 2026 | D77: 76 | E77: 0 | F77: 76 | G77: 1.5 | H77: - | I77: - | J77: 50 | K77: 50 | L77: 50 | M77: 100 | N77: 100 | O77: 50 | P77: 0.5p/Fr | Q77: 0
A78: Oppens | B78: 2025 | C78: 2027 | D78: 79 | E78: 0 | F78: 79 | G78: 1 | H78: - | I78: - | J78: 50 | K78: 30 | L78: 30 | M78: 50 | N78: 100 | O78: - | P78: 90 | Q78: 10
A79: Oulens-sous-Echallens | B79: 2025 | C79: 2026 | D79: 71 | E79: - | F79: 71 | G79: 1 | H79: 0.5 | I79: - | J79: 50 | K79: - | L79: - | M79: 100 | N79: 100 | O79: 50 | P79: 120 | Q79: 0
A80: Pailly | B80: 2025 | C80: 2026 | D80: 76 | E80: 0 | F80: 76 | G80: 1.2 | H80: - | I80: - | J80: 50 | K80: 50 | L80: 50 | M80: 100 | N80: 100 | O80: 50 | P80: 60 | Q80: 0
A81: Penthalaz | B81: 2025 | C81: 2026 | D81: 72.5 | E81: - | F81: 72.5 | G81: 1 | H81: 0.5 | I81: - | J81: 50 | K81: 60 | L81: 60 | M81: 100 | N81: 100 | O81: 50 | P81: 60 | Q81: 0
A82: Penthaz | B82: 2025 | C82: 2026 | D82: 69.5 | E82: 0 | F82: 69.5 | G82: 1 | H82: 0.5 | I82: - | J82: 50 | K82: 70 | L82: 50 | M82: 70 | N82: 100 | O82: 50 | P82: 1.0p/Fr | Q82: 0
A83: Penthéréaz | B83: 2025 | C83: 2026 | D83: 74 | E83: 0 | F83: 74 | G83: 1 | H83: - | I83: - | J83: 50 | K83: - | L83: - | M83: - | N83: - | O83: 50 | P83: 1.0p/Fr | Q83: 0
A84: Poliez-Pittet | B84: 2025 | C84: 2026 | D84: 73 | E84: - | F84: 73 | G84: 1 | H84: - | I84: - | J84: 50 | K84: 50 | L84: 50 | M84: 100 | N84: 100 | O84: 50 | P84: 100 | Q84: 5
A85: Rueyres | B85: 2024 | C85: 2026 | D85: 73 | E85: 0 | F85: 73 | G85: 1 | H85: 0.5 | I85: - | J85: 50 | K85: - | L85: - | M85: 100 | N85: 100 | O85: 50 | P85: 100 | Q85: 0
A86: Saint-Barthélemy | B86: 2025 | C86: 2026 | D86: 77 | E86: - | F86: 77 | G86: 1.5 | H86: - | I86: - | J86: 50 | K86: 30 | L86: 30 | M86: 30 | N86: 100 | O86: 50 | P86: 150 | Q86: 0
A87: Sullens | B87: 2021 | C87: 2026 | D87: 64 | E87: - | F87: 64 | G87: 1 | H87: 0.5 | I87: - | J87: 50 | K87: 50 | L87: 50 | M87: 100 | N87: 100 | O87: - | P87: 50 | Q87: 0
A88: Villars-le-Terroir | B88: 2025 | C88: 2026 | D88: 76 | E88: - | F88: 76 | G88: 1 | H88: 0.5 | I88: 10 | J88: 50 | K88: 10 | L88: 10 | M88: 100 | N88: 100 | O88: 50 | P88: 130 | Q88: 0
A89: Vuarrens | B89: 2025 | C89: 2026 | D89: 73.5 | E89: 0 | F89: 73.5 | G89: 0.8 | H89: - | I89: - | J89: 50 | K89: 30 | L89: 30 | M89: 100 | N89: 100 | O89: 50 | P89: 100 | Q89: 0
A90: Vufflens-la-Ville | B90: 2025 | C90: 2026 | D90: 63 | E90: 2 | F90: 65 | G90: 1.2 | H90: 0.5 | I90: - | J90: 50 | K90: 50 | L90: 50 | M90: 100 | N90: 100 | O90: 50 | P90: 0.80p/Fr | Q90: 10
A92: DISTRICT DU JURA-NORD VAUDOIS
A93: Agiez | B93: 2021 | C93: 2026 | D93: 76 | E93: - | F93: 76 | G93: 0.5 | H93: 0.5 | I93: - | J93: 50 | K93: 30 | L93: 30 | M93: 80 | N93: 100 | O93: 50 | P93: 0.80p/Fr | Q93: 0
A94: Arnex-sur-Orbe | B94: 2025 | C94: 2026 | D94: 71 | E94: 0 | F94: 71 | G94: 0.8 | H94: - | I94: - | J94: 50 | K94: 100 | L94: 100 | M94: 100 | N94: 100 | O94: - | P94: 70 | Q94: 0
A95: Ballaigues | B95: 2025 | C95: 2026 | D95: 65 | E95: - | F95: 65 | G95: 1 | H95: 0.5 | I95: - | J95: 50 | K95: 50 | L95: 50 | M95: 100 | N95: 100 | O95: - | P95: 50 | Q95: 0
A96: Baulmes | B96: 2025 | C96: 2026 | D96: 76.5 | E96: - | F96: 76.5 | G96: 1 | H96: - | I96: - | J96: 50 | K96: 100 | L96: 100 | M96: 100 | N96: 100 | O96: - | P96: 50 | Q96: 0
A97: Bavois | B97: 2025 | C97: 2026 | D97: 72 | E97: - | F97: 72 | G97: 1.2 | H97: 0.5 | I97: - | J97: 50 | K97: 100 | L97: 50 | M97: 100 | N97: 100 | O97: 50 | P97: 90 | Q97: 10
A98: Belmont-sur-Yverdon | B98: 2025 | C98: 2026 | D98: 70 | E98: - | F98: 70 | G98: 1 | H98: - | I98: - | J98: 50 | K98: 50 | L98: 50 | M98: 100 | N98: 100 | O98: - | P98: 60 | Q98: 0
A99: Bioley-Magnoux | B99: 2025 | C99: 2026 | D99: 72 | E99: 0 | F99: 72 | G99: 0.7 | H99: - | I99: - | J99: 50 | K99: 50 | L99: 30 | M99: 100 | N99: 100 | O99: - | P99: 80 | Q99: 20 cts
A100: Bofflens | B100: 2025 | C100: 2026 | D100: 69 | E100: - | F100: 69 | G100: 1 | H100: - | I100: - | J100: 50 | K100: 40 | L100: 40 | M100: 70 | N100: 100 | O100: - | P100: 40 | Q100: 0
A101: Bonvillars | B101: 2025 | C101: 2026 | D101: 67 | E101: 0 | F101: 67 | G101: 1 | H101: - | I101: - | J101: 50 | K101: - | L101: - | M101: 60 | N101: 100 | O101: 40 | P101: 100 | Q101: 0
A102: Bretonnières | B102: 2024 | C102: 2026 | D102: 69 | E102: 0 | F102: 69 | G102: 0.6 | H102: 0.5 | I102: 10 | J102: 50 | K102: - | L102: - | M102: 80 | N102: 100 | O102: - | P102: 50 | Q102: 0
A103: Bullet | B103: 2025 | C103: 2026 | D103: 75 | E103: - | F103: 75 | G103: 1 | H103: 0.5 | I103: - | J103: 50 | K103: 80 | L103: 80 | M103: 90 | N103: 100 | O103: 50 | P103: 1.0p/Fr | Q103: 10
A104: Chamblon | B104: 2025 | C104: 2026 | D104: 66 | E104: - | F104: 66 | G104: 1 | H104: - | I104: - | J104: 50 | K104: 40 | L104: - | M104: 100 | N104: 100 | O104: 50 | P104: 1.0p/Fr | Q104: 10
...

Sheet G
A1: Commune | B1: Total logements vacants | I1: Logements vacants à vendre | P1: Maisons individuelles vacantes | W1: Logements vacants récents
A2: Aclens | B2: 8 | C2: 1 | D2: 1 | E2: 3 | F2: 3 | G2: - | H2: - | I2: - | J2: - | K2: - | L2: - | M2: - | N2: - | O2: - | P2: - | Q2: - | R2: - | S2: - | T2: - | U2: - | V2: - | W2: 4 | X2: - | Y2: 1 | Z2: 1 | AA2: 2 | AB2: - | AC2: -
A3: Agiez | B3: - | C3: - | D3: - | E3: - | F3: - | G3: - | H3: - | I3: - | J3: - | K3: - | L3: - | M3: - | N3: - | O3: - | P3: - | Q3: - | R3: - | S3: - | T3: - | U3: - | V3: - | W3: - | X3: - | Y3: - | Z3: - | AA3: - | AB3: - | AC3: -
A4: Aigle | B4: 43 | C4: 3 | D4: 14 | E4: 17 | F4: 8 | G4: 1 | H4: - | I4: 3 | J4: - | K4: - | L4: - | M4: 3 | N4: - | O4: - | P4: 5 | Q4: - | R4: - | S4: 2 | T4: 2 | U4: 1 | V4: - | W4: - | X4: - | Y4: - | Z4: - | AA4: - | AB4: - | AC4: -
A5: Aigle (district) | B5: 457 | C5: 41 | D5: 74 | E5: 126 | F5: 97 | G5: 46 | H5: 73 | I5: 235 | J5: 7 | K5: 25 | L5: 50 | M5: 56 | N5: 29 | O5: 68 | P5: 123 | Q5: - | R5: 2 | S5: 14 | T5: 21 | U5: 21 | V5: 65 | W5: 19 | X5: 1 | Y5: 2 | Z5: 6 | AA5: 4 | AB5: 3 | AC5: 3
A6: Allaman | B6: 2 | C6: - | D6: - | E6: 2 | F6: - | G6: - | H6: - | I6: 1 | J6: - | K6: - | L6: 1 | M6: - | N6: - | O6: - | P6: - | Q6: - | R6: - | S6: - | T6: - | U6: - | V6: - | W6: - | X6: - | Y6: - | Z6: - | AA6: - | AB6: - | AC6: -
A7: Arnex-sur-Nyon | B7: 2 | C7: - | D7: - | E7: 2 | F7: - | G7: - | H7: - | I7: 1 | J7: - | K7: - | L7: 1 | M7: - | N7: - | O7: - | P7: - | Q7: - | R7: - | S7: - | T7: - | U7: - | V7: - | W7: - | X7: - | Y7: - | Z7: - | AA7: - | AB7: - | AC7: -
A8: Arnex-sur-Orbe | B8: 2 | C8: - | D8: - | E8: - | F8: 1 | G8: 1 | H8: - | I8: 1 | J8: - | K8: - | L8: - | M8: - | N8: 1 | O8: - | P8: 1 | Q8: - | R8: - | S8: - | T8: - | U8: 1 | V8: - | W8: - | X8: - | Y8: - | Z8: - | AA8: - | AB8: - | AC8: -
A9: Arzier-Le Muids | B9: 2 | C9: - | D9: - | E9: - | F9: - | G9: 1 | H9: 1 | I9: 1 | J9: - | K9: - | L9: - | M9: - | N9: - | O9: 1 | P9: 2 | Q9: - | R9: - | S9: - | T9: - | U9: 1 | V9: 1 | W9: - | X9: - | Y9: - | Z9: - | AA9: - | AB9: - | AC9: -
A10: Assens | B10: 100 | C10: - | D10: - | E10: - | F10: - | G10: - | H10: - | I10: - | J10: - | K10: - | L10: - | M10: - | N10: - | O10: - | P10: - | Q10: - | R10: - | S10: - | T10: - | U10: - | V10: - | W10: - | X10: - | Y10: - | Z10: - | AA10: - | AB10: - | AC10: -
A11: Aubonne | B11: 29 | C11: - | D11: 1 | E11: 3 | F11: 10 | G11: 6 | H11: 9 | I11: 15 | J11: - | K11: - | L11: 1 | M11: 2 | N11: 4 | O11: 8 | P11: 10 | Q11: - | R11: - | S11: - | T11: 3 | U11: 2 | V11: 5 | W11: - | X11: - | Y11: - | Z11: - | AA11: - | AB11: - | AC11: -
A12: Avenches | B12: 4 | C12: - | D12: 4 | E12: - | F12: - | G12: - | H12: - | I12: - | J12: - | K12: - | L12: - | M12: - | N12: - | O12: - | P12: - | Q12: - | R12: - | S12: - | T12: - | U12: - | V12: - | W12: - | X12: - | Y12: - | Z12: - | AA12: - | AB12: - | AC12: -
A13: Ballaigues | B13: 19 | C13: 5 | D13: 4 | E13: 6 | F13: 2 | G13: 1 | H13: 1 | I13: - | J13: - | K13: - | L13: - | M13: - | N13: - | O13: - | P13: 1 | Q13: - | R13: - | S13: - | T13: - | U13: - | V13: 1 | W13: 1 | X13: - | Y13: - | Z13: 1 | AA13: - | AB13: - | AC13: -
A14: Ballens | B14: 2 | C14: - | D14: 1 | E14: - | F14: - | G14: - | H14: 1 | I14: 1 | J14: - | K14: - | L14: - | M14: - | N14: - | O14: 1 | P14: 1 | Q14: - | R14: - | S14: - | T14: - | U14: - | V14: 1 | W14: - | X14: - | Y14: - | Z14: - | AA14: - | AB14: - | AC14: -
A15: Bassins | B15: 9 | C15: - | D15: - | E15: 3 | F15: - | G15: 6 | H15: - | I15: 5 | J15: - | K15: - | L15: - | M15: - | N15: 5 | O15: - | P15: 6 | Q15: - | R15: - | S15: - | T15: - | U15: 6 | V15: - | W15: - | X15: - | Y15: - | Z15: - | AA15: - | AB15: - | AC15: -
A16: Baulmes | B16: 16 | C16: - | D16: 3 | E16: 3 | F16: 5 | G16: 2 | H16: 3 | I16: 8 | J16: - | K16: 2 | L16: 2 | M16: - | N16: 1 | O16: 3 | P16: 4 | Q16: - | R16: - | S16: - | T16: - | U16: 1 | V16: 3 | W16: - | X16: - | Y16: - | Z16: - | AA16: - | AB16: - | AC16: -
A17: Bavois | B17: - | C17: - | D17: - | E17: - | F17: - | G17: - | H17: - | I17: - | J17: - | K17: - | L17: - | M17: - | N17: - | O17: - | P17: - | Q17: - | R17: - | S17: - | T17: - | U17: - | V17: - | W17: - | X17: - | Y17: - | Z17: - | AA17: - | AB17: - | AC17: -
A18: Begnins | B18: 12 | C18: - | D18: 2 | E18: 2 | F18: 3 | G18: - | H18: 5 | I18: 5 | J18: - | K18: - | L18: 1 | M18: - | N18: - | O18: 4 | P18: 1 | Q18: - | R18: - | S18: - | T18: - | U18: - | V18: 1 | W18: - | X18: - | Y18: - | Z18: - | AA18: - | AB18: - | AC18: -
A19: Belmont-sur-Lausanne | B19: 5 | C19: 1 | D19: 1 | E19: - | F19: 3 | G19: - | H19: - | I19: 3 | J19: 1 | K19: - | L19: - | M19: 2 | N19: - | O19: - | P19: 2 | Q19: - | R19: - | S19: - | T19: 2 | U19: - | V19: - | W19: - | X19: - | Y19: - | Z19: - | AA19: - | AB19: - | AC19: -
A20: Belmont-sur-Yverdon | B20: 5 | C20: 1 | D20: - | E20: 1 | F20: 2 | G20: 1 | H20: - | I20: 4 | J20: - | K20: - | L20: 1 | M20: 2 | N20: 1 | O20: - | P20: - | Q20: - | R20: - | S20: - | T20: - | U20: - | V20: - | W20: - | X20: - | Y20: - | Z20: - | AA20: - | AB20: - | AC20: -
A21: Bercher | B21: 7 | C21: 1 | D21: - | E21: 1 | F21: 1 | G21: - | H21: 4 | I21: 5 | J21: - | K21: - | L21: 1 | M21: 1 | N21: - | O21: 3 | P21: 4 | Q21: - | R21: - | S21: - | T21: - | U21: - | V21: 4 | W21: - | X21: - | Y21: - | Z21: - | AA21: - | AB21: - | AC21: -
A22: Berolle | B22: 2 | C22: - | D22: - | E22: 1 | F22: - | G22: - | H22: 1 | I22: - | J22: - | K22: - | L22: - | M22: - | N22: - | O22: - | P22: 1 | Q22: - | R22: - | S22: - | T22: - | U22: - | V22: 1 | W22: - | X22: - | Y22: - | Z22: - | AA22: - | AB22: - | AC22: -
A23: Bettens | B23: - | C23: - | D23: - | E23: - | F23: - | G23: - | H23: - | I23: - | J23: - | K23: - | L23: - | M23: - | N23: - | O23: - | P23: - | Q23: - | R23: - | S23: - | T23: - | U23: - | V23: - | W23: - | X23: - | Y23: - | Z23: - | AA23: - | AB23: - | AC23: -
A24: Bex | B24: 36 | C24: 7 | D24: 4 | E24: 13 | F24: 8 | G24: 1 | H24: 3 | I24: 16 | J24: 2 | K24: 3 | L24: 5 | M24: 4 | N24: - | O24: 2 | P24: 5 | Q24: - | R24: - | S24: 1 | T24: 2 | U24: - | V24: 2 | W24: - | X24: - | Y24: - | Z24: - | AA24: - | AB24: - | AC24: -
A25: Bière | B25: 14 | C25: 1 | D25: 3 | E25: 3 | F25: 5 | G25: 2 | H25: - | I25: 3 | J25: - | K25: 1 | L25: - | M25: 1 | N25: 1 | O25: - | P25: 2 | Q25: - | R25: - | S25: - | T25: 1 | U25: 1 | V25: - | W25: - | X25: - | Y25: - | Z25: - | AA25: - | AB25: - | AC25: -
A26: Bioley-Magnoux | B26: - | C26: - | D26: - | E26: - | F26: - | G26: - | H26: - | I26: - | J26: - | K26: - | L26: - | M26: - | N26: - | O26: - | P26: - | Q26: - | R26: - | S26: - | T26: - | U26: - | V26: - | W26: - | X26: - | Y26: - | Z26: - | AA26: - | AB26: - | AC26: -
A27: Blonay - Saint-Légier | B27: 13 | C27: - | D27: 1 | E27: - | F27: 4 | G27: 2 | H27: 6 | I27: 6 | J27: - | K27: - | L27: - | M27: 1 | N27: 1 | O27: 4 | P27: 7 | Q27: - | R27: - | S27: - | T27: - | U27: 1 | V27: 6 | W27: - | X27: - | Y27: - | Z27: - | AA27: - | AB27: - | AC27: -
A28: Bofflens | B28: - | C28: - | D28: - | E28: - | F28: - | G28: - | H28: - | I28: - | J28: - | K28: - | L28: - | M28: - | N28: - | O28: - | P28: - | Q28: - | R28: - | S28: - | T28: - | U28: - | V28: - | W28: - | X28: - | Y28: - | Z28: - | AA28: - | AB28: - | AC28: -
A29: Bogis-Bossey | B29: - | C29: - | D29: - | E29: - | F29: - | G29: - | H29: - | I29: - | J29: - | K29: - | L29: - | M29: - | N29: - | O29: - | P29: - | Q29: - | R29: - | S29: - | T29: - | U29: - | V29: - | W29: - | X29: - | Y29: - | Z29: - | AA29: - | AB29: - | AC29: -
A30: Bonvillars | B30: - | C30: - | D30: - | E30: - | F30: - | G30: - | H30: - | I30: - | J30: - | K30: - | L30: - | M30: - | N30: - | O30: - | P30: - | Q30: - | R30: - | S30: - | T30: - | U30: - | V30: - | W30: - | X30: - | Y30: - | Z30: - | AA30: - | AB30: - | AC30: -
A31: Borex | B31: 19 | C31: 4 | D31: 2 | E31: 1 | F31: 5 | G31: 2 | H31: 5 | I31: 6 | J31: - | K31: - | L31: - | M31: - | N31: 1 | O31: 5 | P31: 5 | Q31: - | R31: - | S31: - | T31: - | U31: 1 | V31: 4 | W31: - | X31: - | Y31: - | Z31: - | AA31: - | AB31: - | AC31: -
A32: Bottens | B32: 26 | C32: 4 | D32: 4 | E32: 1 | F32: 10 | G32: 5 | H32: 2 | I32: 2 | J32: - | K32: - | L32: - | M32: 2 | N32: - | O32: - | P32: - | Q32: - | R32: - | S32: - | T32: - | U32: - | V32: - | W32: - | X32: - | Y32: - | Z32: - | AA32: - | AB32: - | AC32: -
A33: Bougy-Villars | B33: 23 | C33: - | D33: 1 | E33: 2 | F33: 1 | G33: 1 | H33: 18 | I33: 15 | J33: - | K33: 1 | L33: - | M33: - | N33: - | O33: 14 | P33: 19 | Q33: - | R33: 1 | S33: - | T33: - | U33: 1 | V33: 17 | W33: - | X33: - | Y33: - | Z33: - | AA33: - | AB33: - | AC33: -
A34: Boulens | B34: - | C34: - | D34: - | E34: - | F34: - | G34: - | H34: - | I34: - | J34: - | K34: - | L34: - | M34: - | N34: - | O34: - | P34: - | Q34: - | R34: - | S34: - | T34: - | U34: - | V34: - | W34: - | X34: - | Y34: - | Z34: - | AA34: - | AB34: - | AC34: -
A35: Bourg-en-Lavaux | B35: 7 | C35: - | D35: 2 | E35: 1 | F35: 1 | G35: 1 | H35: 2 | I35: - | J35: - | K35: - | L35: - | M35: - | N35: - | O35: - | P35: 2 | Q35: - | R35: 1 | S35: - | T35: 1 | U35: - | V35: - | W35: - | X35: - | Y35: - | Z35: - | AA35: - | AB35: - | AC35: -
A36: Bournens | B36: 2 | C36: - | D36: - | E36: 1 | F36: - | G36: 1 | H36: - | I36: - | J36: - | K36: - | L36: - | M36: - | N36: - | O36: - | P36: 1 | Q36: - | R36: - | S36: - | T36: - | U36: 1 | V36: - | W36: - | X36: - | Y36: - | Z36: - | AA36: - | AB36: - | AC36: -
A37: Boussens | B37: 3 | C37: - | D37: 1 | E37: - | F37: 1 | G37: 1 | H37: - | I37: 1 | J37: - | K37: - | L37: - | M37: 1 | N37: - | O37: - | P37: - | Q37: - | R37: - | S37: - | T37: - | U37: - | V37: - | W37: - | X37: - | Y37: - | Z37: - | AA37: - | AB37: - | AC37: -
A38: Bremblens | B38: 1 | C38: - | D38: - | E38: - | F38: 1 | G38: - | H38: - | I38: - | J38: - | K38: - | L38: - | M38: - | N38: - | O38: - | P38: - | Q38: - | R38: - | S38: - | T38: - | U38: - | V38: - | W38: - | X38: - | Y38: - | Z38: - | AA38: - | AB38: - | AC38: -
A39: Bretigny-sur-Morrens | B39: 14 | C39: - | D39: 6 | E39: 5 | F39: 3 | G39: - | H39: - | I39: - | J39: - | K39: - | L39: - | M39: - | N39: - | O39: - | P39: - | Q39: - | R39: - | S39: - | T39: - | U39: - | V39: - | W39: - | X39: - | Y39: - | Z39: - | AA39: - | AB39: - | AC39: -
A40: Bretonnières | B40: - | C40: - | D40: - | E40: - | F40: - | G40: - | H40: - | I40: - | J40: - | K40: - | L40: - | M40: - | N40: - | O40: - | P40: - | Q40: - | R40: - | S40: - | T40: - | U40: - | V40: - | W40: - | X40: - | Y40: - | Z40: - | AA40: - | AB40: - | AC40: -
A41: Broye-Vully (district) | B41: 282 | C41: 12 | D41: 51 | E41: 70 | F41: 73 | G41: 53 | H41: 23 | I41: 68 | J41: 1 | K41: 1 | L41: 12 | M41: 16 | N41: 23 | O41: 15 | P41: 87 | Q41: - | R41: 3 | S41: 16 | T41: 24 | U41: 28 | V41: 16 | W41: 39 | X41: - | Y41: 7 | Z41: 13 | AA41: 10 | AB41: 9 | AC41: -
A42: Buchillon | B42: 15 | C42: - | D42: 1 | E42: 4 | F42: 2 | G42: 2 | H42: 6 | I42: 8 | J42: - | K42: - | L42: 3 | M42: 1 | N42: 1 | O42: 3 | P42: 12 | Q42: - | R42: - | S42: 3 | T42: 2 | U42: 1 | V42: 6 | W42: - | X42: - | Y42: - | Z42: - | AA42: - | AB42: - | AC42: -
A43: Bullet | B43: 2 | C43: - | D43: - | E43: - | F43: 1 | G43: 1 | H43: - | I43: 1 | J43: - | K43: - | L43: - | M43: - | N43: 1 | O43: - | P43: 1 | Q43: - | R43: - | S43: - | T43: - | U43: 1 | V43: - | W43: - | X43: - | Y43: - | Z43: - | AA43: - | AB43: - | AC43: -
A44: Bursinel | B44: 6 | C44: - | D44: 1 | E44: 4 | F44: 1 | G44: - | H44: - | I44: 3 | J44: - | K44: - | L44: 3 | M44: - | N44: - | O44: - | P44: - | Q44: - | R44: - | S44: - | T44: - | U44: - | V44: - | W44: - | X44: - | Y44: - | Z44: - | AA44: - | AB44: - | AC44: -
A45: Bursins | B45: 3 | C45: - | D45: - | E45: - | F45: 2 | G45: 1 | H45: - | I45: 3 | J45: - | K45: - | L45: - | M45: 2 | N45: 1 | O45: - | P45: 2 | Q45: - | R45: - | S45: - | T45: 1 | U45: 1 | V45: - | W45: 1 | X45: - | Y45: - | Z45: - | AA45: 1 | AB45: - | AC45: -
A46: Burtigny | B46: 2 | C46: - | D46: - | E46: - | F46: - | G46: - | H46: 2 | I46: 2 | J46: - | K46: - | L46: - | M46: - | N46: - | O46: 2 | P46: 2 | Q46: - | R46: - | S46: - | T46: - | U46: - | V46: 2 | W46: - | X46: - | Y46: - | Z46: - | AA46: - | AB46: - | AC46: -
A47: Bussigny | B47: 17 | C47: 4 | D47: 5 | E47: 7 | F47: 1 | G47: - | H47: - | I47: 2 | J47: - | K47: 1 | L47: - | M47: 1 | N47: - | O47: - | P47: - | Q47: - | R47: - | S47: - | T47: - | U47: - | V47: - | W47: - | X47: - | Y47: - | Z47: - | AA47: - | AB47: - | AC47: -
A48: Bussy-sur-Moudon | B48: - | C48: - | D48: - | E48: - | F48: - | G48: - | H48: - | I48: - | J48: - | K48: - | L48: - | M48: - | N48: - | O48: - | P48: - | Q48: - | R48: - | S48: - | T48: - | U48: - | V48: - | W48: - | X48: - | Y48: - | Z48: - | AA48: - | AB48: - | AC48: -
A49: Chamblon | B49: - | C49: - | D49: - | E49: - | F49: - | G49: - | H49: - | I49: - | J49: - | K49: - | L49: - | M49: - | N49: - | O49: - | P49: - | Q49: - | R49: - | S49: - | T49: - | U49: - | V49: - | W49: - | X49: - | Y49: - | Z49: - | AA49: - | AB49: - | AC49: -
A50: Champagne | B50: 11 | C50: - | D50: 1 | E50: 4 | F50: 2 | G50: - | H50: 4 | I50: 6 | J50: - | K50: - | L50: 2 | M50: 2 | N50: - | O50: 2 | P50: 3 | Q50: - | R50: - | S50: - | T50: - | U50: - | V50: 3 | W50: 3 | X50: - | Y50: - | Z50: 3 | AA50: - | AB50: - | AC50: -
A51: Champtauroz | B51: - | C51: - | D51: - | E51: - | F51: - | G51: - | H51: - | I51: - | J51: - | K51: - | L51: - | M51: - | N51: - | O51: - | P51: - | Q51: - | R51: - | S51: - | T51: - | U51: - | V51: - | W51: - | X51: - | Y51: - | Z51: - | AA51: - | AB51: - | AC51: -
A52: Champvent | B52: - | C52: - | D52: - | E52: - | F52: - | G52: - | H52: - | I52: - | J52: - | K52: - | L52: - | M52: - | N52: - | O52: - | P52: - | Q52: - | R52: - | S52: - | T52: - | U52: - | V52: - | W52: - | X52: - | Y52: - | Z52: - | AA52: - | AB52: - | AC52: -
A53: Chardonne | B53: 35 | C53: - | D53: 2 | E53: 11 | F53: 7 | G53: 9 | H53: 6 | I53: 19 | J53: - | K53: 2 | L53: 5 | M53: 5 | N53: 4 | O53: 3 | P53: 13 | Q53: - | R53: - | S53: 2 | T53: 4 | U53: 2 | V53: 5 | W53: 2 | X53: - | Y53: - | Z53: - | AA53: - | AB53: 2 | AC53: -
A54: Château-d'Oex | B54: 36 | C54: 1 | D54: 2 | E54: 6 | F54: 12 | G54: 6 | H54: 9 | I54: 34 | J54: - | K54: 2 | L54: 6 | M54: 11 | N54: 6 | O54: 9 | P54: 11 | Q54: - | R54: - | S54: - | T54: 2 | U54: 1 | V54: 8 | W54: - | X54: - | Y54: - | Z54: - | AA54: - | AB54: - | AC54: -
A55: Chavannes-de-Bogis | B55: 5 | C55: - | D55: - | E55: - | F55: 2 | G55: 1 | H55: 2 | I55: 4 | J55: - | K55: - | L55: - | M55: 1 | N55: 1 | O55: 2 | P55: 3 | Q55: - | R55: - | S55: - | T55: - | U55: 1 | V55: 2 | W55: - | X55: - | Y55: - | Z55: - | AA55: - | AB55: - | AC55: -
A56: Chavannes-des-Bois | B56: 1 | C56: - | D56: - | E56: - | F56: - | G56: - | H56: 1 | I56: 1 | J56: - | K56: - | L56: - | M56: - | N56: - | O56: 1 | P56: 1 | Q56: - | R56: - | S56: - | T56: - | U56: - | V56: 1 | W56: - | X56: - | Y56: - | Z56: - | AA56: - | AB56: - | AC56: -
A57: Chavannes-le-Chêne | B57: - | C57: - | D57: - | E57: - | F57: - | G57: - | H57: - | I57: - | J57: - | K57: - | L57: - | M57: - | N57: - | O57: - | P57: - | Q57: - | R57: - | S57: - | T57: - | U57: - | V57: - | W57: - | X57: - | Y57: - | Z57: - | AA57: - | AB57: - | AC57: -
A58: Chavannes-le-Veyron | B58: - | C58: - | D58: - | E58: - | F58: - | G58: - | H58: - | I58: - | J58: - | K58: - | L58: - | M58: - | N58: - | O58: - | P58: - | Q58: - | R58: - | S58: - | T58: - | U58: - | V58: - | W58: - | X58: - | Y58: - | Z58: - | AA58: - | AB58: - | AC58: -
A59: Chavannes-près-Renens | B59: 7 | C59: 4 | D59: 1 | E59: 2 | F59: - | G59: - | H59: - | I59: - | J59: - | K59: - | L59: - | M59: - | N59: - | O59: - | P59: - | Q59: - | R59: - | S59: - | T59: - | U59: - | V59: - | W59: - | X59: - | Y59: - | Z59: - | AA59: - | AB59: - | AC59: -
A60: Chavannes-sur-Moudon | B60: 1 | C60: - | D60: 1 | E60: - | F60: - | G60: - | H60: - | I60: - | J60: - | K60: - | L60: - | M60: - | N60: - | O60: - | P60: - | Q60: - | R60: - | S60: - | T60: - | U60: - | V60: - | W60: - | X60: - | Y60: - | Z60: - | AA60: - | AB60: - | AC60: -
A61: Chavornay | B61: 7 | C61: - | D61: 3 | E61: 3 | F61: - | G61: - | H61: 1 | I61: 1 | J61: - | K61: - | L61: - | M61: - | N61: - | O61: 1 | P61: 1 | Q61: - | R61: - | S61: - | T61: - | U61: - | V61: 1 | W61: - | X61: - | Y61: - | Z61: - | AA61: - | AB61: - | AC61: -
A62: Chêne-Pâquier | B62: - | C62: - | D62: - | E62: - | F62: - | G62: - | H62: - | I62: - | J62: - | K62: - | L62: - | M62: - | N62: - | O62: - | P62: - | Q62: - | R62: - | S62: - | T62: - | U62: - | V62: - | W62: - | X62: - | Y62: - | Z62: - | AA62: - | AB62: - | AC62: -
A63: Cheseaux-Noréaz | B63: 2 | C63: - | D63: - | E63: - | F63: 2 | G63: - | H63: - | I63: 2 | J63: - | K63: - | L63: - | M63: 2 | N63: - | O63: - | P63: 2 | Q63: - | R63: - | S63: - | T63: 2 | U63: - | V63: - | W63: - | X63: - | Y63: - | Z63: - | AA63: - | AB63: - | AC63: -
A64: Cheseaux-sur-Lausanne | B64: 8 | C64: - | D64: - | E64: 2 | F64: 4 | G64: 1 | H64: 1 | I64: - | J64: - | K64: - | L64: - | M64: - | N64: - | O64: - | P64: 2 | Q64: - | R64: - | S64: - | T64: 1 | U64: - | V64: 1 | W64: 1 | X64: - | Y64: - | Z64: - | AA64: 1 | AB64: - | AC64: -
A65: Chéserex | B65: 5 | C65: - | D65: - | E65: - | F65: 2 | G65: 2 | H65: 1 | I65: 3 | J65: - | K65: - | L65: - | M65: - | N65: 2 | O65: 1 | P65: 2 | Q65: - | R65: - | S65: - | T65: - | U65: 1 | V65: 1 | W65: 1 | X65: - | Y65: - | Z65: - | AA65: 1 | AB65: - | AC65: -
A66: Chessel | B66: 6 | C66: - | D66: 2 | E66: 1 | F66: 2 | G66: 1 | H66: - | I66: 2 | J66: - | K66: - | L66: 1 | M66: - | N66: 1 | O66: - | P66: 2 | Q66: - | R66: 1 | S66: - | T66: - | U66: 1 | V66: - | W66: - | X66: - | Y66: - | Z66: - | AA66: - | AB66: - | AC66: -
A67: Chevilly | B67: 8 | C67: - | D67: 3 | E67: 4 | F67: - | G67: 1 | H67: - | I67: 4 | J67: - | K67: 1 | L67: 3 | M67: - | N67: - | O67: - | P67: - | Q67: - | R67: - | S67: - | T67: - | U67: - | V67: - | W67: 5 | X67: - | Y67: 2 | Z67: 3 | AA67: - | AB67: - | AC67: -
A68: Chevroux | B68: 5 | C68: - | D68: 2 | E68: 1 | F68: 1 | G68: 1 | H68: - | I68: 1 | J68: - | K68: - | L68: - | M68: - | N68: 1 | O68: - | P68: 1 | Q68: - | R68: - | S68: - | T68: - | U68: 1 | V68: - | W68: - | X68: - | Y68: - | Z68: - | AA68: - | AB68: - | AC68: -
A69: Chexbres | B69: 8 | C69: 3 | D69: 2 | E69: 2 | F69: 1 | G69: - | H69: - | I69: - | J69: - | K69: - | L69: - | M69: - | N69: - | O69: - | P69: - | Q69: - | R69: - | S69: - | T69: - | U69: - | V69: - | W69: - | X69: - | Y69: - | Z69: - | AA69: - | AB69: - | AC69: -
A70: Chigny | B70: - | C70: - | D70: - | E70: - | F70: - | G70: - | H70: - | I70: - | J70: - | K70: - | L70: - | M70: - | N70: - | O70: - | P70: - | Q70: - | R70: - | S70: - | T70: - | U70: - | V70: - | W70: - | X70: - | Y70: - | Z70: - | AA70: - | AB70: - | AC70: -
A71: Clarmont | B71: 7 | C71: 1 | D71: 1 | E71: 3 | F71: - | G71: - | H71: 2 | I71: - | J71: - | K71: - | L71: - | M71: - | N71: - | O71: - | P71: - | Q71: - | R71: - | S71: - | T71: - | U71: - | V71: - | W71: - | X71: - | Y71: - | Z71: - | AA71: - | AB71: - | AC71: -
A72: Coinsins | B72: 1 | C72: - | D72: - | E72: - | F72: 1 | G72: - | H72: - | I72: 1 | J72: - | K72: - | L72: - | M72: 1 | N72: - | O72: - | P72: 1 | Q72: - | R72: - | S72: - | T72: 1 | U72: - | V72: - | W72: - | X72: - | Y72: - | Z72: - | AA72: - | AB72: - | AC72: -
A73: Commugny | B73: 98 | C73: 11 | D73: 16 | E73: 9 | F73: 11 | G73: 16 | H73: 35 | I73: - | J73: - | K73: - | L73: - | M73: - | N73: - | O73: - | P73: 71 | Q73: 6 | R73: 8 | S73: 4 | T73: 5 | U73: 13 | V73: 35 | W73: - | X73: - | Y73: - | Z73: - | AA73: - | AB73: - | AC73: -
A74: Concise | B74: 13 | C74: - | D74: 1 | E74: 2 | F74: 8 | G74: - | H74: 2 | I74: 10 | J74: - | K74: 1 | L74: 2 | M74: 5 | N74: - | O74: 2 | P74: 3 | Q74: - | R74: - | S74: - | T74: 1 | U74: - | V74: 2 | W74: - | X74: - | Y74: - | Z74: - | AA74: - | AB74: - | AC74: -
A75: Coppet | B75: 34 | C75: - | D75: 3 | E75: 2 | F75: 4 | G75: 4 | H75: 21 | I75: 18 | J75: - | K75: 1 | L75: - | M75: 2 | N75: 1 | O75: 14 | P75: 19 | Q75: - | R75: - | S75: - | T75: 1 | U75: 2 | V75: 16 | W75: 2 | X75: - | Y75: - | Z75: - | AA75: - | AB75: - | AC75: 2
A76: Corbeyrier | B76: 7 | C76: - | D76: 1 | E76: 1 | F76: - | G76: 5 | H76: - | I76: 2 | J76: - | K76: - | L76: - | M76: - | N76: 2 | O76: - | P76: 3 | Q76: - | R76: - | S76: - | T76: - | U76: 3 | V76: - | W76: - | X76: - | Y76: - | Z76: - | AA76: - | AB76: - | AC76: -
A77: Corcelles-le-Jorat | B77: 9 | C77: - | D77: 4 | E77: 3 | F77: - | G77: 2 | H77: - | I77: 3 | J77: - | K77: - | L77: 1 | M77: - | N77: 2 | O77: - | P77: 2 | Q77: - | R77: - | S77: - | T77: - | U77: 2 | V77: - | W77: - | X77: - | Y77: - | Z77: - | AA77: - | AB77: - | AC77: -
A78: Corcelles-près-Concise | B78: 2 | C78: - | D78: - | E78: 1 | F78: 1 | G78: - | H78: - | I78: - | J78: - | K78: - | L78: - | M78: - | N78: - | O78: - | P78: - | Q78: - | R78: - | S78: - | T78: - | U78: - | V78: - | W78: - | X78: - | Y78: - | Z78: - | AA78: - | AB78: - | AC78: -
A79: Corcelles-près-Payerne | B79: 21 | C79: 1 | D79: 9 | E79: 7 | F79: 2 | G79: 1 | H79: 1 | I79: 2 | J79: - | K79: - | L79: 2 | M79: - | N79: - | O79: - | P79: - | Q79: - | R79: - | S79: - | T79: - | U79: - | V79: - | W79: 12 | X79: - | Y79: 6 | Z79: 4 | AA79: 2 | AB79: - | AC79: -
A80: Corseaux | B80: 27 | C80: 1 | D80: 5 | E80: 8 | F80: 7 | G80: 4 | H80: 2 | I80: 10 | J80: - | K80: 2 | L80: 2 | M80: 3 | N80: 3 | O80: - | P80: 4 | Q80: - | R80: - | S80: - | T80: 2 | U80: 2 | V80: - | W80: - | X80: - | Y80: - | Z80: - | AA80: - | AB80: - | AC80: -
A81: Corsier-sur-Vevey | B81: 12 | C81: - | D81: 5 | E81: 3 | F81: - | G81: 2 | H81: 2 | I81: - | J81: - | K81: - | L81: - | M81: - | N81: - | O81: - | P81: - | Q81: - | R81: - | S81: - | T81: - | U81: - | V81: - | W81: - | X81: - | Y81: - | Z81: - | AA81: - | AB81: - | AC81: -
A82: Cossonay | B82: 9 | C82: - | D82: 3 | E82: 4 | F82: 1 | G82: 1 | H82: - | I82: 4 | J82: - | K82: 2 | L82: 1 | M82: - | N82: 1 | O82: - | P82: - | Q82: - | R82: - | S82: - | T82: - | U82: - | V82: - | W82: - | X82: - | Y82: - | Z82: - | AA82: - | AB82: - | AC82: -
A83: Crans | B83: 9 | C83: - | D83: 1 | E83: - | F83: 4 | G83: 1 | H83: 3 | I83: 5 | J83: - | K83: - | L83: - | M83: 2 | N83: - | O83: 3 | P83: 6 | Q83: - | R83: - | S83: - | T83: 2 | U83: 1 | V83: 3 | W83: 1 | X83: - | Y83: - | Z83: - | AA83: - | AB83: - | AC83: 1
A84: Crassier | B84: 22 | C84: 1 | D84: 1 | E84: 5 | F84: 6 | G84: 6 | H84: 3 | I84: 3 | J84: - | K84: - | L84: - | M84: - | N84: 1 | O84: 2 | P84: 2 | Q84: - | R84: - | S84: - | T84: - | U84: - | V84: 2 | W84: - | X84: - | Y84: - | Z84: - | AA84: - | AB84: - | AC84: -
A85: Crissier | B85: 31 | C85: 4 | D85: 4 | E85: 9 | F85: 6 | G85: 8 | H85: - | I85: 9 | J85: - | K85: - | L85: 1 | M85: 1 | N85: 7 | O85: - | P85: 8 | Q85: - | R85: - | S85: - | T85: 2 | U85: 6 | V85: - | W85: 14 | X85: 2 | Y85: - | Z85: 8 | AA85: 4 | AB85: - | AC85: -
A86: Cronay | B86: - | C86: - | D86: - | E86: - | F86: - | G86: - | H86: - | I86: - | J86: - | K86: - | L86: - | M86: - | N86: - | O86: - | P86: - | Q86: - | R86: - | S86: - | T86: - | U86: - | V86: - | W86: - | X86: - | Y86: - | Z86: - | AA86: - | AB86: - | AC86: -
A87: Croy | B87: 12 | C87: 3 | D87: 3 | E87: 2 | F87: 3 | G87: 1 | H87: - | I87: - | J87: - | K87: - | L87: - | M87: - | N87: - | O87: - | P87: - | Q87: - | R87: - | S87: - | T87: - | U87: - | V87: - | W87: - | X87: - | Y87: - | Z87: - | AA87: - | AB87: - | AC87: -
A88: Cuarnens | B88: 3 | C88: - | D88: - | E88: 2 | F88: - | G88: 1 | H88: - | I88: - | J88: - | K88: - | L88: - | M88: - | N88: - | O88: - | P88: - | Q88: - | R88: - | S88: - | T88: - | U88: - | V88: - | W88: - | X88: - | Y88: - | Z88: - | AA88: - | AB88: - | AC88: -
A89: Cuarny | B89: - | C89: - | D89: - | E89: - | F89: - | G89: - | H89: - | I89: - | J89: - | K89: - | L89: - | M89: - | N89: - | O89: - | P89: - | Q89: - | R89: - | S89: - | T89: - | U89: - | V89: - | W89: - | X89: - | Y89: - | Z89: - | AA89: - | AB89: - | AC89: -
A90: Cudrefin | B90: 11 | C90: - | D90: 1 | E90: 4 | F90: 3 | G90: 3 | H90: - | I90: 3 | J90: - | K90: - | L90: - | M90: 1 | N90: 2 | O90: - | P90: 2 | Q90: - | R90: - | S90: - | T90: - | U90: 2 | V90: - | W90: - | X90: - | Y90: - | Z90: - | AA90: - | AB90: - | AC90: -
A91: Cugy | B91: 2 | C91: - | D91: 2 | E91: - | F91: - | G91: - | H91: - | I91: - | J91: - | K91: - | L91: - | M91: - | N91: - | O91: - | P91: - | Q91: - | R91: - | S91: - | T91: - | U91: - | V91: - | W91: - | X91: - | Y91: - | Z91: - | AA91: - | AB91: - | AC91: -
A92: Curtilles | B92: 6 | C92: 1 | D92: 2 | E92: 1 | F92: - | G92: 1 | H92: 1 | I92: 2 | J92: - | K92: - | L92: - | M92: - | N92: 1 | O92: 1 | P92: 4 | Q92: - | R92: 1 | S92: 1 | T92: - | U92: 1 | V92: 1 | W92: - | X92: - | Y92: - | Z92: - | AA92: - | AB92: - | AC92: -
A93: Daillens | B93: 10 | C93: 3 | D93: 2 | E93: 3 | F93: - | G93: 2 | H93: - | I93: - | J93: - | K93: - | L93: - | M93: - | N93: - | O93: - | P93: 1 | Q93: - | R93: - | S93: - | T93: - | U93: 1 | V93: - | W93: - | X93: - | Y93: - | Z93: - | AA93: - | AB93: - | AC93: -
A94: Démoret | B94: - | C94: - | D94: - | E94: - | F94: - | G94: - | H94: - | I94: - | J94: - | K94: - | L94: - | M94: - | N94: - | O94: - | P94: - | Q94: - | R94: - | S94: - | T94: - | U94: - | V94: - | W94: - | X94: - | Y94: - | Z94: - | AA94: - | AB94: - | AC94: -
A95: Denens | B95: 3 | C95: - | D95: - | E95: - | F95: - | G95: 3 | H95: - | I95: 3 | J95: - | K95: - | L95: - | M95: - | N95: 3 | O95: - | P95: 2 | Q95: - | R95: - | S95: - | T95: - | U95: 2 | V95: - | W95: - | X95: - | Y95: - | Z95: - | AA95: - | AB95: - | AC95: -
A96: Denges | B96: 9 | C96: - | D96: 5 | E96: 3 | F96: 1 | G96: - | H96: - | I96: 9 | J96: - | K96: 5 | L96: 3 | M96: 1 | N96: - | O96: - | P96: - | Q96: - | R96: - | S96: - | T96: - | U96: - | V96: - | W96: 9 | X96: - | Y96: 5 | Z96: 3 | AA96: 1 | AB96: - | AC96: -
A97: Dizy | B97: - | C97: - | D97: - | E97: - | F97: - | G97: - | H97: - | I97: - | J97: - | K97: - | L97: - | M97: - | N97: - | O97: - | P97: - | Q97: - | R97: - | S97: - | T97: - | U97: - | V97: - | W97: - | X97: - | Y97: - | Z97: - | AA97: - | AB97: - | AC97: -
A98: Dompierre | B98: 3 | C98: - | D98: - | E98: 1 | F98: 1 | G98: - | H98: 1 | I98: 3 | J98: - | K98: - | L98: 1 | M98: 1 | N98: - | O98: 1 | P98: 3 | Q98: - | R98: - | S98: 1 | T98: 1 | U98: - | V98: 1 | W98: - | X98: - | Y98: - | Z98: - | AA98: - | AB98: - | AC98: -
A99: Donneloye | B99: 11 | C99: - | D99: 2 | E99: - | F99: 5 | G99: 1 | H99: 3 | I99: 2 | J99: - | K99: - | L99: - | M99: - | N99: 1 | O99: 1 | P99: 3 | Q99: - | R99: - | S99: - | T99: 1 | U99: 1 | V99: 1 | W99: - | X99: - | Y99: - | Z99: - | AA99: - | AB99: - | AC99: -
A100: Duillier | B100: 9 | C100: 2 | D100: - | E100: - | F100: 3 | G100: 1 | H100: 3 | I100: 3 | J100: 1 | K100: - | L100: - | M100: - | N100: 1 | O100: 1 | P100: 5 | Q100: - | R100: - | S100: - | T100: 1 | U100: 1 | V100: 3 | W100: - | X100: - | Y100: - | Z100: - | AA100: - | AB100: - | AC100: -
...
